Workbook

Sheet Painel Manutenção
A1: Painel de manutenção periódica
A4: Total projetos | D4: Com Manuntenção Prev | G4: Com Contrato Ativo | J4: Contratos de Man Prev Expirados | M4: Contratos que acabam nos proximos 6 meses
A5: =COUNTA('Project Overview'!B:B)-1 -> 264 | D5: =COUNTIF('Project Overview'!N:N,"yes") -> 88 | G5: =COUNTIF('Project Overview'!Y:Y,"yes") -> 80 | J5: =COUNTIFS('Project Overview'!Y:Y,"no",'Project Overview'!N:N,"yes") -> 8 | M5: =COUNTIFS('Project Overview'!W:W,">="&TODAY(),'Project Overview'!W:W,"<="&EDATE(TODAY(),6)) -> 4
A9: Estado dos projetos | H9: ="Taxa de retenção: " & TEXT(I12/I13,"0%") -> Taxa de retenção: 90%
A10: Tipo de Contrato | B10: Contagem | H10: Estado de Contrato | I10: Contagem
A11: =Painel_Apoio!A5 -> EPC | B11: =Painel_Apoio!B5 -> 22 | H11: =Painel_Apoio!D5 -> no | I11: =Painel_Apoio!E5 -> 9
A12: =Painel_Apoio!A6 -> ESCO | B12: =Painel_Apoio!B6 -> 67 | H12: =Painel_Apoio!D6 -> yes | I12: =Painel_Apoio!E6 -> 80
A13: =Painel_Apoio!A7 -> Grand Total | B13: =Painel_Apoio!B7 -> 89 | H13: =Painel_Apoio!D7 -> Grand Total | I13: =Painel_Apoio!E7 -> 89
A26: Localizações com mais projetos | I26: Finalização de Contratos
A27: Principais Localizações | B27: Contagem | I27: Ano Conclusão | J27: Contagem
A28: =Painel_Apoio!J5 -> Lisboa | B28: =Painel_Apoio!K5 -> 8 | I28: =Painel_Apoio!M5 -> 2026 | J28: =Painel_Apoio!N5 -> 5
A29: =Painel_Apoio!J6 -> Leiria | B29: =Painel_Apoio!K6 -> 8 | I29: =Painel_Apoio!M6 -> 2027 | J29: =Painel_Apoio!N6 -> 8
A30: =Painel_Apoio!J7 -> Santarém | B30: =Painel_Apoio!K7 -> 7 | I30: =Painel_Apoio!M7 -> 2028 | J30: =Painel_Apoio!N7 -> 5
A31: =Painel_Apoio!J8 -> Sintra | B31: =Painel_Apoio!K8 -> 6 | I31: =Painel_Apoio!M8 -> 2029 | J31: =Painel_Apoio!N8 -> 3
A32: =Painel_Apoio!J9 -> Porto | B32: =Painel_Apoio!K9 -> 4 | I32: =Painel_Apoio!M9 -> 2032 | J32: =Painel_Apoio!N9 -> 3
A33: =Painel_Apoio!J10 -> Castelo Branco | B33: =Painel_Apoio!K10 -> 4 | I33: =Painel_Apoio!M10 -> 2033 | J33: =Painel_Apoio!N10 -> 7
A34: =Painel_Apoio!J11 -> Setúbal | B34: =Painel_Apoio!K11 -> 4 | I34: =Painel_Apoio!M11 -> 2034 | J34: =Painel_Apoio!N11 -> 3
A35: =Painel_Apoio!J12 -> Aveiro | B35: =Painel_Apoio!K12 -> 3 | I35: =Painel_Apoio!M12 -> 2035 | J35: =Painel_Apoio!N12 -> 7
A36: =Painel_Apoio!J13 -> Badajoz | B36: =Painel_Apoio!K13 -> 3 | I36: =Painel_Apoio!M13 -> 2036 | J36: =Painel_Apoio!N13 -> 10
A37: =Painel_Apoio!J14 -> São João da Madeira | B37: =Painel_Apoio!K14 -> 2 | I37: =Painel_Apoio!M14 -> 2037 | J37: =Painel_Apoio!N14 -> 5
I38: =Painel_Apoio!M15 -> 2038 | J38: =Painel_Apoio!N15 -> 16
I39: =Painel_Apoio!M16 -> 2039 | J39: =Painel_Apoio!N16 -> 5
I40: =Painel_Apoio!M17 -> 2041 | J40: =Painel_Apoio!N17 -> 2
I41: =Painel_Apoio!M18 -> 2043 | J41: =Painel_Apoio!N18 -> 1
A43: Alertas rápidos

Sheet Project Overview
A1: N° | B1: Project | C1: Company Name | D1: Nif | E1: Address | F1: Location | G1: Nº Panels | H1: Kwp | I1: Type of Contract | J1: Sell To | K1: Duration | L1: Duration Month2 | M1: Start Contract | N1: Maintenance | O1: Type of Coverage | P1: Access | Q1: Maintenance comment | R1: Status Detail | S1: Nome da Pessoa | T1: Cargo | U1: Email | V1: Telefone | W1: End Contract | X1: Year of End Contract | Y1: Active Contract | Z1: Notes | AA1: €€ | AB1: Tipo
A2: 1 | B2: A Colmeia do Minho | C2: A Colmeia do Minho, S.A., | D2: 500001022 | E2: Rua Jose Gregorio Almeida 14, Quinta da Cucena, 2840-582 Aldeia de Paio Pires Seixal | F2: Castelo Branco | G2: 220 | H2: 61.6 | I2: ESCO | J2: Solcorelios | K2: 7 | L2: =Table1[[#This Row],[Duration]]*12 -> 84 | M2: 43724 | N2: =IF(AND(Table1[[#This Row],[ Type of Contract]]="ESCO",Table1[[#This Row],[Status Detail]]="ACTIVE"),"yes","no") -> yes | O2: Sandwich | P2: Cobertura | R2: ACTIVE | S2: António Diogo Jacinto | T2: Presidente do Conselho de Administragdo | U2: pjacinto@acolmeiadominho.com.pt / geral@acolmeiadominho.com .pt | V2: 212279020 | W2: =IF(Table1[[#This Row],[Maintenance]]="yes",IF(OR(Table1[[#This Row],[Start Contract]]="",Table1[[#This Row],[Duration Month2]]=""),"",EDATE(Table1[[#This Row],[Start Contract]],Table1[[#This Row],[Duration Month2]])),"-") -> 46281 | X2: =IF(OR((W2=""),(W2="-")),"",YEAR(Table1[[#This Row],[End Contract]])) -> 2026 | Y2: =IF(Table1[[#This Row],[Maintenance]]="yes",IF(Table1[[#This Row],[End Contract]]="","no",IF(TODAY()<=Table1[[#This Row],[End Contract]],"yes","no")),"no") -> yes | AA2: - | AB2: Tarifa
A3: 2 | B3: Florineve | C3: Florineve - Produção e Comércio de Flores de Corte | D3: 510912974 | E3: Estr. do Seixalinho, 2870-491 Montijo | F3: Setúbal | G3: 272 | H3: 89.8 | I3: ESCO | J3: Solcorelios | K3: 15 | L3: =Table1[[#This Row],[Duration]]*12 -> 180 | M3: 43803 | N3: =IF(AND(Table1[[#This Row],[ Type of Contract]]="ESCO",Table1[[#This Row],[Status Detail]]="ACTIVE"),"yes","no") -> yes | O3: Sandwich | P3: Escada | R3: ACTIVE | S3: Victor Manuel de Amaral Araújo Abreu | T3: Sócio-gerente | U3: victor.araujo@florineve.pt / geral@florineve.pt | V3: 917275304 | W3: =IF(Table1[[#This Row],[Maintenance]]="yes",IF(OR(Table1[[#This Row],[Start Contract]]="",Table1[[#This Row],[Duration Month2]]=""),"",EDATE(Table1[[#This Row],[Start Contract]],Table1[[#This Row],[Duration Month2]])),"-") -> 49282 | X3: =IF(OR((W3=""),(W3="-")),"",YEAR(Table1[[#This Row],[End Contract]])) -> 2034 | Y3: =IF(Table1[[#This Row],[Maintenance]]="yes",IF(Table1[[#This Row],[End Contract]]="","no",IF(TODAY()<=Table1[[#This Row],[End Contract]],"yes","no")),"no") -> yes | AA3: - | AB3: Tarifa
A4: 3 | B4: Dialogos do Bosque | C4: Diálogos do Bosque, Unipessoal, LDA | D4: 510731570 | E4: Herdade dos Catos - Gralheira CCI 1304, 7050-636 Cortiçadas de Lavre | F4: Évora | G4: 90 | H4: 29.7 | I4: ESCO | J4: Solcorelios | K4: 15 | L4: =Table1[[#This Row],[Duration]]*12 -> 180 | M4: 43831 | N4: =IF(AND(Table1[[#This Row],[ Type of Contract]]="ESCO",Table1[[#This Row],[Status Detail]]="ACTIVE"),"yes","no") -> yes | O4: Sandwich | P4: Escada | R4: ACTIVE | T4: Gerente | U4: nuno.pires@dialogosdobosque.pt / info@dialogosdobosque.pt | V4: 938654762 / 917285177 | W4: =IF(Table1[[#This Row],[Maintenance]]="yes",IF(OR(Table1[[#This Row],[Start Contract]]="",Table1[[#This Row],[Duration Month2]]=""),"",EDATE(Table1[[#This Row],[Start Contract]],Table1[[#This Row],[Duration Month2]])),"-") -> 49310 | X4: =IF(OR((W4=""),(W4="-")),"",YEAR(Table1[[#This Row],[End Contract]])) -> 2035 | Y4: =IF(Table1[[#This Row],[Maintenance]]="yes",IF(Table1[[#This Row],[End Contract]]="","no",IF(TODAY()<=Table1[[#This Row],[End Contract]],"yes","no")),"no") -> yes | AA4: - | AB4: Tarifa
A5: 4 | B5: Presuntos Lourenço 2 | C5: A. Pires Lourenço & Filhos S.A | D5: 502265906 | E5: Rua do Outeiro 154, Cebolais de Cima, Castelo Branco, Portugal | F5: Castelo Branco | G5: 684 | H5: 307.8 | I5: EPC | J5: Cliente | K5: 2 | L5: =Table1[[#This Row],[Duration]]*12 -> 24 | M5: 45474 | N5: yes | O5: Sandwich | P5: Escada Vertical | Q5: To discuss with the client | R5: ACTIVE | S5: Vítor Manuel Rodrigues Lourenço | T5: Gerente | U5: apireslourenco@apireslourenco.pt / mario@apireslourenco.pt / victor@apireslourenco.pt | V5: 962546961 | W5: =IF(Table1[[#This Row],[Maintenance]]="yes",IF(OR(Table1[[#This Row],[Start Contract]]="",Table1[[#This Row],[Duration Month2]]=""),"",EDATE(Table1[[#This Row],[Start Contract]],Table1[[#This Row],[Duration Month2]])),"-") -> 46204 | X5: =IF(OR((W5=""),(W5="-")),"",YEAR(Table1[[#This Row],[End Contract]])) -> 2026 | Y5: =IF(Table1[[#This Row],[Maintenance]]="yes",IF(Table1[[#This Row],[End Contract]]="","no",IF(TODAY()<=Table1[[#This Row],[End Contract]],"yes","no")),"no") -> yes | Z5: Missing contract duration (EPC) | AA5: 1750 | AB5: O&M
A6: 4 | B6: Pires Lourenço 1 | C6: A. Pires Lourenço & Filhos S.A | D6: 502265906 | E6: Empresarial Rua I - Lote 129, Apartado 1142 6001-901 Castelo Branco | F6: Castelo Branco | G6: 648 | H6: 243 | I6: ESCO | J6: Solcorelios | K6: 8 | L6: =Table1[[#This Row],[Duration]]*12 -> 96 | M6: 44013 | N6: =IF(AND(Table1[[#This Row],[ Type of Contract]]="ESCO",Table1[[#This Row],[Status Detail]]="ACTIVE"),"yes","no") -> yes | O6: Sandwich | P6: Cobertura | R6: ACTIVE | S6: Vítor Manuel Rodrigues Lourenço | T6: Gerente | U6: apireslourenco@apireslourenco.pt / mario@apireslourenco.pt / victor@apireslourenco.pt | V6: 272989489 | W6: =IF(Table1[[#This Row],[Maintenance]]="yes",IF(OR(Table1[[#This Row],[Start Contract]]="",Table1[[#This Row],[Duration Month2]]=""),"",EDATE(Table1[[#This Row],[Start Contract]],Table1[[#This Row],[Duration Month2]])),"-") -> 46935 | X6: =IF(OR((W6=""),(W6="-")),"",YEAR(Table1[[#This Row],[End Contract]])) -> 2028 | Y6: =IF(Table1[[#This Row],[Maintenance]]="yes",IF(Table1[[#This Row],[End Contract]]="","no",IF(TODAY()<=Table1[[#This Row],[End Contract]],"yes","no")),"no") -> yes | AA6: - | AB6: Tarifa
A7: 5 | B7: Usinage | C7: Usinage - Maquinação e Porta Moldes, Lda | D7: 505435748 | E7: Estrada Nacional 356, n.º 87, Maceirinha, 2405-026 Maceira LRA | F7: Leiria | G7: 360 | H7: 138.6 | I7: ESCO BUYOUT | J7: Solcorelios | K7: 15 | L7: =Table1[[#This Row],[Duration]]*12 -> 180 | M7: 44136 | N7: =IF(AND(Table1[[#This Row],[ Type of Contract]]="ESCO",Table1[[#This Row],[Status Detail]]="ACTIVE"),"yes","no") -> no | O7: Sandwich | P7: Escada | R7: ACTIVE | S7: Pedro Miguel da Silva Rodrigues | T7: Gerente | U7: comercial@usinage.pt / geral@usinage.pt | V7: 917569054 | W7: =IF(Table1[[#This Row],[Maintenance]]="yes",IF(OR(Table1[[#This Row],[Start Contract]]="",Table1[[#This Row],[Duration Month2]]=""),"",EDATE(Table1[[#This Row],[Start Contract]],Table1[[#This Row],[Duration Month2]])),"-") -> - | X7: =IF(OR((W7=""),(W7="-")),"",YEAR(Table1[[#This Row],[End Contract]])) | Y7: =IF(Table1[[#This Row],[Maintenance]]="yes",IF(Table1[[#This Row],[End Contract]]="","no",IF(TODAY()<=Table1[[#This Row],[End Contract]],"yes","no")),"no") -> no
A8: 6 | B8: Museu Caramulo | C8: Fundação Abel e João de Lacerda | D8: 500792640 | E8: Museu do Caramulo 3475-031 Caramulo | F8: Tondela | G8: 68 | H8: 26.18 | I8: ESCO | J8: Solcorelios | K8: =84/12 -> 7 | L8: =Table1[[#This Row],[Duration]]*12 -> 84 | M8: 44105 | N8: =IF(AND(Table1[[#This Row],[ Type of Contract]]="ESCO",Table1[[#This Row],[Status Detail]]="ACTIVE"),"yes","no") -> yes | O8: Telha | P8: Escada | R8: ACTIVE | S8: Tiago Patricio Lacerda pinto Basto Gouveia | T8: Vogal da Direção/Diretor Delegado | U8: tiago.gouveia@museu-caramulo.net / salvador.gouveia@museudocaramulo.pt | V8: 232861270 | W8: =IF(Table1[[#This Row],[Maintenance]]="yes",IF(OR(Table1[[#This Row],[Start Contract]]="",Table1[[#This Row],[Duration Month2]]=""),"",EDATE(Table1[[#This Row],[Start Contract]],Table1[[#This Row],[Duration Month2]])),"-") -> 46661 | X8: =IF(OR((W8=""),(W8="-")),"",YEAR(Table1[[#This Row],[End Contract]])) -> 2027 | Y8: =IF(Table1[[#This Row],[Maintenance]]="yes",IF(Table1[[#This Row],[End Contract]]="","no",IF(TODAY()<=Table1[[#This Row],[End Contract]],"yes","no")),"no") -> yes | AA8: - | AB8: Tarifa
A9: 7 | B9: Confrontar Sabores | C9: Confrontan Sabores, Lda | D9: 509891500 | E9: Zona Industrial de Albergaria-A-Velha, Arruamento H, Lote 4 3850-184 Albergaria-A-Velha | H9: 45 | I9: ESCO | J9: Solcorelios | K9: 15 | L9: =Table1[[#This Row],[Duration]]*12 -> 180 | N9: =IF(AND(Table1[[#This Row],[ Type of Contract]]="ESCO",Table1[[#This Row],[Status Detail]]="ACTIVE"),"yes","no") -> no | R9: CANCELLED | S9: António da Rocha Martins | T9: Gerente | W9: =IF(Table1[[#This Row],[Maintenance]]="yes",IF(OR(Table1[[#This Row],[Start Contract]]="",Table1[[#This Row],[Duration Month2]]=""),"",EDATE(Table1[[#This Row],[Start Contract]],Table1[[#This Row],[Duration Month2]])),"-") -> - | X9: =IF(OR((W9=""),(W9="-")),"",YEAR(Table1[[#This Row],[End Contract]])) | Y9: =IF(Table1[[#This Row],[Maintenance]]="yes",IF(Table1[[#This Row],[End Contract]]="","no",IF(TODAY()<=Table1[[#This Row],[End Contract]],"yes","no")),"no") -> no
A10: 8 | B10: Marmores da Granja | C10: Marmores da Granja Lda | D10: 501754679 | E10: Av. da Aviação Portuguesa 82 - Lameiras 2715-776 Terrugem Snt | F10: Sintra | G10: 360 | H10: 138.6 | I10: ESCO | J10: Solcorelios | K10: 15 | L10: =Table1[[#This Row],[Duration]]*12 -> 180 | M10: 44228 | N10: =IF(AND(Table1[[#This Row],[ Type of Contract]]="ESCO",Table1[[#This Row],[Status Detail]]="ACTIVE"),"yes","no") -> yes | O10: Sandwich | P10: Escada | R10: ACTIVE | S10: Eugénia Maria Nunes Marcelino Firmino / Américo Manuel Ventura Firmino | T10: Sócio-gerente | U10: eugenia@marmoresgranja.pt / granja@marmoresgranja.pt | V10: 968064212/966475439 | W10: =IF(Table1[[#This Row],[Maintenance]]="yes",IF(OR(Table1[[#This Row],[Start Contract]]="",Table1[[#This Row],[Duration Month2]]=""),"",EDATE(Table1[[#This Row],[Start Contract]],Table1[[#This Row],[Duration Month2]])),"-") -> 49706 | X10: =IF(OR((W10=""),(W10="-")),"",YEAR(Table1[[#This Row],[End Contract]])) -> 2036 | Y10: =IF(Table1[[#This Row],[Maintenance]]="yes",IF(Table1[[#This Row],[End Contract]]="","no",IF(TODAY()<=Table1[[#This Row],[End Contract]],"yes","no")),"no") -> yes | AA10: - | AB10: Tarifa
A11: 9 | B11: Lands Hause - Pataias | C11: Ah Pinhal do Rei, Lda | D11: 514968044 | E11: 2445-045 Pataias | F11: Leiria | G11: 68 | H11: 26.86 | I11: ESCO BUYOUT | J11: Solcorelios | K11: 8 | L11: =Table1[[#This Row],[Duration]]*12 -> 96 | M11: 44287 | N11: =IF(AND(Table1[[#This Row],[ Type of Contract]]="ESCO",Table1[[#This Row],[Status Detail]]="ACTIVE"),"yes","no") -> no | O11: Sandwich | P11: Escada | R11: ACTIVE | S11: Manuel Joaquim de Oliveira Brites | T11: Gerente | U11: mblello@hotmail.com | V11: 912378796 | W11: =IF(Table1[[#This Row],[Maintenance]]="yes",IF(OR(Table1[[#This Row],[Start Contract]]="",Table1[[#This Row],[Duration Month2]]=""),"",EDATE(Table1[[#This Row],[Start Contract]],Table1[[#This Row],[Duration Month2]])),"-") -> - | X11: =IF(OR((W11=""),(W11="-")),"",YEAR(Table1[[#This Row],[End Contract]])) | Y11: =IF(Table1[[#This Row],[Maintenance]]="yes",IF(Table1[[#This Row],[End Contract]]="","no",IF(TODAY()<=Table1[[#This Row],[End Contract]],"yes","no")),"no") -> no
A12: 10 | B12: Lusobatata | C12: Lusobatata- Produtos de lV Gama, LDA | D12: 503722170 | E12: Av, Sra. Da Lapa, N84, Barreiralva, 2640416 Mafra | F12: Mafra | G12: 158 | H12: 59.25 | I12: ESCO | J12: Solcorelios | K12: 7 | L12: =Table1[[#This Row],[Duration]]*12 -> 84 | M12: 44348 | N12: =IF(AND(Table1[[#This Row],[ Type of Contract]]="ESCO",Table1[[#This Row],[Status Detail]]="ACTIVE"),"yes","no") -> yes | O12: Sandwich | P12: Escada | R12: ACTIVE | S12: Feliciano Ricardo Fernando | T12: Gerente | U12: geral@lusobatata.com / filipe.ricardo@lusobatata.com | V12: 939017210 | W12: =IF(Table1[[#This Row],[Maintenance]]="yes",IF(OR(Table1[[#This Row],[Start Contract]]="",Table1[[#This Row],[Duration Month2]]=""),"",EDATE(Table1[[#This Row],[Start Contract]],Table1[[#This Row],[Duration Month2]])),"-") -> 46905 | X12: =IF(OR((W12=""),(W12="-")),"",YEAR(Table1[[#This Row],[End Contract]])) -> 2028 | Y12: =IF(Table1[[#This Row],[Maintenance]]="yes",IF(Table1[[#This Row],[End Contract]]="","no",IF(TODAY()<=Table1[[#This Row],[End Contract]],"yes","no")),"no") -> yes | AA12: - | AB12: Tarifa
A13: 11 | B13: Solidus | C13: Solidus Soluções Para Ferramentas e Moldes, Lda. | D13: 505030896 | E13: Avenida D. João V, Nº. 35, 1º., Dtº. 2610-087 Amadora | F13: Sintra | G13: 114 | H13: 45.03 | I13: ESCO | J13: Solcorelios | K13: 15 | L13: =Table1[[#This Row],[Duration]]*12 -> 180 | M13: 44287 | N13: =IF(AND(Table1[[#This Row],[ Type of Contract]]="ESCO",Table1[[#This Row],[Status Detail]]="ACTIVE"),"yes","no") -> yes | O13: Sandwich | P13: Escada | R13: ACTIVE | S13: Paulo Alexandre dos Santos Lourenço | T13: Gerente | U13: solidus@sapo.pt | V13: 912006543 | W13: =IF(Table1[[#This Row],[Maintenance]]="yes",IF(OR(Table1[[#This Row],[Start Contract]]="",Table1[[#This Row],[Duration Month2]]=""),"",EDATE(Table1[[#This Row],[Start Contract]],Table1[[#This Row],[Duration Month2]])),"-") -> 49766 | X13: =IF(OR((W13=""),(W13="-")),"",YEAR(Table1[[#This Row],[End Contract]])) -> 2036 | Y13: =IF(Table1[[#This Row],[Maintenance]]="yes",IF(Table1[[#This Row],[End Contract]]="","no",IF(TODAY()<=Table1[[#This Row],[End Contract]],"yes","no")),"no") -> yes | AA13: - | AB13: Tarifa
A14: 12 | B14: NC Logistica | C14: Natureza Em Congelados, Armazenagem e Comercialização de Produtos Alimentares Lda | D14: 505185016 | E14: Estrada Nacional 10, Alverca Park, Corpo E, Fracção Ao 2619-501 Alverca do Ribatejo | H14: 385 | I14: ESCO | J14: Solcorelios | K14: 15 | L14: =Table1[[#This Row],[Duration]]*12 -> 180 | N14: =IF(AND(Table1[[#This Row],[ Type of Contract]]="ESCO",Table1[[#This Row],[Status Detail]]="ACTIVE"),"yes","no") -> no | R14: CANCELLED | S14: Eurico do Carmo Cid | T14: Gerente | U14: euricocid@nclogistica.pt / filipacid@nclogistica.pt / fabianarodrigues@nclogistica.pt | V14: 219577123 | W14: =IF(Table1[[#This Row],[Maintenance]]="yes",IF(OR(Table1[[#This Row],[Start Contract]]="",Table1[[#This Row],[Duration Month2]]=""),"",EDATE(Table1[[#This Row],[Start Contract]],Table1[[#This Row],[Duration Month2]])),"-") -> - | X14: =IF(OR((W14=""),(W14="-")),"",YEAR(Table1[[#This Row],[End Contract]])) | Y14: =IF(Table1[[#This Row],[Maintenance]]="yes",IF(Table1[[#This Row],[End Contract]]="","no",IF(TODAY()<=Table1[[#This Row],[End Contract]],"yes","no")),"no") -> no
A15: 13 | B15: Marmo J | C15: Marmo J - Exportação, Importação, Mármores Unipessoal Lda | D15: 503995762 | E15: Avenida da Aviação Portuguesa, Nº 55, Fação 2715-140 Pêro Pinheiro | F15: Sintra | G15: 256 | H15: 101.12 | I15: ESCO | J15: Solcorelios | K15: 15 | L15: =Table1[[#This Row],[Duration]]*12 -> 180 | M15: 44287 | N15: =IF(AND(Table1[[#This Row],[ Type of Contract]]="ESCO",Table1[[#This Row],[Status Detail]]="ACTIVE"),"yes","no") -> yes | O15: Sandwich | P15: Escada | R15: ACTIVE | S15: Jorge Manuel Dos Santos Bernardes | T15: Gerente | U15: mara.cruz@marmoj.pt | V15: 912242073 | W15: =IF(Table1[[#This Row],[Maintenance]]="yes",IF(OR(Table1[[#This Row],[Start Contract]]="",Table1[[#This Row],[Duration Month2]]=""),"",EDATE(Table1[[#This Row],[Start Contract]],Table1[[#This Row],[Duration Month2]])),"-") -> 49766 | X15: =IF(OR((W15=""),(W15="-")),"",YEAR(Table1[[#This Row],[End Contract]])) -> 2036 | Y15: =IF(Table1[[#This Row],[Maintenance]]="yes",IF(Table1[[#This Row],[End Contract]]="","no",IF(TODAY()<=Table1[[#This Row],[End Contract]],"yes","no")),"no") -> yes | AA15: - | AB15: Tarifa
A16: 14 | B16: Roufimar | C16: Roufimar Industria de Marmores, S.A | D16: 501782265 | E16: Rua das Piçarras, 37, Maceira 2715-646 Maceira | F16: Sintra | G16: 475 | H16: 187.63 | I16: ESCO | J16: Solcorelios | K16: 15 | L16: =Table1[[#This Row],[Duration]]*12 -> 180 | M16: 44287 | N16: =IF(AND(Table1[[#This Row],[ Type of Contract]]="ESCO",Table1[[#This Row],[Status Detail]]="ACTIVE"),"yes","no") -> yes | O16: Sandwich | P16: Escada | R16: ACTIVE | S16: Arnaldo José Bordalo Roussado Ricardo | T16: Presidente | U16: info@roufinar.com | V16: 969056490 963685277 | W16: =IF(Table1[[#This Row],[Maintenance]]="yes",IF(OR(Table1[[#This Row],[Start Contract]]="",Table1[[#This Row],[Duration Month2]]=""),"",EDATE(Table1[[#This Row],[Start Contract]],Table1[[#This Row],[Duration Month2]])),"-") -> 49766 | X16: =IF(OR((W16=""),(W16="-")),"",YEAR(Table1[[#This Row],[End Contract]])) -> 2036 | Y16: =IF(Table1[[#This Row],[Maintenance]]="yes",IF(Table1[[#This Row],[End Contract]]="","no",IF(TODAY()<=Table1[[#This Row],[End Contract]],"yes","no")),"no") -> yes | AA16: - | AB16: Tarifa
A17: 15 | B17: Viarco | C17: Viarco-Industria de Lapis Lda | D17: 500751722 | E17: R Jaime Afreixo 533 3700-144 Sao Joao Madeira Codex | F17: Aveiro | G17: 76 | H17: 30.02 | I17: ESCO | J17: Solcorelios | K17: 15 | L17: =Table1[[#This Row],[Duration]]*12 -> 180 | M17: 44317 | N17: =IF(AND(Table1[[#This Row],[ Type of Contract]]="ESCO",Table1[[#This Row],[Status Detail]]="ACTIVE"),"yes","no") -> yes | O17: Sandwich | P17: Escada | R17: ACTIVE | S17: José Miguel Vieira Araújo Riobom dos Santos | T17: Gerente | U17: geral@viarco.pt / anacosta@viarco.pt | V17: 918302947 | W17: =IF(Table1[[#This Row],[Maintenance]]="yes",IF(OR(Table1[[#This Row],[Start Contract]]="",Table1[[#This Row],[Duration Month2]]=""),"",EDATE(Table1[[#This Row],[Start Contract]],Table1[[#This Row],[Duration Month2]])),"-") -> 49796 | X17: =IF(OR((W17=""),(W17="-")),"",YEAR(Table1[[#This Row],[End Contract]])) -> 2036 | Y17: =IF(Table1[[#This Row],[Maintenance]]="yes",IF(Table1[[#This Row],[End Contract]]="","no",IF(TODAY()<=Table1[[#This Row],[End Contract]],"yes","no")),"no") -> yes | AA17: - | AB17: Tarifa
A18: 16 | B18: O Zé Pacheco | C18: Gadelho de Castro, S.A | D18: 513203524 | E18: Rua D. António Castro Meireles, 907 4435-666 Baguim do Monte | F18: Porto | G18: 75 | H18: 29.625 | I18: ESCO | J18: Solcorelios | K18: 15 | L18: =Table1[[#This Row],[Duration]]*12 -> 180 | M18: 44531 | N18: =IF(AND(Table1[[#This Row],[ Type of Contract]]="ESCO",Table1[[#This Row],[Status Detail]]="ACTIVE"),"yes","no") -> yes | O18: Cobertura + Telha | P18: Escada | R18: ACTIVE | S18: António Castro de Jesus Gadelho Diogo Gadelho | T18: Administrador Único | U18: geral@ozepacheco.pt | V18: 915913810 | W18: =IF(Table1[[#This Row],[Maintenance]]="yes",IF(OR(Table1[[#This Row],[Start Contract]]="",Table1[[#This Row],[Duration Month2]]=""),"",EDATE(Table1[[#This Row],[Start Contract]],Table1[[#This Row],[Duration Month2]])),"-") -> 50010 | X18: =IF(OR((W18=""),(W18="-")),"",YEAR(Table1[[#This Row],[End Contract]])) -> 2036 | Y18: =IF(Table1[[#This Row],[Maintenance]]="yes",IF(Table1[[#This Row],[End Contract]]="","no",IF(TODAY()<=Table1[[#This Row],[End Contract]],"yes","no")),"no") -> yes | AA18: - | AB18: Tarifa
A19: 17 | B19: Amadois | C19: Amadois-Calçado Lda | D19: 502480335 | E19: Avenida Juventude Desportiva Carregosense, Nº 202 3720-018 Carregosa Oaz | F19: Arouca | G19: 144 | H19: 64.6 | I19: ESCO | J19: Solcorelios | K19: 7 | L19: =Table1[[#This Row],[Duration]]*12 -> 84 | M19: 44348 | N19: =IF(AND(Table1[[#This Row],[ Type of Contract]]="ESCO",Table1[[#This Row],[Status Detail]]="ACTIVE"),"yes","no") -> yes | O19: Sandwich | P19: Escada | R19: ACTIVE | S19: Paulo André Aguiar de Melo Almeida Miguel Melo | T19: Gerente | U19: mmelo@cruzeiro.pt | V19: 924434110 | W19: =IF(Table1[[#This Row],[Maintenance]]="yes",IF(OR(Table1[[#This Row],[Start Contract]]="",Table1[[#This Row],[Duration Month2]]=""),"",EDATE(Table1[[#This Row],[Start Contract]],Table1[[#This Row],[Duration Month2]])),"-") -> 46905 | X19: =IF(OR((W19=""),(W19="-")),"",YEAR(Table1[[#This Row],[End Contract]])) -> 2028 | Y19: =IF(Table1[[#This Row],[Maintenance]]="yes",IF(Table1[[#This Row],[End Contract]]="","no",IF(TODAY()<=Table1[[#This Row],[End Contract]],"yes","no")),"no") -> yes | AA19: - | AB19: Tarifa
A20: 18 | B20: Transportes Rapido | C20: Sociedade de Transportes Poiarense Lda | D20: 500269203 | E20: Zona Industrial de São Miguel Lts 33 e 34 3350-214 São Miguel de Poiares | F20: Coimbra | G20: 192 | H20: 85.5 | I20: ESCO | J20: Solcorelios | K20: 8 | L20: =Table1[[#This Row],[Duration]]*12 -> 96 | M20: 44317 | N20: =IF(AND(Table1[[#This Row],[ Type of Contract]]="ESCO",Table1[[#This Row],[Status Detail]]="ACTIVE"),"yes","no") -> yes | O20: Sandwich | P20: Escada | R20: ACTIVE | S20: Luisa Maria Henriques Simões / Jose Eduardo Henriques Simões / Vitor Fernando Cardoso De Carvalho | T20: Gerentes | U20: luisa.simoes@transportesrapido.com / mario.almeida@transportesrapido.com | V20: 966631463 | W20: =IF(Table1[[#This Row],[Maintenance]]="yes",IF(OR(Table1[[#This Row],[Start Contract]]="",Table1[[#This Row],[Duration Month2]]=""),"",EDATE(Table1[[#This Row],[Start Contract]],Table1[[#This Row],[Duration Month2]])),"-") -> 47239 | X20: =IF(OR((W20=""),(W20="-")),"",YEAR(Table1[[#This Row],[End Contract]])) -> 2029 | Y20: =IF(Table1[[#This Row],[Maintenance]]="yes",IF(Table1[[#This Row],[End Contract]]="","no",IF(TODAY()<=Table1[[#This Row],[End Contract]],"yes","no")),"no") -> yes | AA20: - | AB20: Tarifa
A21: 19 | B21: Granetos | C21: Granetos-Mármores e Granitos, S.A | D21: 501150617 | E21: Covão do Coelho 2395-001 Minde | F21: Leiria | G21: 360 | H21: 163.8 | I21: ESCO BUYOUT | J21: Solcorelios | K21: 15 | L21: =Table1[[#This Row],[Duration]]*12 -> 180 | M21: 44440 | N21: =IF(AND(Table1[[#This Row],[ Type of Contract]]="ESCO",Table1[[#This Row],[Status Detail]]="ACTIVE"),"yes","no") -> no | O21: Sandwich | P21: Escada | R21: ACTIVE | S21: Madalena Da Conceição Castanheira Neto Cerejeira | T21: Administrador | U21: miguelcerejeira@granetos.pt | V21: 249 840 579 | W21: =IF(Table1[[#This Row],[Maintenance]]="yes",IF(OR(Table1[[#This Row],[Start Contract]]="",Table1[[#This Row],[Duration Month2]]=""),"",EDATE(Table1[[#This Row],[Start Contract]],Table1[[#This Row],[Duration Month2]])),"-") -> - | X21: =IF(OR((W21=""),(W21="-")),"",YEAR(Table1[[#This Row],[End Contract]])) | Y21: =IF(Table1[[#This Row],[Maintenance]]="yes",IF(Table1[[#This Row],[End Contract]]="","no",IF(TODAY()<=Table1[[#This Row],[End Contract]],"yes","no")),"no") -> no
A22: 20 | B22: Queijaria Inácio Corvelo | C22: Inácio José Vinhas Corvelo | D22: 196141494 | E22: Rua Estacão 9168, Rio De Moinhos Borba, 7150-368 Borba | F22: Évora | G22: 108 | H22: 42.7 | I22: EPC | J22: Cliente | K22: 0 | L22: =Table1[[#This Row],[Duration]]*12 -> 0 | M22: - | N22: =IF(AND(Table1[[#This Row],[ Type of Contract]]="ESCO",Table1[[#This Row],[Status Detail]]="ACTIVE"),"yes","no") -> no | O22: Sandwich | P22: Escada | Q22: To discuss with Oscar | R22: ACTIVE | S22: Inácio José Vinhas Corvelo | T22: Gerente | V22: 961302782 | W22: =IF(Table1[[#This Row],[Maintenance]]="yes",IF(OR(Table1[[#This Row],[Start Contract]]="",Table1[[#This Row],[Duration Month2]]=""),"",EDATE(Table1[[#This Row],[Start Contract]],Table1[[#This Row],[Duration Month2]])),"-") -> - | X22: =IF(OR((W22=""),(W22="-")),"",YEAR(Table1[[#This Row],[End Contract]])) | Y22: =IF(Table1[[#This Row],[Maintenance]]="yes",IF(Table1[[#This Row],[End Contract]]="","no",IF(TODAY()<=Table1[[#This Row],[End Contract]],"yes","no")),"no") -> no
A23: 21 | B23: Topeca | C23: Topeca-Produtos de Construção Civil Lda | D23: 502782374 | E23: Cercal 2490-115 Cercal | F23: Leiria | G23: 160 | H23: 72.8 | I23: EPC | J23: Cliente | K23: 1 | L23: =Table1[[#This Row],[Duration]]*12 -> 12 | M23: 46179 | N23: yes | O23: Sandwich | P23: Escada | Q23: Maintenance discussed yearly with the client | R23: ACTIVE | S23: Francisco Ferreira Nunes César Nunes | T23: Gerente | U23: cesar.nunes@topeca.pt | V23: 938095499 | W23: =IF(Table1[[#This Row],[Maintenance]]="yes",IF(OR(Table1[[#This Row],[Start Contract]]="",Table1[[#This Row],[Duration Month2]]=""),"",EDATE(Table1[[#This Row],[Start Contract]],Table1[[#This Row],[Duration Month2]])),"-") -> 46544 | X23: =IF(OR((W23=""),(W23="-")),"",YEAR(Table1[[#This Row],[End Contract]])) -> 2027 | Y23: =IF(Table1[[#This Row],[Maintenance]]="yes",IF(Table1[[#This Row],[End Contract]]="","no",IF(TODAY()<=Table1[[#This Row],[End Contract]],"yes","no")),"no") -> yes | Z23: Sem certeza na quantidade de anos, imagino que seja 1
A24: 22 | B24: Mindtrooper | C24: Mindtrooper, Unipessoal, Limitada | D24: 509875874 | E24: Rua Antonio Bravo, N.0 140 | F24: Lisboa | H24: 140 | I24: EPC | J24: Cliente | K24: 0 | L24: =Table1[[#This Row],[Duration]]*12 -> 0 | M24: - | N24: =IF(AND(Table1[[#This Row],[ Type of Contract]]="ESCO",Table1[[#This Row],[Status Detail]]="ACTIVE"),"yes","no") -> no | R24: ACTIVE | W24: =IF(Table1[[#This Row],[Maintenance]]="yes",IF(OR(Table1[[#This Row],[Start Contract]]="",Table1[[#This Row],[Duration Month2]]=""),"",EDATE(Table1[[#This Row],[Start Contract]],Table1[[#This Row],[Duration Month2]])),"-") -> - | X24: =IF(OR((W24=""),(W24="-")),"",YEAR(Table1[[#This Row],[End Contract]])) | Y24: =IF(Table1[[#This Row],[Maintenance]]="yes",IF(Table1[[#This Row],[End Contract]]="","no",IF(TODAY()<=Table1[[#This Row],[End Contract]],"yes","no")),"no") -> no
A25: 23 | B25: Heden | C25: Liveworks, Lda | D25: 514345250 | E25: Doca Jardim do Tabaco, Terminal de Cruzeiros de Lisboa, Edifício Ne, 1º Piso 1100-651 Lisboa | F25: Lisboa | G25: 48 | H25: 18 | I25: EPC | J25: Cliente | K25: 0 | L25: =Table1[[#This Row],[Duration]]*12 -> 0 | M25: 44582 | N25: =IF(AND(Table1[[#This Row],[ Type of Contract]]="ESCO",Table1[[#This Row],[Status Detail]]="ACTIVE"),"yes","no") -> no | O25: Cobertura | P25: Escada | Q25: Maintenance discussed yearly with the client | R25: ACTIVE | S25: Manuel Bastos | U25: manuel@heden.co | V25: 919237074 | W25: =IF(Table1[[#This Row],[Maintenance]]="yes",IF(OR(Table1[[#This Row],[Start Contract]]="",Table1[[#This Row],[Duration Month2]]=""),"",EDATE(Table1[[#This Row],[Start Contract]],Table1[[#This Row],[Duration Month2]])),"-") -> - | X25: =IF(OR((W25=""),(W25="-")),"",YEAR(Table1[[#This Row],[End Contract]])) | Y25: =IF(Table1[[#This Row],[Maintenance]]="yes",IF(Table1[[#This Row],[End Contract]]="","no",IF(TODAY()<=Table1[[#This Row],[End Contract]],"yes","no")),"no") -> no
A26: 24 | B26: O Bolo do Caco | C26: Horizontes Renovados Lda | D26: 508975913 | E26: Rua Vicente Vaz das Vacas, Nº 22 8500-746 Portimão | F26: Faro | H26: 42.7 | I26: EPC | J26: Cliente | K26: 0 | L26: =Table1[[#This Row],[Duration]]*12 -> 0 | M26: 44922 | N26: =IF(AND(Table1[[#This Row],[ Type of Contract]]="ESCO",Table1[[#This Row],[Status Detail]]="ACTIVE"),"yes","no") -> no | R26: CANCELLED | S26: Paulo Pedrosa | T26: Gerente | W26: =IF(Table1[[#This Row],[Maintenance]]="yes",IF(OR(Table1[[#This Row],[Start Contract]]="",Table1[[#This Row],[Duration Month2]]=""),"",EDATE(Table1[[#This Row],[Start Contract]],Table1[[#This Row],[Duration Month2]])),"-") -> - | X26: =IF(OR((W26=""),(W26="-")),"",YEAR(Table1[[#This Row],[End Contract]])) | Y26: =IF(Table1[[#This Row],[Maintenance]]="yes",IF(Table1[[#This Row],[End Contract]]="","no",IF(TODAY()<=Table1[[#This Row],[End Contract]],"yes","no")),"no") -> no
A27: 25 | B27: Betafiel | C27: Betafiel-Artefactos de Betão de Penafiel S.A | D27: 500782016 | E27: Tapadinho 4560-162 Guilhufe | H27: 85.5 | I27: ESCO | J27: Solcorelios | K27: 10 | L27: =Table1[[#This Row],[Duration]]*12 -> 120 | N27: =IF(AND(Table1[[#This Row],[ Type of Contract]]="ESCO",Table1[[#This Row],[Status Detail]]="ACTIVE"),"yes","no") -> no | R27: CANCELLED | S27: Carlos Manuel Paquim da Costa | T27: Presidente do conselho de administração | U27: administracao@betafiel.pt | W27: =IF(Table1[[#This Row],[Maintenance]]="yes",IF(OR(Table1[[#This Row],[Start Contract]]="",Table1[[#This Row],[Duration Month2]]=""),"",EDATE(Table1[[#This Row],[Start Contract]],Table1[[#This Row],[Duration Month2]])),"-") -> - | X27: =IF(OR((W27=""),(W27="-")),"",YEAR(Table1[[#This Row],[End Contract]])) | Y27: =IF(Table1[[#This Row],[Maintenance]]="yes",IF(Table1[[#This Row],[End Contract]]="","no",IF(TODAY()<=Table1[[#This Row],[End Contract]],"yes","no")),"no") -> no
A28: 26 | B28: Multiaves | C28: Multiaves-Avicola Internacional Lda | D28: 502882514 | E28: Caramulo 3475-031 Caramulo | F28: Tondela | G28: 152 | H28: 69.2 | I28: ESCO | J28: Solcorelios | K28: 15 | L28: =Table1[[#This Row],[Duration]]*12 -> 180 | M28: 44440 | N28: =IF(AND(Table1[[#This Row],[ Type of Contract]]="ESCO",Table1[[#This Row],[Status Detail]]="ACTIVE"),"yes","no") -> yes | O28: Solo | P28: Não é necessário | R28: ACTIVE | S28: Gonçalo José Sousa Ornellas de Avillez Pereira / João Maria Lopes de Figueiredo de Lacerda | T28: Gerentes | U28: g.avillez.pereira@multiaves.pt / joao.lacerda@ovoscaramulo.com | V28: 232.860.030 | W28: =IF(Table1[[#This Row],[Maintenance]]="yes",IF(OR(Table1[[#This Row],[Start Contract]]="",Table1[[#This Row],[Duration Month2]]=""),"",EDATE(Table1[[#This Row],[Start Contract]],Table1[[#This Row],[Duration Month2]])),"-") -> 49919 | X28: =IF(OR((W28=""),(W28="-")),"",YEAR(Table1[[#This Row],[End Contract]])) -> 2036 | Y28: =IF(Table1[[#This Row],[Maintenance]]="yes",IF(Table1[[#This Row],[End Contract]]="","no",IF(TODAY()<=Table1[[#This Row],[End Contract]],"yes","no")),"no") -> yes | AA28: 8760 | AB28: Fixa
A29: 27 | B29: ITM Moita | C29: Intervedros - Supermercados, Lda | D29: 513018590 | E29: Quinta de Santa Rosa 2860-050 Alhos Vedros | F29: Setúbal | G29: 408 | H29: 183.6 | I29: ESCO | J29: Solcorelios | K29: 7 | L29: =Table1[[#This Row],[Duration]]*12 -> 84 | M29: 44470 | N29: =IF(AND(Table1[[#This Row],[ Type of Contract]]="ESCO",Table1[[#This Row],[Status Detail]]="ACTIVE"),"yes","no") -> yes | O29: Sandwich | P29: Escada | R29: ACTIVE | S29: Hugo Almeida | T29: Gerente | U29: interuedrcs@gmail.com | V29: 968973531 | W29: =IF(Table1[[#This Row],[Maintenance]]="yes",IF(OR(Table1[[#This Row],[Start Contract]]="",Table1[[#This Row],[Duration Month2]]=""),"",EDATE(Table1[[#This Row],[Start Contract]],Table1[[#This Row],[Duration Month2]])),"-") -> 47027 | X29: =IF(OR((W29=""),(W29="-")),"",YEAR(Table1[[#This Row],[End Contract]])) -> 2028 | Y29: =IF(Table1[[#This Row],[Maintenance]]="yes",IF(Table1[[#This Row],[End Contract]]="","no",IF(TODAY()<=Table1[[#This Row],[End Contract]],"yes","no")),"no") -> yes | AA29: - | AB29: Tarifa
A30: 28 | B30: Serralharia Vieira | C30: Serralharia Vieira Lda | D30: 501258060 | E30: Av. Estrada Real, N.º 1167-A 4620-787 Torno | F30: Porto | G30: 100 | H30: 45.5 | I30: ESCO | J30: Solcorelios | K30: 20 | L30: =Table1[[#This Row],[Duration]]*12 -> 240 | M30: 44470 | N30: =IF(AND(Table1[[#This Row],[ Type of Contract]]="ESCO",Table1[[#This Row],[Status Detail]]="ACTIVE"),"yes","no") -> yes | O30: Sandwich | P30: Escada | R30: ACTIVE | S30: Vitor Hugo Moreira Vieira | T30: Gerente | U30: Vítorserralhariavieira@hotmail.com | V30: 917528030 | W30: =IF(Table1[[#This Row],[Maintenance]]="yes",IF(OR(Table1[[#This Row],[Start Contract]]="",Table1[[#This Row],[Duration Month2]]=""),"",EDATE(Table1[[#This Row],[Start Contract]],Table1[[#This Row],[Duration Month2]])),"-") -> 51775 | X30: =IF(OR((W30=""),(W30="-")),"",YEAR(Table1[[#This Row],[End Contract]])) -> 2041 | Y30: =IF(Table1[[#This Row],[Maintenance]]="yes",IF(Table1[[#This Row],[End Contract]]="","no",IF(TODAY()<=Table1[[#This Row],[End Contract]],"yes","no")),"no") -> yes | AA30: - | AB30: Tarifa
A31: 29 | B31: Colégio Nossa Senhora da Apresentação | C31: Colégio Diocesano de Nossa Senhora da Apresentação | D31: 502786078 | E31: Aveiro - Vagos - | F31: Aveiro | G31: 340 | H31: =210*0.53 -> 111.3 | I31: ESCO | J31: Solcorelios | K31: 15 | L31: =Table1[[#This Row],[Duration]]*12 -> 180 | M31: 44501 | N31: =IF(AND(Table1[[#This Row],[ Type of Contract]]="ESCO",Table1[[#This Row],[Status Detail]]="ACTIVE"),"yes","no") -> yes | O31: Sandwich | P31: Escada Vertical | R31: ACTIVE | S31: Luís Fernando Oliveira David Malta/Ricardo Silva | T31: Diretor | U31: luísolíveira@colegiocalcao.org | V31: 931731853/925094080 | W31: =IF(Table1[[#This Row],[Maintenance]]="yes",IF(OR(Table1[[#This Row],[Start Contract]]="",Table1[[#This Row],[Duration Month2]]=""),"",EDATE(Table1[[#This Row],[Start Contract]],Table1[[#This Row],[Duration Month2]])),"-") -> 49980 | X31: =IF(OR((W31=""),(W31="-")),"",YEAR(Table1[[#This Row],[End Contract]])) -> 2036 | Y31: =IF(Table1[[#This Row],[Maintenance]]="yes",IF(Table1[[#This Row],[End Contract]]="","no",IF(TODAY()<=Table1[[#This Row],[End Contract]],"yes","no")),"no") -> yes | AA31: - | AB31: Tarifa
A32: 30 | B32: Absorvalor | C32: Absorvalor Lda | D32: 507685733 | E32: Rua da Ferraria, Chãs 2415-178 Regueira de Pontes | F32: Leiria | G32: 576 | H32: 254.8 | I32: ESCO BUYOUT | J32: Solcorelios | K32: 15 | L32: =Table1[[#This Row],[Duration]]*12 -> 180 | M32: 44531 | N32: =IF(AND(Table1[[#This Row],[ Type of Contract]]="ESCO",Table1[[#This Row],[Status Detail]]="ACTIVE"),"yes","no") -> no | O32: Sandwich | P32: Escada | R32: ACTIVE | S32: Muhammad Abdul Satar / Bernardino Manuel Amaro dos Santos Carla | T32: Gerentes | V32: 910983469 | W32: =IF(Table1[[#This Row],[Maintenance]]="yes",IF(OR(Table1[[#This Row],[Start Contract]]="",Table1[[#This Row],[Duration Month2]]=""),"",EDATE(Table1[[#This Row],[Start Contract]],Table1[[#This Row],[Duration Month2]])),"-") -> - | X32: =IF(OR((W32=""),(W32="-")),"",YEAR(Table1[[#This Row],[End Contract]])) | Y32: =IF(Table1[[#This Row],[Maintenance]]="yes",IF(Table1[[#This Row],[End Contract]]="","no",IF(TODAY()<=Table1[[#This Row],[End Contract]],"yes","no")),"no") -> no
A33: 31 | B33: MC Rios | C33: M.C. Rios, S.A | D33: 502893575 | E33: Lugar do Areeiro 3850-200 Albergaria-A-Velha | H33: 172.9 | I33: ESCO | J33: Solcorelios | K33: 15 | L33: =Table1[[#This Row],[Duration]]*12 -> 180 | N33: =IF(AND(Table1[[#This Row],[ Type of Contract]]="ESCO",Table1[[#This Row],[Status Detail]]="ACTIVE"),"yes","no") -> no | R33: CANCELLED | S33: Maria Leonor Duarte Rios Pires / Carlos Alberto Rodrigues Duarte Rios | T33: Vogal | W33: =IF(Table1[[#This Row],[Maintenance]]="yes",IF(OR(Table1[[#This Row],[Start Contract]]="",Table1[[#This Row],[Duration Month2]]=""),"",EDATE(Table1[[#This Row],[Start Contract]],Table1[[#This Row],[Duration Month2]])),"-") -> - | X33: =IF(OR((W33=""),(W33="-")),"",YEAR(Table1[[#This Row],[End Contract]])) | Y33: =IF(Table1[[#This Row],[Maintenance]]="yes",IF(Table1[[#This Row],[End Contract]]="","no",IF(TODAY()<=Table1[[#This Row],[End Contract]],"yes","no")),"no") -> no
A34: 32 | B34: VCP | C34: Vidraria Central do Porto, S.A | D34: 503502707 | E34: Avenida D. Miguel, 340, Pavilhão E, Zona Industrial Baguim do Monte 4435-678 Baguim do Monte - Gondomar | F34: Porto | G34: 80 | H34: 36.4 | I34: EPC | J34: Cliente | K34: 0 | L34: =Table1[[#This Row],[Duration]]*12 -> 0 | M34: - | N34: =IF(AND(Table1[[#This Row],[ Type of Contract]]="ESCO",Table1[[#This Row],[Status Detail]]="ACTIVE"),"yes","no") -> no | O34: Sandwich | P34: Escada | Q34: Maintenance discussed yearly with the client | R34: ACTIVE | S34: Nuno Amilcar Fragoso / Vítor Manuel da Fonseca Pereira | T34: Presidente / Vogal | W34: =IF(Table1[[#This Row],[Maintenance]]="yes",IF(OR(Table1[[#This Row],[Start Contract]]="",Table1[[#This Row],[Duration Month2]]=""),"",EDATE(Table1[[#This Row],[Start Contract]],Table1[[#This Row],[Duration Month2]])),"-") -> - | X34: =IF(OR((W34=""),(W34="-")),"",YEAR(Table1[[#This Row],[End Contract]])) | Y34: =IF(Table1[[#This Row],[Maintenance]]="yes",IF(Table1[[#This Row],[End Contract]]="","no",IF(TODAY()<=Table1[[#This Row],[End Contract]],"yes","no")),"no") -> no
A35: 33 | B35: Sicobrita | C35: Sicobrita - Extracção e Britagem de Pedra S.A | D35: 501277676 | E35: R de Santa Luzia Nº 22 - Sala 32 3100-483 Pombal | F35: Pombal | G35: 1824 | H35: =1824*0.45 -> 820.8 | I35: ESCO | J35: Solcorelios | K35: 15 | L35: =Table1[[#This Row],[Duration]]*12 -> 180 | M35: 44743 | N35: =IF(AND(Table1[[#This Row],[ Type of Contract]]="ESCO",Table1[[#This Row],[Status Detail]]="ACTIVE"),"yes","no") -> yes | O35: Solo | P35: Não é necessário | R35: ACTIVE | S35: Armando Jose Manuel Bugalhão Carrilho Patricio Artur | T35: Presidente do Conselho de Administração | U35: armando.vieira@sicobrita.pt | V35: 969507300 916036244 963063582 963642561 | W35: =IF(Table1[[#This Row],[Maintenance]]="yes",IF(OR(Table1[[#This Row],[Start Contract]]="",Table1[[#This Row],[Duration Month2]]=""),"",EDATE(Table1[[#This Row],[Start Contract]],Table1[[#This Row],[Duration Month2]])),"-") -> 50222 | X35: =IF(OR((W35=""),(W35="-")),"",YEAR(Table1[[#This Row],[End Contract]])) -> 2037 | Y35: =IF(Table1[[#This Row],[Maintenance]]="yes",IF(Table1[[#This Row],[End Contract]]="","no",IF(TODAY()<=Table1[[#This Row],[End Contract]],"yes","no")),"no") -> yes | AA35: - | AB35: Tarifa
A36: 34 | B36: Mirandesa | C36: Cooperativa Agro-Pecuária Mirandesa Crl | D36: 501416382 | E36: Zona Industrial de Vimioso - Lote 42/45 5230-284 Vimioso | F36: Bragança - Vimioso | G36: 144 | H36: 76.32 | I36: ESCO | J36: Solcorelios | K36: 15 | L36: =Table1[[#This Row],[Duration]]*12 -> 180 | M36: 44501 | N36: =IF(AND(Table1[[#This Row],[ Type of Contract]]="ESCO",Table1[[#This Row],[Status Detail]]="ACTIVE"),"yes","no") -> yes | O36: Sandwich | P36: Escada | R36: ACTIVE | S36: Nuno Paulo António Manuel Luís / José Abílio João | T36: Presidente / Tesoureiro | U36: nunorpaulo@mirandesa.pt | V36: 966969869 | W36: =IF(Table1[[#This Row],[Maintenance]]="yes",IF(OR(Table1[[#This Row],[Start Contract]]="",Table1[[#This Row],[Duration Month2]]=""),"",EDATE(Table1[[#This Row],[Start Contract]],Table1[[#This Row],[Duration Month2]])),"-") -> 49980 | X36: =IF(OR((W36=""),(W36="-")),"",YEAR(Table1[[#This Row],[End Contract]])) -> 2036 | Y36: =IF(Table1[[#This Row],[Maintenance]]="yes",IF(Table1[[#This Row],[End Contract]]="","no",IF(TODAY()<=Table1[[#This Row],[End Contract]],"yes","no")),"no") -> yes | AA36: - | AB36: Tarifa
A37: 35 | B37: Jovi-Sola | C37: Jovi-Sola – Pré fabricados para calçado, Lda | D37: 504277219 | E37: Rua Dom Dinis, N.º 110 3700-466 Arrifana Vfr | H37: 45.1 | I37: ESCO | J37: Solcorelios | K37: 15 | L37: =Table1[[#This Row],[Duration]]*12 -> 180 | N37: =IF(AND(Table1[[#This Row],[ Type of Contract]]="ESCO",Table1[[#This Row],[Status Detail]]="ACTIVE"),"yes","no") -> no | R37: CANCELLED | S37: Vítor Manuel Francisco | T37: Gerente | U37: jovi-sola@sapo.pt | W37: =IF(Table1[[#This Row],[Maintenance]]="yes",IF(OR(Table1[[#This Row],[Start Contract]]="",Table1[[#This Row],[Duration Month2]]=""),"",EDATE(Table1[[#This Row],[Start Contract]],Table1[[#This Row],[Duration Month2]])),"-") -> - | X37: =IF(OR((W37=""),(W37="-")),"",YEAR(Table1[[#This Row],[End Contract]])) | Y37: =IF(Table1[[#This Row],[Maintenance]]="yes",IF(Table1[[#This Row],[End Contract]]="","no",IF(TODAY()<=Table1[[#This Row],[End Contract]],"yes","no")),"no") -> no
A38: 36 | B38: Joaquim Pinheiro Santos | C38: JOAQUIM PINHEIRO SANTOS,SUCESSORES LDA | D38: 500152624 | E38: Vila Moreira (39.471324, -8.675141) | F38: Santarém | G38: 413 | H38: 218.9 | I38: EPC | J38: Cliente | K38: 2 | L38: =Table1[[#This Row],[Duration]]*12 -> 24 | M38: 45108 | N38: yes | O38: Sandwich | P38: Escada | Q38: To discuss with the client | R38: ACTIVE | S38: Nuno Santos | U38: curtir@sapo.pt | V38: 939720430 | W38: =IF(Table1[[#This Row],[Maintenance]]="yes",IF(OR(Table1[[#This Row],[Start Contract]]="",Table1[[#This Row],[Duration Month2]]=""),"",EDATE(Table1[[#This Row],[Start Contract]],Table1[[#This Row],[Duration Month2]])),"-") -> 45839 | X38: =IF(OR((W38=""),(W38="-")),"",YEAR(Table1[[#This Row],[End Contract]])) -> 2025 | Y38: =IF(Table1[[#This Row],[Maintenance]]="yes",IF(Table1[[#This Row],[End Contract]]="","no",IF(TODAY()<=Table1[[#This Row],[End Contract]],"yes","no")),"no") -> no | Z38: Não ha registo de contrato estar renovado
A39: 37 | B39: Ferraz & Ferreira | C39: Ferraz & Ferreira, Lda. | D39: 500876746 | E39: Rua do Padrão, 140 4760-743 Vilarinho das Cambas | F39: Vila Nova de Famalicão | G39: 272 | H39: =(44+80+148)*0.53 -> 144.16 | I39: ESCO | J39: Solcorelios | K39: 10 | L39: =Table1[[#This Row],[Duration]]*12 -> 120 | M39: 44713 | N39: =IF(AND(Table1[[#This Row],[ Type of Contract]]="ESCO",Table1[[#This Row],[Status Detail]]="ACTIVE"),"yes","no") -> yes | O39: Cobertura + Sandwich | P39: Escada | R39: ACTIVE | S39: Paula Ana Maria Fluckiger Ferraz Coutinho | T39: Gerente | U39: paulaferrazferreira.com.pt | V39: 252301350 252301351 914981896 914933459 | W39: =IF(Table1[[#This Row],[Maintenance]]="yes",IF(OR(Table1[[#This Row],[Start Contract]]="",Table1[[#This Row],[Duration Month2]]=""),"",EDATE(Table1[[#This Row],[Start Contract]],Table1[[#This Row],[Duration Month2]])),"-") -> 48366 | X39: =IF(OR((W39=""),(W39="-")),"",YEAR(Table1[[#This Row],[End Contract]])) -> 2032 | Y39: =IF(Table1[[#This Row],[Maintenance]]="yes",IF(Table1[[#This Row],[End Contract]]="","no",IF(TODAY()<=Table1[[#This Row],[End Contract]],"yes","no")),"no") -> yes | AA39: - | AB39: Tarifa
A40: 38 | B40: LIDL | C40: Lidl & Companhia | D40: 503340855 | G40: 316(bragança)+332(lousã)+33(moução)+316(porto)+333(tomar)+333(covilhã)+333(viana do castelo) | H40: 873.81 | I40: EPC | J40: Cliente | K40: 0 | L40: =Table1[[#This Row],[Duration]]*12 -> 0 | M40: - | N40: =IF(AND(Table1[[#This Row],[ Type of Contract]]="ESCO",Table1[[#This Row],[Status Detail]]="ACTIVE"),"yes","no") -> no | O40: Cobertura | P40: Escada | R40: ACTIVE | W40: =IF(Table1[[#This Row],[Maintenance]]="yes",IF(OR(Table1[[#This Row],[Start Contract]]="",Table1[[#This Row],[Duration Month2]]=""),"",EDATE(Table1[[#This Row],[Start Contract]],Table1[[#This Row],[Duration Month2]])),"-") -> - | X40: =IF(OR((W40=""),(W40="-")),"",YEAR(Table1[[#This Row],[End Contract]])) | Y40: =IF(Table1[[#This Row],[Maintenance]]="yes",IF(Table1[[#This Row],[End Contract]]="","no",IF(TODAY()<=Table1[[#This Row],[End Contract]],"yes","no")),"no") -> no
A41: 39 | B41: ELS Sede | C41: Estevão Luis Salvador Lda | D41: 502786639 | E41: R. José Salvador 90, 2715-311 | F41: Santarém | G41: 924 | H41: 498.96 | I41: EPC | J41: Cliente | K41: 0 | L41: =Table1[[#This Row],[Duration]]*12 -> 0 | M41: - | N41: =IF(AND(Table1[[#This Row],[ Type of Contract]]="ESCO",Table1[[#This Row],[Status Detail]]="ACTIVE"),"yes","no") -> no | O41: Sandwich | P41: Escada | Q41: To discuss with Oscar | R41: ACTIVE | S41: Oscar Vale | U41: oscar.vale@partilhextrema.pt | V41: 912253249 | W41: =IF(Table1[[#This Row],[Maintenance]]="yes",IF(OR(Table1[[#This Row],[Start Contract]]="",Table1[[#This Row],[Duration Month2]]=""),"",EDATE(Table1[[#This Row],[Start Contract]],Table1[[#This Row],[Duration Month2]])),"-") -> - | X41: =IF(OR((W41=""),(W41="-")),"",YEAR(Table1[[#This Row],[End Contract]])) | Y41: =IF(Table1[[#This Row],[Maintenance]]="yes",IF(Table1[[#This Row],[End Contract]]="","no",IF(TODAY()<=Table1[[#This Row],[End Contract]],"yes","no")),"no") -> no
A42: 40 | B42: ELS Bolo do Caco | C42: Estevão Luis Salvador Lda | D42: 502786639 | E42: Pinhal dos Frades, Ericeira (38.971454, -9.385205) | F42: Leiria | G42: 278 | H42: 150.12 | I42: EPC | J42: Cliente | K42: 0 | L42: =Table1[[#This Row],[Duration]]*12 -> 0 | M42: - | N42: =IF(AND(Table1[[#This Row],[ Type of Contract]]="ESCO",Table1[[#This Row],[Status Detail]]="ACTIVE"),"yes","no") -> no | O42: Sandwich | P42: Escada | Q42: To discuss with Oscar | R42: ACTIVE | S42: Oscar Vale | U42: oscar.vale@partilhextrema.pt | V42: 912253249 | W42: =IF(Table1[[#This Row],[Maintenance]]="yes",IF(OR(Table1[[#This Row],[Start Contract]]="",Table1[[#This Row],[Duration Month2]]=""),"",EDATE(Table1[[#This Row],[Start Contract]],Table1[[#This Row],[Duration Month2]])),"-") -> - | X42: =IF(OR((W42=""),(W42="-")),"",YEAR(Table1[[#This Row],[End Contract]])) | Y42: =IF(Table1[[#This Row],[Maintenance]]="yes",IF(Table1[[#This Row],[End Contract]]="","no",IF(TODAY()<=Table1[[#This Row],[End Contract]],"yes","no")),"no") -> no
A43: 41 | B43: Mármores Galrão | C43: Marmores Galrão-Eduardo Galrão Jorge & Filhos S.A. | D43: 500091161 | E43: Av. Da Liberdade 153, 2765-004, Pêro Pinheiro | F43: Sintra | G43: 792 | H43: 431.64 | I43: ESCO | J43: Solcorelios | K43: 15 | L43: =Table1[[#This Row],[Duration]]*12 -> 180 | M43: 45108 | N43: =IF(AND(Table1[[#This Row],[ Type of Contract]]="ESCO",Table1[[#This Row],[Status Detail]]="ACTIVE"),"yes","no") -> yes | O43: Sandwich | P43: Escada | R43: ACTIVE | S43: José Manuel Rodrigues Galrão Jorge / Augusto Manuel de Oliveira Diniz / Paulo Hortensio Jorge Diniz/ Ricardo Diniz | T43: Presidente do conselho de administração / Vogal do conselho de administração | U43: jroseiro@galrao.com / jgalraoj@galrao.com | V43: 910410024 | W43: =IF(Table1[[#This Row],[Maintenance]]="yes",IF(OR(Table1[[#This Row],[Start Contract]]="",Table1[[#This Row],[Duration Month2]]=""),"",EDATE(Table1[[#This Row],[Start Contract]],Table1[[#This Row],[Duration Month2]])),"-") -> 50587 | X43: =IF(OR((W43=""),(W43="-")),"",YEAR(Table1[[#This Row],[End Contract]])) -> 2038 | Y43: =IF(Table1[[#This Row],[Maintenance]]="yes",IF(Table1[[#This Row],[End Contract]]="","no",IF(TODAY()<=Table1[[#This Row],[End Contract]],"yes","no")),"no") -> yes | AA43: - | AB43: Tarifa
A44: 42 | B44: Granitos Galrão do Norte | C44: Granitos Galrão, Norte, Limitada | D44: 502247185 | E44: Rua da Gandra, nº 20, 4950-850 Mazedo e Cortes | F44: Monção | G44: 684 | H44: 307.8 | I44: ESCO | J44: Solcorelios | K44: 15 | L44: =Table1[[#This Row],[Duration]]*12 -> 180 | M44: 44805 | N44: =IF(AND(Table1[[#This Row],[ Type of Contract]]="ESCO",Table1[[#This Row],[Status Detail]]="ACTIVE"),"yes","no") -> yes | O44: Sandwich | P44: Escada | R44: ACTIVE | S44: José Manuel Rodrigues Galrão Jorge / Augusto Manuel de Oliveira Diniz / Paulo Hortensio Jorge Diniz | T44: Presidente do conselho de administração / Vogal do conselho de administração | U44: jroseiro@galrao.com / jgalraoj@galrao.com | V44: 918705411 966826769 | W44: =IF(Table1[[#This Row],[Maintenance]]="yes",IF(OR(Table1[[#This Row],[Start Contract]]="",Table1[[#This Row],[Duration Month2]]=""),"",EDATE(Table1[[#This Row],[Start Contract]],Table1[[#This Row],[Duration Month2]])),"-") -> 50284 | X44: =IF(OR((W44=""),(W44="-")),"",YEAR(Table1[[#This Row],[End Contract]])) -> 2037 | Y44: =IF(Table1[[#This Row],[Maintenance]]="yes",IF(Table1[[#This Row],[End Contract]]="","no",IF(TODAY()<=Table1[[#This Row],[End Contract]],"yes","no")),"no") -> yes | AA44: - | AB44: Tarifa
A45: 43 | B45: Ardavi | C45: Ardavi-Maquinação E Comercialização De Artefactos Metal... | D45: 502605545 | E45: Rua Das Cavadas, S/n, Pedrulheira, 243O-4O2 Marinha Grande | F45: Leiria | G45: 136 | H45: 72.76 | I45: ESCO | J45: Solcorelios | K45: 15 | L45: =Table1[[#This Row],[Duration]]*12 -> 180 | M45: 44621 | N45: =IF(AND(Table1[[#This Row],[ Type of Contract]]="ESCO",Table1[[#This Row],[Status Detail]]="ACTIVE"),"yes","no") -> yes | O45: Sandwich | P45: Escada | R45: ACTIVE | S45: Hugo David Gonçalves Simões / Aldina Alves Gonçalves Simões | T45: Gerentes | U45: joao.mendes@ardavi.pt | V45: 967272016 | W45: =IF(Table1[[#This Row],[Maintenance]]="yes",IF(OR(Table1[[#This Row],[Start Contract]]="",Table1[[#This Row],[Duration Month2]]=""),"",EDATE(Table1[[#This Row],[Start Contract]],Table1[[#This Row],[Duration Month2]])),"-") -> 50100 | X45: =IF(OR((W45=""),(W45="-")),"",YEAR(Table1[[#This Row],[End Contract]])) -> 2037 | Y45: =IF(Table1[[#This Row],[Maintenance]]="yes",IF(Table1[[#This Row],[End Contract]]="","no",IF(TODAY()<=Table1[[#This Row],[End Contract]],"yes","no")),"no") -> yes | AA45: - | AB45: Tarifa
A46: 44 | B46: Textil do Marco | C46: Textil Do Marco S.A. | D46: 501534008 | E46: Zona lndustrial -Tuias 4630-489 Marco de Canaveses | F46: Porto | G46: 120 | H46: 63.6 | I46: EPC | J46: Cliente | K46: 0 | L46: =Table1[[#This Row],[Duration]]*12 -> 0 | M46: - | N46: =IF(AND(Table1[[#This Row],[ Type of Contract]]="ESCO",Table1[[#This Row],[Status Detail]]="ACTIVE"),"yes","no") -> no | O46: Cobertura | P46: Escada | Q46: To discuss with the client | R46: ACTIVE | S46: Oskar Andreas Falley | T46: Presidente | V46: 255534434 | W46: =IF(Table1[[#This Row],[Maintenance]]="yes",IF(OR(Table1[[#This Row],[Start Contract]]="",Table1[[#This Row],[Duration Month2]]=""),"",EDATE(Table1[[#This Row],[Start Contract]],Table1[[#This Row],[Duration Month2]])),"-") -> - | X46: =IF(OR((W46=""),(W46="-")),"",YEAR(Table1[[#This Row],[End Contract]])) | Y46: =IF(Table1[[#This Row],[Maintenance]]="yes",IF(Table1[[#This Row],[End Contract]]="","no",IF(TODAY()<=Table1[[#This Row],[End Contract]],"yes","no")),"no") -> no
A47: 45 | B47: Diaco Fábrica 1 | C47: Diamantino Coelho & Filho S.A. | D47: 502099666 | E47: Rua Zona Industrial - C/C 20 Bajo Santa Cita Santarém | F47: Tomar | G47: 480 | H47: 256.8 | I47: ESCO | J47: Solcorelios | K47: 10 | L47: =Table1[[#This Row],[Duration]]*12 -> 120 | M47: 44652 | N47: =IF(AND(Table1[[#This Row],[ Type of Contract]]="ESCO",Table1[[#This Row],[Status Detail]]="ACTIVE"),"yes","no") -> yes | O47: Sandwich | P47: Escada | R47: ACTIVE | S47: Carlos Manuel Vicente Coelho | T47: Presidente | U47: ccoelho@diaco.pt | V47: 932255257 916597424 | W47: =IF(Table1[[#This Row],[Maintenance]]="yes",IF(OR(Table1[[#This Row],[Start Contract]]="",Table1[[#This Row],[Duration Month2]]=""),"",EDATE(Table1[[#This Row],[Start Contract]],Table1[[#This Row],[Duration Month2]])),"-") -> 48305 | X47: =IF(OR((W47=""),(W47="-")),"",YEAR(Table1[[#This Row],[End Contract]])) -> 2032 | Y47: =IF(Table1[[#This Row],[Maintenance]]="yes",IF(Table1[[#This Row],[End Contract]]="","no",IF(TODAY()<=Table1[[#This Row],[End Contract]],"yes","no")),"no") -> yes | AA47: - | AB47: Tarifa
A48: 45 | B48: Diaco - Agriloja Tomar | C48: Diamantino Coelho & Filho S.A. | D48: 502099666 | E48: Marmelais de Baixo Nº43, 2300-4O1 Tomar | F48: Santarém | G48: 34 | H48: 18.02 | I48: EPC | J48: Cliente | K48: 0 | L48: =Table1[[#This Row],[Duration]]*12 -> 0 | M48: - | N48: =IF(AND(Table1[[#This Row],[ Type of Contract]]="ESCO",Table1[[#This Row],[Status Detail]]="ACTIVE"),"yes","no") -> no | O48: Chapa ou Sandwich | P48: Escada | Q48: To discuss with the client | R48: ACTIVE | S48: Carlos Manuel Vicente Coelho/Luis | T48: Presidente/responsável agriloja | U48: ccoelho@diaco.pt | V48: 932255257/933800521 | W48: =IF(Table1[[#This Row],[Maintenance]]="yes",IF(OR(Table1[[#This Row],[Start Contract]]="",Table1[[#This Row],[Duration Month2]]=""),"",EDATE(Table1[[#This Row],[Start Contract]],Table1[[#This Row],[Duration Month2]])),"-") -> - | X48: =IF(OR((W48=""),(W48="-")),"",YEAR(Table1[[#This Row],[End Contract]])) | Y48: =IF(Table1[[#This Row],[Maintenance]]="yes",IF(Table1[[#This Row],[End Contract]]="","no",IF(TODAY()<=Table1[[#This Row],[End Contract]],"yes","no")),"no") -> no
A49: 45 | B49: Diaco - Casa | C49: Diamantino Coelho & Filho S.A. | D49: 0 | F49: Santarém | G49: 10 | H49: 5.4 | I49: EPC | J49: Cliente | K49: 0 | L49: =Table1[[#This Row],[Duration]]*12 -> 0 | M49: - | N49: =IF(AND(Table1[[#This Row],[ Type of Contract]]="ESCO",Table1[[#This Row],[Status Detail]]="ACTIVE"),"yes","no") -> no | O49: Telha | P49: Escada | Q49: To discuss with the client | R49: ACTIVE | S49: Carlos Manuel Vicente Coelho | T49: Presidente | U49: ccoelho@diaco.pt | V49: 932255257 | W49: =IF(Table1[[#This Row],[Maintenance]]="yes",IF(OR(Table1[[#This Row],[Start Contract]]="",Table1[[#This Row],[Duration Month2]]=""),"",EDATE(Table1[[#This Row],[Start Contract]],Table1[[#This Row],[Duration Month2]])),"-") -> - | X49: =IF(OR((W49=""),(W49="-")),"",YEAR(Table1[[#This Row],[End Contract]])) | Y49: =IF(Table1[[#This Row],[Maintenance]]="yes",IF(Table1[[#This Row],[End Contract]]="","no",IF(TODAY()<=Table1[[#This Row],[End Contract]],"yes","no")),"no") -> no
A50: 46 | B50: Pinhão & Irmão | C50: Pinhão & Irmão Lda | D50: 501271716 | E50: R. 10 Zona Industrial 397, Rio Meão | F50: Aveiro | G50: =216+69 -> 285 | H50: =30.4+97.2 -> 127.6 | I50: EPC | J50: Cliente | K50: 2 | L50: =Table1[[#This Row],[Duration]]*12 -> 24 | M50: 45538 | N50: yes | O50: Sandwich | P50: Escada | Q50: 2 years - Complete O&M | R50: ACTIVE | S50: Rui Pinhão | T50: Gerente | U50: rui.pinhao@pinhao.pt | V50: 937891282 | W50: =IF(Table1[[#This Row],[Maintenance]]="yes",IF(OR(Table1[[#This Row],[Start Contract]]="",Table1[[#This Row],[Duration Month2]]=""),"",EDATE(Table1[[#This Row],[Start Contract]],Table1[[#This Row],[Duration Month2]])),"-") -> 46268 | X50: =IF(OR((W50=""),(W50="-")),"",YEAR(Table1[[#This Row],[End Contract]])) -> 2026 | Y50: =IF(Table1[[#This Row],[Maintenance]]="yes",IF(Table1[[#This Row],[End Contract]]="","no",IF(TODAY()<=Table1[[#This Row],[End Contract]],"yes","no")),"no") -> yes | AA50: 1450 | AB50: O&M
A51: 47 | B51: Jetesetecar | C51: Jetesetecar - Equipamentos Auto Lda | D51: 503194387 | E51: Rua Manuel da Costa Correia Júnior, Zona Industrial Oaz 3720-517 Santiago de Riba-Ul | F51: Oliveira de Azemeis | G51: 198 | H51: 89.1 | I51: ESCO | J51: Solcorelios | K51: 15 | L51: =Table1[[#This Row],[Duration]]*12 -> 180 | M51: 44774 | N51: =IF(AND(Table1[[#This Row],[ Type of Contract]]="ESCO",Table1[[#This Row],[Status Detail]]="ACTIVE"),"yes","no") -> yes | O51: Sandwich | P51: Escada Vertical | R51: ACTIVE | S51: Adelino da Costa Sá Pedro Santos | T51: Gerente | U51: pedro.santos@jetesetecar.com | V51: 913385462 | W51: =IF(Table1[[#This Row],[Maintenance]]="yes",IF(OR(Table1[[#This Row],[Start Contract]]="",Table1[[#This Row],[Duration Month2]]=""),"",EDATE(Table1[[#This Row],[Start Contract]],Table1[[#This Row],[Duration Month2]])),"-") -> 50253 | X51: =IF(OR((W51=""),(W51="-")),"",YEAR(Table1[[#This Row],[End Contract]])) -> 2037 | Y51: =IF(Table1[[#This Row],[Maintenance]]="yes",IF(Table1[[#This Row],[End Contract]]="","no",IF(TODAY()<=Table1[[#This Row],[End Contract]],"yes","no")),"no") -> yes | AA51: - | AB51: Tarifa
A52: 48 | B52: ELS Laundos | C52: Estevão Luis Salvador Lda | D52: 502786639 | F52: Braga | G52: 126 | H52: 68.04 | I52: EPC | J52: Cliente | K52: 0 | L52: =Table1[[#This Row],[Duration]]*12 -> 0 | M52: - | N52: =IF(AND(Table1[[#This Row],[ Type of Contract]]="ESCO",Table1[[#This Row],[Status Detail]]="ACTIVE"),"yes","no") -> no | O52: Sandwich | P52: Escada | Q52: To discuss with Oscar | R52: ACTIVE | S52: Oscar Vale | U52: oscar.vale@partilhextrema.pt | V52: 912253249 | W52: =IF(Table1[[#This Row],[Maintenance]]="yes",IF(OR(Table1[[#This Row],[Start Contract]]="",Table1[[#This Row],[Duration Month2]]=""),"",EDATE(Table1[[#This Row],[Start Contract]],Table1[[#This Row],[Duration Month2]])),"-") -> - | X52: =IF(OR((W52=""),(W52="-")),"",YEAR(Table1[[#This Row],[End Contract]])) | Y52: =IF(Table1[[#This Row],[Maintenance]]="yes",IF(Table1[[#This Row],[End Contract]]="","no",IF(TODAY()<=Table1[[#This Row],[End Contract]],"yes","no")),"no") -> no
A53: 49 | B53: Vatel | C53: Vatel-Companhia De Produtos Alimentares S.A. | D53: 502644699 | E53: Av. dos Operários Conserveiros, Olhão | F53: Faro | G53: 288 | H53: 129.6 | I53: EPC | J53: Cliente | K53: 0 | L53: =Table1[[#This Row],[Duration]]*12 -> 0 | M53: 44986 | N53: yes | O53: Sandwich | P53: Escada | Q53: Maintenance contract | R53: ACTIVE | S53: Rui Branco | U53: rui.branco@k-plus-s.com | V53: 289710168 | W53: =IF(Table1[[#This Row],[Maintenance]]="yes",IF(OR(Table1[[#This Row],[Start Contract]]="",Table1[[#This Row],[Duration Month2]]=""),"",EDATE(Table1[[#This Row],[Start Contract]],Table1[[#This Row],[Duration Month2]])),"-") -> 44986 | X53: =IF(OR((W53=""),(W53="-")),"",YEAR(Table1[[#This Row],[End Contract]])) -> 2023 | Y53: =IF(Table1[[#This Row],[Maintenance]]="yes",IF(Table1[[#This Row],[End Contract]]="","no",IF(TODAY()<=Table1[[#This Row],[End Contract]],"yes","no")),"no") -> no | Z53: Não ha registo de contrato estar renovado | AA53: ? | AB53: O&M
A54: 50 | B54: Tecnisata | C54: Tecnisata - Indústria Metalomecânica S.A. | D54: 500280614 | E54: Rua dos seteais nº1 Algueirão, 2725-658 Nem Martins | F54: Lisboa | G54: 270 | H54: 147.15 | I54: ESCO | J54: Solcorelios | K54: 15 | L54: =Table1[[#This Row],[Duration]]*12 -> 180 | M54: 44927 | N54: =IF(AND(Table1[[#This Row],[ Type of Contract]]="ESCO",Table1[[#This Row],[Status Detail]]="ACTIVE"),"yes","no") -> yes | O54: Sandwich | P54: Escada | R54: ACTIVE | S54: Maria Helena Pereira Filipe / Pedro Miguel Ribeiro Teixeira | T54: Vogal do Conselho de Administração | U54: tecnisata@tecnisata.pt | V54: 910081951 | W54: =IF(Table1[[#This Row],[Maintenance]]="yes",IF(OR(Table1[[#This Row],[Start Contract]]="",Table1[[#This Row],[Duration Month2]]=""),"",EDATE(Table1[[#This Row],[Start Contract]],Table1[[#This Row],[Duration Month2]])),"-") -> 50406 | X54: =IF(OR((W54=""),(W54="-")),"",YEAR(Table1[[#This Row],[End Contract]])) -> 2038 | Y54: =IF(Table1[[#This Row],[Maintenance]]="yes",IF(Table1[[#This Row],[End Contract]]="","no",IF(TODAY()<=Table1[[#This Row],[End Contract]],"yes","no")),"no") -> yes | AA54: - | AB54: Tarifa
A55: 51 | B55: Moviportas 1 - Sede | C55: Moviportas-Fábrica De Móveis E Portas De Rio De Couros Lda | D55: 500441731 | E55: Rio de Couros 2435 – 530 Rio de Couros | F55: Santarém | G55: 270 | H55: 147.15 | I55: EPC | J55: Cliente | K55: 0 | L55: =Table1[[#This Row],[Duration]]*12 -> 0 | M55: - | N55: =IF(AND(Table1[[#This Row],[ Type of Contract]]="ESCO",Table1[[#This Row],[Status Detail]]="ACTIVE"),"yes","no") -> no | O55: Sandwich | P55: Escada | Q55: To discuss with the client | R55: ACTIVE | S55: Joaquim Marques Gomes | T55: Gerente | U55: moviportas@gmail.com | V55: 919840229 | W55: =IF(Table1[[#This Row],[Maintenance]]="yes",IF(OR(Table1[[#This Row],[Start Contract]]="",Table1[[#This Row],[Duration Month2]]=""),"",EDATE(Table1[[#This Row],[Start Contract]],Table1[[#This Row],[Duration Month2]])),"-") -> - | X55: =IF(OR((W55=""),(W55="-")),"",YEAR(Table1[[#This Row],[End Contract]])) | Y55: =IF(Table1[[#This Row],[Maintenance]]="yes",IF(Table1[[#This Row],[End Contract]]="","no",IF(TODAY()<=Table1[[#This Row],[End Contract]],"yes","no")),"no") -> no
A56: 52 | B56: Moviportas 2 | C56: Moviportas-Fábrica De Móveis E Portas De Rio De Couros Lda | D56: 500441731 | E56: Zona Industrial Do Camprez, Chão De Couce, 3240-509 Ansião | F56: Leiria | G56: 85 | H56: 43.325 | I56: EPC | J56: Cliente | K56: 0 | L56: =Table1[[#This Row],[Duration]]*12 -> 0 | M56: - | N56: =IF(AND(Table1[[#This Row],[ Type of Contract]]="ESCO",Table1[[#This Row],[Status Detail]]="ACTIVE"),"yes","no") -> no | O56: Sandwich | P56: Escada | Q56: To discuss with the client | R56: ACTIVE | S56: Joaquim Marques Gomes | T56: Gerente | U56: moviportas@gmail.com | V56: 919840229 | W56: =IF(Table1[[#This Row],[Maintenance]]="yes",IF(OR(Table1[[#This Row],[Start Contract]]="",Table1[[#This Row],[Duration Month2]]=""),"",EDATE(Table1[[#This Row],[Start Contract]],Table1[[#This Row],[Duration Month2]])),"-") -> - | X56: =IF(OR((W56=""),(W56="-")),"",YEAR(Table1[[#This Row],[End Contract]])) | Y56: =IF(Table1[[#This Row],[Maintenance]]="yes",IF(Table1[[#This Row],[End Contract]]="","no",IF(TODAY()<=Table1[[#This Row],[End Contract]],"yes","no")),"no") -> no
A57: 53 | B57: Moviportas 3 - casa | C57: Moviportas-Fábrica De Móveis E Portas De Rio De Couros Lda | D57: 0 | F57: Santarém | G57: 18 | H57: 8.1 | I57: EPC | J57: Cliente | K57: 0 | L57: =Table1[[#This Row],[Duration]]*12 -> 0 | M57: - | N57: =IF(AND(Table1[[#This Row],[ Type of Contract]]="ESCO",Table1[[#This Row],[Status Detail]]="ACTIVE"),"yes","no") -> no | O57: Sandwich | P57: Escada | Q57: To discuss with the client | R57: ACTIVE | S57: Joaquim Marques Gomes | T57: Gerente | U57: moviportas@gmail.com | V57: 919840229 | W57: =IF(Table1[[#This Row],[Maintenance]]="yes",IF(OR(Table1[[#This Row],[Start Contract]]="",Table1[[#This Row],[Duration Month2]]=""),"",EDATE(Table1[[#This Row],[Start Contract]],Table1[[#This Row],[Duration Month2]])),"-") -> - | X57: =IF(OR((W57=""),(W57="-")),"",YEAR(Table1[[#This Row],[End Contract]])) | Y57: =IF(Table1[[#This Row],[Maintenance]]="yes",IF(Table1[[#This Row],[End Contract]]="","no",IF(TODAY()<=Table1[[#This Row],[End Contract]],"yes","no")),"no") -> no
A58: 54 | B58: Homeupdate | C58: Homeupdate, Lda | D58: 510504965 | E58: Rua da Citela 10, Terrugem | F58: Sintra | G58: 180 | H58: 81 | I58: ESCO | J58: Solcorelios | K58: 10 | L58: =Table1[[#This Row],[Duration]]*12 -> 120 | M58: 44927 | N58: =IF(AND(Table1[[#This Row],[ Type of Contract]]="ESCO",Table1[[#This Row],[Status Detail]]="ACTIVE"),"yes","no") -> yes | O58: Sandwich | P58: Escada | R58: ACTIVE | S58: Joaquim Marques Gomes | T58: Gerente | U58: sandra.ferreira@homeupdate.pt | V58: 935522884 | W58: =IF(Table1[[#This Row],[Maintenance]]="yes",IF(OR(Table1[[#This Row],[Start Contract]]="",Table1[[#This Row],[Duration Month2]]=""),"",EDATE(Table1[[#This Row],[Start Contract]],Table1[[#This Row],[Duration Month2]])),"-") -> 48580 | X58: =IF(OR((W58=""),(W58="-")),"",YEAR(Table1[[#This Row],[End Contract]])) -> 2033 | Y58: =IF(Table1[[#This Row],[Maintenance]]="yes",IF(Table1[[#This Row],[End Contract]]="","no",IF(TODAY()<=Table1[[#This Row],[End Contract]],"yes","no")),"no") -> yes | AA58: - | AB58: Tarifa
A59: 55 | B59: ELS Guia | C59: Estevão Luis Salvador Lda | D59: 502786639 | E59: Zona Industrial de Laundos 39, 4570-311 Laundos / Estufas agrícolas, Estrada de Valverde – Baiãs, 8200-429 Guia, Albufeira | F59: Algarve | G59: 94 | H59: 116.64 | I59: EPC | J59: Cliente | K59: 0 | L59: =Table1[[#This Row],[Duration]]*12 -> 0 | M59: 44798 | N59: =IF(AND(Table1[[#This Row],[ Type of Contract]]="ESCO",Table1[[#This Row],[Status Detail]]="ACTIVE"),"yes","no") -> no | O59: Sandwich | P59: Escada | Q59: To discuss with Oscar | R59: ACTIVE | S59: Oscar Vale | U59: oscar.vale@partilhextrema.pt | V59: 912253249 | W59: =IF(Table1[[#This Row],[Maintenance]]="yes",IF(OR(Table1[[#This Row],[Start Contract]]="",Table1[[#This Row],[Duration Month2]]=""),"",EDATE(Table1[[#This Row],[Start Contract]],Table1[[#This Row],[Duration Month2]])),"-") -> - | X59: =IF(OR((W59=""),(W59="-")),"",YEAR(Table1[[#This Row],[End Contract]])) | Y59: =IF(Table1[[#This Row],[Maintenance]]="yes",IF(Table1[[#This Row],[End Contract]]="","no",IF(TODAY()<=Table1[[#This Row],[End Contract]],"yes","no")),"no") -> no
A60: 56 | B60: Dayton Progress | C60: Dayton Progress - Perfuradores, Lda | D60: 505416921 | E60: Zona Industrial do Casal da Areia, Lote 17, Casal da Areia 2460-392 Alcobaça | F60: Leiria | G60: 560 | H60: 336 | I60: ESCO | J60: Solcorelios | K60: 10 | L60: =Table1[[#This Row],[Duration]]*12 -> 120 | M60: 45786 | N60: =IF(AND(Table1[[#This Row],[ Type of Contract]]="ESCO",Table1[[#This Row],[Status Detail]]="ACTIVE"),"yes","no") -> yes | O60: Sandwich | P60: Escada | R60: ACTIVE | S60: João Miguel Correia Pascoal | T60: Gerente | U60: JPascoal@daytonprogress.pt / Carolino@daytonprogress.pt | V60: . | W60: =IF(Table1[[#This Row],[Maintenance]]="yes",IF(OR(Table1[[#This Row],[Start Contract]]="",Table1[[#This Row],[Duration Month2]]=""),"",EDATE(Table1[[#This Row],[Start Contract]],Table1[[#This Row],[Duration Month2]])),"-") -> 49438 | X60: =IF(OR((W60=""),(W60="-")),"",YEAR(Table1[[#This Row],[End Contract]])) -> 2035 | Y60: =IF(Table1[[#This Row],[Maintenance]]="yes",IF(Table1[[#This Row],[End Contract]]="","no",IF(TODAY()<=Table1[[#This Row],[End Contract]],"yes","no")),"no") -> yes | AA60: 2352 | AB60: O&M
A61: 57 | B61: RAP Industrial | C61: Rap - Industrial Lda | D61: 506178374 | E61: Avenida do Brasil, 231 – São João da Madeira – Aveiro – 3700-070 | F61: São João da Madeira | G61: 168 | H61: 91.56 | I61: ESCO | J61: Solcorelios | K61: 15 | L61: =Table1[[#This Row],[Duration]]*12 -> 180 | M61: 44896 | N61: =IF(AND(Table1[[#This Row],[ Type of Contract]]="ESCO",Table1[[#This Row],[Status Detail]]="ACTIVE"),"yes","no") -> yes | O61: Sandwich | P61: Escada | R61: ACTIVE | S61: Manuel Augusto Silva Tavares | T61: Gerente | U61: manueltavares@arautorap.com / pedrotavares@arautorap.com | V61: 966938380 | W61: =IF(Table1[[#This Row],[Maintenance]]="yes",IF(OR(Table1[[#This Row],[Start Contract]]="",Table1[[#This Row],[Duration Month2]]=""),"",EDATE(Table1[[#This Row],[Start Contract]],Table1[[#This Row],[Duration Month2]])),"-") -> 50375 | X61: =IF(OR((W61=""),(W61="-")),"",YEAR(Table1[[#This Row],[End Contract]])) -> 2037 | Y61: =IF(Table1[[#This Row],[Maintenance]]="yes",IF(Table1[[#This Row],[End Contract]]="","no",IF(TODAY()<=Table1[[#This Row],[End Contract]],"yes","no")),"no") -> yes | AA61: - | AB61: Tarifa
A62: 58 | B62: DRA Detergentes | I62: ESCO | J62: Solcorelios | L62: =Table1[[#This Row],[Duration]]*12 -> 0 | N62: =IF(AND(Table1[[#This Row],[ Type of Contract]]="ESCO",Table1[[#This Row],[Status Detail]]="ACTIVE"),"yes","no") -> no | R62: CANCELLED | W62: =IF(Table1[[#This Row],[Maintenance]]="yes",IF(OR(Table1[[#This Row],[Start Contract]]="",Table1[[#This Row],[Duration Month2]]=""),"",EDATE(Table1[[#This Row],[Start Contract]],Table1[[#This Row],[Duration Month2]])),"-") -> - | X62: =IF(OR((W62=""),(W62="-")),"",YEAR(Table1[[#This Row],[End Contract]])) | Y62: =IF(Table1[[#This Row],[Maintenance]]="yes",IF(Table1[[#This Row],[End Contract]]="","no",IF(TODAY()<=Table1[[#This Row],[End Contract]],"yes","no")),"no") -> no
A63: 59 | B63: Corkplas Armazém 21 | C63: Corkplas - Indústria De Transformação E Comércio De Plásticos E Derivados De Cortiça Lda | D63: 506252914 | E63: Estrada de Manique, Alcabideche, 2645-999 Cascais | F63: Lisboa | G63: 30 | H63: 16.4 | I63: EPC | J63: Cliente | K63: 0 | L63: =Table1[[#This Row],[Duration]]*12 -> 0 | M63: - | N63: =IF(AND(Table1[[#This Row],[ Type of Contract]]="ESCO",Table1[[#This Row],[Status Detail]]="ACTIVE"),"yes","no") -> no | O63: Sandwich | P63: Escada | Q63: To discuss with the client | R63: ACTIVE | S63: Nuno Miguel Laginha Catarino dos Santos | T63: Gerente | W63: =IF(Table1[[#This Row],[Maintenance]]="yes",IF(OR(Table1[[#This Row],[Start Contract]]="",Table1[[#This Row],[Duration Month2]]=""),"",EDATE(Table1[[#This Row],[Start Contract]],Table1[[#This Row],[Duration Month2]])),"-") -> - | X63: =IF(OR((W63=""),(W63="-")),"",YEAR(Table1[[#This Row],[End Contract]])) | Y63: =IF(Table1[[#This Row],[Maintenance]]="yes",IF(Table1[[#This Row],[End Contract]]="","no",IF(TODAY()<=Table1[[#This Row],[End Contract]],"yes","no")),"no") -> no
A64: 60 | B64: Corkplas Armazém 13 | C64: Corkplas - Indústria De Transformação E Comércio De Plásticos E Derivados De Cortiça Lda | D64: 506252914 | E64: Estrada de Manique, Alcabideche, 2645-999 Cascais | F64: Lisboa | G64: 56 | H64: 30.5 | I64: EPC | J64: Cliente | K64: 0 | L64: =Table1[[#This Row],[Duration]]*12 -> 0 | M64: - | N64: =IF(AND(Table1[[#This Row],[ Type of Contract]]="ESCO",Table1[[#This Row],[Status Detail]]="ACTIVE"),"yes","no") -> no | O64: Sandwich | P64: Escada | Q64: To discuss with the client | R64: ACTIVE | S64: Nuno Miguel Laginha Catarino dos Santos | T64: Gerente | W64: =IF(Table1[[#This Row],[Maintenance]]="yes",IF(OR(Table1[[#This Row],[Start Contract]]="",Table1[[#This Row],[Duration Month2]]=""),"",EDATE(Table1[[#This Row],[Start Contract]],Table1[[#This Row],[Duration Month2]])),"-") -> - | X64: =IF(OR((W64=""),(W64="-")),"",YEAR(Table1[[#This Row],[End Contract]])) | Y64: =IF(Table1[[#This Row],[Maintenance]]="yes",IF(Table1[[#This Row],[End Contract]]="","no",IF(TODAY()<=Table1[[#This Row],[End Contract]],"yes","no")),"no") -> no
A65: 61 | B65: Jeteprodesing | C65: Jeteprodesign, Lda | D65: 510808212 | E65: Rua Eduardo Paul, nº 520, Lugar de Lações de Baixo | G65: 182 | H65: 81.9 | I65: ESCO | J65: Solcorelios | K65: 15 | L65: =Table1[[#This Row],[Duration]]*12 -> 180 | N65: =IF(AND(Table1[[#This Row],[ Type of Contract]]="ESCO",Table1[[#This Row],[Status Detail]]="ACTIVE"),"yes","no") -> no | R65: ON HOLD | S65: Gabriel Fernando da Costa Fortuna /Adelino da Costa Sá | T65: Gerente | U65: geral@jeteprodesign.com / gabriel.fortuna@jeteprodesign.com | V65: . | W65: =IF(Table1[[#This Row],[Maintenance]]="yes",IF(OR(Table1[[#This Row],[Start Contract]]="",Table1[[#This Row],[Duration Month2]]=""),"",EDATE(Table1[[#This Row],[Start Contract]],Table1[[#This Row],[Duration Month2]])),"-") -> - | X65: =IF(OR((W65=""),(W65="-")),"",YEAR(Table1[[#This Row],[End Contract]])) | Y65: =IF(Table1[[#This Row],[Maintenance]]="yes",IF(Table1[[#This Row],[End Contract]]="","no",IF(TODAY()<=Table1[[#This Row],[End Contract]],"yes","no")),"no") -> no
A66: 62 | B66: BV Arruda dos Vinhos | C66: Associação Dos Bombeiros Voluntarios De Arruda Dos Vinhos | D66: 501137092 | E66: Rua Luís Camões s/n, 2630-253 Arruda dos Vinhos, Portugal | F66: Arruda dos Vinhos | G66: 54 | H66: 29.43 | I66: ESCO | J66: Solcorelios | K66: 15 | L66: =Table1[[#This Row],[Duration]]*12 -> 180 | M66: 44927 | N66: =IF(AND(Table1[[#This Row],[ Type of Contract]]="ESCO",Table1[[#This Row],[Status Detail]]="ACTIVE"),"yes","no") -> yes | O66: Sandwich | P66: Plataforma Elevatória dos Bombeiros | R66: ACTIVE | S66: Rui José dos santos silva / Carla José Granja Lima e sílva | T66: Presidenye da direção / Tesoureiro da direção | U66: secretaria@bv-arruda.pt | V66: 263975114 917601545 | W66: =IF(Table1[[#This Row],[Maintenance]]="yes",IF(OR(Table1[[#This Row],[Start Contract]]="",Table1[[#This Row],[Duration Month2]]=""),"",EDATE(Table1[[#This Row],[Start Contract]],Table1[[#This Row],[Duration Month2]])),"-") -> 50406 | X66: =IF(OR((W66=""),(W66="-")),"",YEAR(Table1[[#This Row],[End Contract]])) -> 2038 | Y66: =IF(Table1[[#This Row],[Maintenance]]="yes",IF(Table1[[#This Row],[End Contract]]="","no",IF(TODAY()<=Table1[[#This Row],[End Contract]],"yes","no")),"no") -> yes | AA66: - | AB66: Tarifa
A67: 63 | B67: Encontrus | C67: Encontrus-Sociedade Hoteleira Lda | D67: 502930942 | E67: Rua Afonso Marques, Nº 4 3430-004 Carregal do Sal | F67: Carregal do Sal | G67: 124 | H67: 67.58 | I67: ESCO | J67: Solcorelios | K67: 15 | L67: =Table1[[#This Row],[Duration]]*12 -> 180 | M67: 45017 | N67: =IF(AND(Table1[[#This Row],[ Type of Contract]]="ESCO",Table1[[#This Row],[Status Detail]]="ACTIVE"),"yes","no") -> yes | O67: Sandwich | P67: Escada | R67: ACTIVE | S67: João Carlos de Figueiredo Alves | T67: Gerente | U67: financeiro@encontrus.com / nunoalves@encontrus.com | V67: 967139306 | W67: =IF(Table1[[#This Row],[Maintenance]]="yes",IF(OR(Table1[[#This Row],[Start Contract]]="",Table1[[#This Row],[Duration Month2]]=""),"",EDATE(Table1[[#This Row],[Start Contract]],Table1[[#This Row],[Duration Month2]])),"-") -> 50496 | X67: =IF(OR((W67=""),(W67="-")),"",YEAR(Table1[[#This Row],[End Contract]])) -> 2038 | Y67: =IF(Table1[[#This Row],[Maintenance]]="yes",IF(Table1[[#This Row],[End Contract]]="","no",IF(TODAY()<=Table1[[#This Row],[End Contract]],"yes","no")),"no") -> yes | AA67: - | AB67: Tarifa
A68: 64 | B68: Licofrutos | C68: Licofrutos, Unipessoal Lda | D68: 509090990 | E68: Rua da Vitória, 18, lj 1, Boavista - Bombarral – Leiria – 2540-575 | F68: Óbidos - Leiria | G68: 160 | H68: 72 | I68: ESCO | J68: Solcorelios | K68: 10 | L68: =Table1[[#This Row],[Duration]]*12 -> 120 | M68: 44896 | N68: =IF(AND(Table1[[#This Row],[ Type of Contract]]="ESCO",Table1[[#This Row],[Status Detail]]="ACTIVE"),"yes","no") -> yes | O68: Sandwich | P68: Escada | R68: ACTIVE | S68: João Manuel Correia Rodrigues | T68: Gerente | U68: licofrutos@gmail.com | V68: 936174154 | W68: =IF(Table1[[#This Row],[Maintenance]]="yes",IF(OR(Table1[[#This Row],[Start Contract]]="",Table1[[#This Row],[Duration Month2]]=""),"",EDATE(Table1[[#This Row],[Start Contract]],Table1[[#This Row],[Duration Month2]])),"-") -> 48549 | X68: =IF(OR((W68=""),(W68="-")),"",YEAR(Table1[[#This Row],[End Contract]])) -> 2032 | Y68: =IF(Table1[[#This Row],[Maintenance]]="yes",IF(Table1[[#This Row],[End Contract]]="","no",IF(TODAY()<=Table1[[#This Row],[End Contract]],"yes","no")),"no") -> yes | AA68: - | AB68: Tarifa
A69: 65 | B69: Pancrisp | C69: Pancrisp-Industria De Panificação Lda | D69: 502680296 | E69: Rua Casais de S. Gião, N.º 21, Torres Vedras 2560-249 Torres Vedras | F69: Leiria | G69: 306 | H69: 137.7 | I69: ESCO | J69: Solcorelios | K69: 20 | L69: =Table1[[#This Row],[Duration]]*12 -> 240 | M69: 45108 | N69: =IF(AND(Table1[[#This Row],[ Type of Contract]]="ESCO",Table1[[#This Row],[Status Detail]]="ACTIVE"),"yes","no") -> yes | O69: Carport e Sandwich | P69: Escada | R69: ACTIVE | S69: Fernando Crispim / Ângela (secretaria) | T69: Gerente / secretaria | U69: fjfcrispim@sapo.pt | V69: 914731811 | W69: =IF(Table1[[#This Row],[Maintenance]]="yes",IF(OR(Table1[[#This Row],[Start Contract]]="",Table1[[#This Row],[Duration Month2]]=""),"",EDATE(Table1[[#This Row],[Start Contract]],Table1[[#This Row],[Duration Month2]])),"-") -> 52413 | X69: =IF(OR((W69=""),(W69="-")),"",YEAR(Table1[[#This Row],[End Contract]])) -> 2043 | Y69: =IF(Table1[[#This Row],[Maintenance]]="yes",IF(Table1[[#This Row],[End Contract]]="","no",IF(TODAY()<=Table1[[#This Row],[End Contract]],"yes","no")),"no") -> yes | AA69: - | AB69: Tarifa
A70: 66 | B70: Barbotina | C70: Barbotina-Fábrica de Artigos Cerâmicos S.A | D70: 502295147 | E70: Rua Indústria, 16, Freguesia de Oliveira do Bairro, Distrito de Aveiro | H70: 441.5 | I70: ESCO | J70: Solcorelios | K70: 10 | L70: =Table1[[#This Row],[Duration]]*12 -> 120 | N70: =IF(AND(Table1[[#This Row],[ Type of Contract]]="ESCO",Table1[[#This Row],[Status Detail]]="ACTIVE"),"yes","no") -> no | R70: CANCELLED | S70: António José Santiago dos Reis Moita | T70: Administrador único | U70: antonio@barbotina.com | W70: =IF(Table1[[#This Row],[Maintenance]]="yes",IF(OR(Table1[[#This Row],[Start Contract]]="",Table1[[#This Row],[Duration Month2]]=""),"",EDATE(Table1[[#This Row],[Start Contract]],Table1[[#This Row],[Duration Month2]])),"-") -> - | X70: =IF(OR((W70=""),(W70="-")),"",YEAR(Table1[[#This Row],[End Contract]])) | Y70: =IF(Table1[[#This Row],[Maintenance]]="yes",IF(Table1[[#This Row],[End Contract]]="","no",IF(TODAY()<=Table1[[#This Row],[End Contract]],"yes","no")),"no") -> no
A71: 67 | B71: ITECMO | C71: Itecmo - Indústria De Fabricação De Moldes Lda | D71: 501493603 | E71: Rua da Figueirinha nº6, Telheiro | F71: Leiria | G71: 225 | H71: 101.25 | I71: ESCO | J71: Solcorelios | K71: 15 | L71: =Table1[[#This Row],[Duration]]*12 -> 180 | M71: 44958 | N71: =IF(AND(Table1[[#This Row],[ Type of Contract]]="ESCO",Table1[[#This Row],[Status Detail]]="ACTIVE"),"yes","no") -> yes | O71: Sandwich | P71: Escada | R71: ACTIVE | S71: Miguel da Silva Ascenso / Paulo Cristóvão da Silva Pinto | T71: Gerente | U71: m.ascenso@itecmo.pt / itecmo@itecmo.pt | V71: 914330176 | W71: =IF(Table1[[#This Row],[Maintenance]]="yes",IF(OR(Table1[[#This Row],[Start Contract]]="",Table1[[#This Row],[Duration Month2]]=""),"",EDATE(Table1[[#This Row],[Start Contract]],Table1[[#This Row],[Duration Month2]])),"-") -> 50437 | X71: =IF(OR((W71=""),(W71="-")),"",YEAR(Table1[[#This Row],[End Contract]])) -> 2038 | Y71: =IF(Table1[[#This Row],[Maintenance]]="yes",IF(Table1[[#This Row],[End Contract]]="","no",IF(TODAY()<=Table1[[#This Row],[End Contract]],"yes","no")),"no") -> yes | AA71: - | AB71: Tarifa
A72: 68 | B72: Real Sport Clube | C72: Real Sport Clube | D72: 501084819 | E72: Rua Cidade Desportiva, S/N Monte Abraão 2745-012 | F72: Massamá | G72: 112 | H72: 61.4 | I72: ESCO | J72: Solcorelios | K72: 10 | L72: =Table1[[#This Row],[Duration]]*12 -> 120 | M72: 45108 | N72: =IF(AND(Table1[[#This Row],[ Type of Contract]]="ESCO",Table1[[#This Row],[Status Detail]]="ACTIVE"),"yes","no") -> yes | O72: Cobertura Plana | P72: Acesso pela cobertura | R72: ACTIVE | S72: José Adelino Marques Ramos / Francisco José Ferreira de Lima Freire | T72: Presidente / Vice-Presidente Financeiro | U72: departamentofinanceiro@realsportclube.com | V72: 969011518 926656720 919778199 | W72: =IF(Table1[[#This Row],[Maintenance]]="yes",IF(OR(Table1[[#This Row],[Start Contract]]="",Table1[[#This Row],[Duration Month2]]=""),"",EDATE(Table1[[#This Row],[Start Contract]],Table1[[#This Row],[Duration Month2]])),"-") -> 48761 | X72: =IF(OR((W72=""),(W72="-")),"",YEAR(Table1[[#This Row],[End Contract]])) -> 2033 | Y72: =IF(Table1[[#This Row],[Maintenance]]="yes",IF(Table1[[#This Row],[End Contract]]="","no",IF(TODAY()<=Table1[[#This Row],[End Contract]],"yes","no")),"no") -> yes | AA72: - | AB72: Tarifa
A73: 69 | B73: Agrovácuo | C73: Agrovácuo Preparação E Embalagem De Produtos Horticolas Lda | D73: 505248417 | E73: R. Jornal de Sintra, 2710-450 Sintra | F73: Lisboa | G73: 94 | H73: 42.3 | I73: EPC | J73: Cliente | L73: =Table1[[#This Row],[Duration]]*12 -> 0 | M73: - | N73: =IF(AND(Table1[[#This Row],[ Type of Contract]]="ESCO",Table1[[#This Row],[Status Detail]]="ACTIVE"),"yes","no") -> no | O73: Sandwich | P73: Escada | Q73: To discuss with the client | R73: ACTIVE | S73: Gonçalo Manuel Duarte Simões | T73: Gerente | V73: 965352795 | W73: =IF(Table1[[#This Row],[Maintenance]]="yes",IF(OR(Table1[[#This Row],[Start Contract]]="",Table1[[#This Row],[Duration Month2]]=""),"",EDATE(Table1[[#This Row],[Start Contract]],Table1[[#This Row],[Duration Month2]])),"-") -> - | X73: =IF(OR((W73=""),(W73="-")),"",YEAR(Table1[[#This Row],[End Contract]])) | Y73: =IF(Table1[[#This Row],[Maintenance]]="yes",IF(Table1[[#This Row],[End Contract]]="","no",IF(TODAY()<=Table1[[#This Row],[End Contract]],"yes","no")),"no") -> no
A74: 70 | B74: Maryasa | C74: Maryasa - Importação E Exportação, Unipessoal Lda | D74: 510352855 | E74: Rua 1º de Maio, 409 Fracção A e B 3700-541 Arrifana Vfr | F74: São João da Madeira | G74: 384 | H74: 172.8 | I74: ESCO | J74: Solcorelios | K74: 15 | L74: =Table1[[#This Row],[Duration]]*12 -> 180 | M74: 45108 | N74: =IF(AND(Table1[[#This Row],[ Type of Contract]]="ESCO",Table1[[#This Row],[Status Detail]]="ACTIVE"),"yes","no") -> yes | O74: Sandwich | P74: Escada | R74: ACTIVE | S74: Manuel Andrade Ferreira da Silva | T74: Gerente | U74: geral@maryasa.com / producao@maryasa.com | V74: 966371326 | W74: =IF(Table1[[#This Row],[Maintenance]]="yes",IF(OR(Table1[[#This Row],[Start Contract]]="",Table1[[#This Row],[Duration Month2]]=""),"",EDATE(Table1[[#This Row],[Start Contract]],Table1[[#This Row],[Duration Month2]])),"-") -> 50587 | X74: =IF(OR((W74=""),(W74="-")),"",YEAR(Table1[[#This Row],[End Contract]])) -> 2038 | Y74: =IF(Table1[[#This Row],[Maintenance]]="yes",IF(Table1[[#This Row],[End Contract]]="","no",IF(TODAY()<=Table1[[#This Row],[End Contract]],"yes","no")),"no") -> yes | AA74: - | AB74: Tarifa
A75: 71 | B75: Diaco Agriloja Expanção | C75: Diamantino Coelho & Filho S.A. | D75: 502099666 | E75: Marmelais de Baixo Nº43, 2300-4O1 Tomar | F75: Santarém | H75: 30.1 | I75: EPC | J75: Cliente | K75: 0 | L75: =Table1[[#This Row],[Duration]]*12 -> 0 | M75: - | N75: =IF(AND(Table1[[#This Row],[ Type of Contract]]="ESCO",Table1[[#This Row],[Status Detail]]="ACTIVE"),"yes","no") -> no | O75: Sandwich | P75: Escada | Q75: To discuss with the client | R75: ACTIVE | S75: Carlos Manuel Vicente Coelho | T75: Predidente | V75: 932255257 916597424 | W75: =IF(Table1[[#This Row],[Maintenance]]="yes",IF(OR(Table1[[#This Row],[Start Contract]]="",Table1[[#This Row],[Duration Month2]]=""),"",EDATE(Table1[[#This Row],[Start Contract]],Table1[[#This Row],[Duration Month2]])),"-") -> - | X75: =IF(OR((W75=""),(W75="-")),"",YEAR(Table1[[#This Row],[End Contract]])) | Y75: =IF(Table1[[#This Row],[Maintenance]]="yes",IF(Table1[[#This Row],[End Contract]]="","no",IF(TODAY()<=Table1[[#This Row],[End Contract]],"yes","no")),"no") -> no
A76: 71 | B76: Diaco Expansão | C76: Diamantino Coelho & Filho S.A. | D76: 502099666 | E76: Rua Zona Industrial - C/C 20 Bajo Santa Cita Santarém | F76: Santarém | G76: 66 | H76: 35.97 | I76: EPC | J76: Cliente | K76: 0 | L76: =Table1[[#This Row],[Duration]]*12 -> 0 | M76: - | N76: =IF(AND(Table1[[#This Row],[ Type of Contract]]="ESCO",Table1[[#This Row],[Status Detail]]="ACTIVE"),"yes","no") -> no | O76: Sandwich | P76: Escada | Q76: To discuss with the client | R76: ACTIVE | S76: Carlos Manuel Vicente Coelho | T76: Predidente | V76: 932255257 916597424 | W76: =IF(Table1[[#This Row],[Maintenance]]="yes",IF(OR(Table1[[#This Row],[Start Contract]]="",Table1[[#This Row],[Duration Month2]]=""),"",EDATE(Table1[[#This Row],[Start Contract]],Table1[[#This Row],[Duration Month2]])),"-") -> - | X76: =IF(OR((W76=""),(W76="-")),"",YEAR(Table1[[#This Row],[End Contract]])) | Y76: =IF(Table1[[#This Row],[Maintenance]]="yes",IF(Table1[[#This Row],[End Contract]]="","no",IF(TODAY()<=Table1[[#This Row],[End Contract]],"yes","no")),"no") -> no
A77: 71 | B77: Diaco Fabrica 2 | C77: Diamantino Coelho & Filho S.A. | D77: 502099666 | E77: Rua Principal – Lt 16 Santarém | F77: Santarém | G77: 704 | H77: 316.8 | I77: EPC | J77: Cliente | K77: 0 | L77: =Table1[[#This Row],[Duration]]*12 -> 0 | M77: 44958 | N77: =IF(AND(Table1[[#This Row],[ Type of Contract]]="ESCO",Table1[[#This Row],[Status Detail]]="ACTIVE"),"yes","no") -> no | O77: Sandwich | P77: Escada | Q77: To discuss with the client | R77: ACTIVE | S77: Carlos Manuel Vicente Coelho | T77: Predidente | V77: 932255257 916597424 | W77: =IF(Table1[[#This Row],[Maintenance]]="yes",IF(OR(Table1[[#This Row],[Start Contract]]="",Table1[[#This Row],[Duration Month2]]=""),"",EDATE(Table1[[#This Row],[Start Contract]],Table1[[#This Row],[Duration Month2]])),"-") -> - | X77: =IF(OR((W77=""),(W77="-")),"",YEAR(Table1[[#This Row],[End Contract]])) | Y77: =IF(Table1[[#This Row],[Maintenance]]="yes",IF(Table1[[#This Row],[End Contract]]="","no",IF(TODAY()<=Table1[[#This Row],[End Contract]],"yes","no")),"no") -> no
A78: 72 | B78: Casa da Divina Providência e Maria Auxiliadora | C78: Casa Da Divina Providencia E De Maria Auxiliadora(Centro Paroquial De Safara) | D78: 502312254 | E78: Rua da Divina Providência 7875-054 Safara | F78: Safara | G78: 92 | H78: 50.6 | I78: ESCO | J78: Solcorelios II | K78: 15 | L78: =Table1[[#This Row],[Duration]]*12 -> 180 | M78: 45078 | N78: =IF(AND(Table1[[#This Row],[ Type of Contract]]="ESCO",Table1[[#This Row],[Status Detail]]="ACTIVE"),"yes","no") -> yes | O78: Solo | P78: Não é necessário | R78: ACTIVE | S78: Rui Luís Ferreira Sousa / Maria Almeida dos Santos Pereira Rodrigues / Florência Fonseca Valente | T78: Presidente / Secretária / Tesoureira | U78: geral@larsafara.pt | V78: 933261098 | W78: =IF(Table1[[#This Row],[Maintenance]]="yes",IF(OR(Table1[[#This Row],[Start Contract]]="",Table1[[#This Row],[Duration Month2]]=""),"",EDATE(Table1[[#This Row],[Start Contract]],Table1[[#This Row],[Duration Month2]])),"-") -> 50557 | X78: =IF(OR((W78=""),(W78="-")),"",YEAR(Table1[[#This Row],[End Contract]])) -> 2038 | Y78: =IF(Table1[[#This Row],[Maintenance]]="yes",IF(Table1[[#This Row],[End Contract]]="","no",IF(TODAY()<=Table1[[#This Row],[End Contract]],"yes","no")),"no") -> yes | AA78: 7601.76 | AB78: Fixa
A79: 73 | B79: S.C.M. Alpedrinha | C79: Santa Casa Da Misericordia De Alpedrinha | D79: 500986894 | E79: Rua Deao Boavida 9639 | F79: Castelo Branco | G79: 83 | H79: 40.67 | I79: ESCO | J79: Solcorelios II | K79: 15 | L79: =Table1[[#This Row],[Duration]]*12 -> 180 | M79: 44986 | N79: =IF(AND(Table1[[#This Row],[ Type of Contract]]="ESCO",Table1[[#This Row],[Status Detail]]="ACTIVE"),"yes","no") -> yes | O79: Telha | P79: Acesso pela cobertura | R79: ACTIVE | S79: Maria do Carmo Sanches de Oliveira / Luís dos Santos de Aguiar | T79: Provedora / Tesoureiro | U79: scmalpedrinha@sapo.pt | V79: 965360258 | W79: =IF(Table1[[#This Row],[Maintenance]]="yes",IF(OR(Table1[[#This Row],[Start Contract]]="",Table1[[#This Row],[Duration Month2]]=""),"",EDATE(Table1[[#This Row],[Start Contract]],Table1[[#This Row],[Duration Month2]])),"-") -> 50465 | X79: =IF(OR((W79=""),(W79="-")),"",YEAR(Table1[[#This Row],[End Contract]])) -> 2038 | Y79: =IF(Table1[[#This Row],[Maintenance]]="yes",IF(Table1[[#This Row],[End Contract]]="","no",IF(TODAY()<=Table1[[#This Row],[End Contract]],"yes","no")),"no") -> yes | AA79: 5447.28 | AB79: Fixa
A80: 74 | B80: ASCRECC - Lar da Cumieira | C80: Associação Sócio-Cultural Recreativa Educativa Da Cumieira E Circunvizinhas | D80: 503071625 | E80: Rua Principal, Nº 3, 3100-334 Pombal | F80: Leiria | G80: 104 | H80: 47.7 | I80: ESCO BUYOUT | J80: Solcorelios II | K80: 15 | L80: =Table1[[#This Row],[Duration]]*12 -> 180 | M80: 45047 | N80: =IF(AND(Table1[[#This Row],[ Type of Contract]]="ESCO",Table1[[#This Row],[Status Detail]]="ACTIVE"),"yes","no") -> no | O80: Telha | P80: Acesso pela cobertura | R80: ACTIVE | S80: Joaquim da Silva / António Vítor da Silva Lopes | T80: Presidente / Tesoureiro | U80: geral@acumieira.com | V80: 236212072 | W80: =IF(Table1[[#This Row],[Maintenance]]="yes",IF(OR(Table1[[#This Row],[Start Contract]]="",Table1[[#This Row],[Duration Month2]]=""),"",EDATE(Table1[[#This Row],[Start Contract]],Table1[[#This Row],[Duration Month2]])),"-") -> - | X80: =IF(OR((W80=""),(W80="-")),"",YEAR(Table1[[#This Row],[End Contract]])) | Y80: =IF(Table1[[#This Row],[Maintenance]]="yes",IF(Table1[[#This Row],[End Contract]]="","no",IF(TODAY()<=Table1[[#This Row],[End Contract]],"yes","no")),"no") -> no | AA80: 5018.88 | AB80: Fixa
A81: 75 | B81: Colégio São José de Bairros (EPC) | C81: Ângulos E Argumentos Lda | D81: 513003657 | E81: R. de Minas 132, 4620-219 | F81: Porto | G81: 78 | H81: 38.22 | I81: EPC | J81: Cliente | K81: 0 | L81: =Table1[[#This Row],[Duration]]*12 -> 0 | M81: 45078 | N81: =IF(AND(Table1[[#This Row],[ Type of Contract]]="ESCO",Table1[[#This Row],[Status Detail]]="ACTIVE"),"yes","no") -> no | O81: Cobertura Plana | P81: Escada Vertical | Q81: To discuss with Rui Nunes | R81: ACTIVE | S81: Rui Bessa | V81: 968700937 | W81: =IF(Table1[[#This Row],[Maintenance]]="yes",IF(OR(Table1[[#This Row],[Start Contract]]="",Table1[[#This Row],[Duration Month2]]=""),"",EDATE(Table1[[#This Row],[Start Contract]],Table1[[#This Row],[Duration Month2]])),"-") -> - | X81: =IF(OR((W81=""),(W81="-")),"",YEAR(Table1[[#This Row],[End Contract]])) | Y81: =IF(Table1[[#This Row],[Maintenance]]="yes",IF(Table1[[#This Row],[End Contract]]="","no",IF(TODAY()<=Table1[[#This Row],[End Contract]],"yes","no")),"no") -> no
A82: 76 | B82: SCM Entroncamento - Hospital S. Joao Batista (EPC) | C82: Santa Casa Da Misericordia Do Entroncamento | D82: 500876088 | E82: R. da Misericórdia, 2334-909 Entroncamento | F82: Santarém | G82: 182 | H82: 99 | I82: EPC | J82: Cliente | K82: 0 | L82: =Table1[[#This Row],[Duration]]*12 -> 0 | M82: 45017 | N82: =IF(AND(Table1[[#This Row],[ Type of Contract]]="ESCO",Table1[[#This Row],[Status Detail]]="ACTIVE"),"yes","no") -> no | O82: Telha/ Cobertura Plana | P82: Acesso pela cobertura | Q82: To discuss with Rui Nunes | R82: ACTIVE | S82: Vitor Bertelo / José Paulino Manutenção | V82: 939900147 / 913576424 | W82: =IF(Table1[[#This Row],[Maintenance]]="yes",IF(OR(Table1[[#This Row],[Start Contract]]="",Table1[[#This Row],[Duration Month2]]=""),"",EDATE(Table1[[#This Row],[Start Contract]],Table1[[#This Row],[Duration Month2]])),"-") -> - | X82: =IF(OR((W82=""),(W82="-")),"",YEAR(Table1[[#This Row],[End Contract]])) | Y82: =IF(Table1[[#This Row],[Maintenance]]="yes",IF(Table1[[#This Row],[End Contract]]="","no",IF(TODAY()<=Table1[[#This Row],[End Contract]],"yes","no")),"no") -> no
A83: 77 | B83: SCM Entroncamento - Lar (EPC) | C83: Santa Casa Da Misericordia Do Entroncamento | D83: 500876088 | E83: Rua Maria Serrana 13, Entroncamento | F83: Santarém | G83: 250 | H83: 115 | I83: EPC | J83: Cliente | K83: 0 | L83: =Table1[[#This Row],[Duration]]*12 -> 0 | M83: 45047 | N83: =IF(AND(Table1[[#This Row],[ Type of Contract]]="ESCO",Table1[[#This Row],[Status Detail]]="ACTIVE"),"yes","no") -> no | O83: Telha | P83: Escada | Q83: To discuss with Rui Nunes | R83: ACTIVE | S83: Vitor Bertelo / José Paulino Manutenção | V83: 939900147 / 913576424 | W83: =IF(Table1[[#This Row],[Maintenance]]="yes",IF(OR(Table1[[#This Row],[Start Contract]]="",Table1[[#This Row],[Duration Month2]]=""),"",EDATE(Table1[[#This Row],[Start Contract]],Table1[[#This Row],[Duration Month2]])),"-") -> - | X83: =IF(OR((W83=""),(W83="-")),"",YEAR(Table1[[#This Row],[End Contract]])) | Y83: =IF(Table1[[#This Row],[Maintenance]]="yes",IF(Table1[[#This Row],[End Contract]]="","no",IF(TODAY()<=Table1[[#This Row],[End Contract]],"yes","no")),"no") -> no
A84: 78 | B84: SCM Entroncamento UCCI | C84: Santa Casa Da Misericordia Do Entroncamento | D84: 500876088 | E84: Rua da Barroca 60 2330-108 Entroncamento | F84: Santarém | G84: 100 | H84: 49 | I84: EPC | J84: Cliente | K84: 0 | L84: =Table1[[#This Row],[Duration]]*12 -> 0 | M84: 44986 | N84: =IF(AND(Table1[[#This Row],[ Type of Contract]]="ESCO",Table1[[#This Row],[Status Detail]]="ACTIVE"),"yes","no") -> no | O84: Cobertura Plana | P84: Acesso pela cobertura | Q84: To discuss with Rui Nunes | R84: ACTIVE | S84: Bárbara | V84: 931123964/249729240 | W84: =IF(Table1[[#This Row],[Maintenance]]="yes",IF(OR(Table1[[#This Row],[Start Contract]]="",Table1[[#This Row],[Duration Month2]]=""),"",EDATE(Table1[[#This Row],[Start Contract]],Table1[[#This Row],[Duration Month2]])),"-") -> - | X84: =IF(OR((W84=""),(W84="-")),"",YEAR(Table1[[#This Row],[End Contract]])) | Y84: =IF(Table1[[#This Row],[Maintenance]]="yes",IF(Table1[[#This Row],[End Contract]]="","no",IF(TODAY()<=Table1[[#This Row],[End Contract]],"yes","no")),"no") -> no
A85: 79 | B85: ARIPSI | C85: Aripsi-Associação De Reformados E Idosos Da Póvoa De Santa Iria | D85: 502570660 | E85: Rua Morgado da Povoa, 3, 2625-229 Pova de Santa Iria | F85: Lisboa | G85: 150 | H85: 73.5 | I85: ESCO | J85: Solcorelios II | K85: 15 | L85: =Table1[[#This Row],[Duration]]*12 -> 180 | M85: 44986 | N85: =IF(AND(Table1[[#This Row],[ Type of Contract]]="ESCO",Table1[[#This Row],[Status Detail]]="ACTIVE"),"yes","no") -> yes | O85: Cobertura Plana | P85: Acesso pela cobertura | R85: ACTIVE | S85: Luís Vieira / Maria Fernanda Joaquina António | T85: Presidente da Direcção / Tesoureira | U85: geral@aripsi.pt | V85: 965382444 | W85: =IF(Table1[[#This Row],[Maintenance]]="yes",IF(OR(Table1[[#This Row],[Start Contract]]="",Table1[[#This Row],[Duration Month2]]=""),"",EDATE(Table1[[#This Row],[Start Contract]],Table1[[#This Row],[Duration Month2]])),"-") -> 50465 | X85: =IF(OR((W85=""),(W85="-")),"",YEAR(Table1[[#This Row],[End Contract]])) -> 2038 | Y85: =IF(Table1[[#This Row],[Maintenance]]="yes",IF(Table1[[#This Row],[End Contract]]="","no",IF(TODAY()<=Table1[[#This Row],[End Contract]],"yes","no")),"no") -> yes | AA85: 8838.12 | AB85: Fixa
A86: 80 | B86: Centro de dia de Alferrarede - Jardim de Infância | C86: Centro Social De Alferrarede | D86: 500851085 | E86: Rua de Diu Alferrarede, 2200-045 Abrantes | F86: Alferrarede - Abrantes | G86: 33 | H86: 16.2 | I86: ESCO | J86: Solcorelios II | K86: 15 | L86: =Table1[[#This Row],[Duration]]*12 -> 180 | M86: 45017 | N86: =IF(AND(Table1[[#This Row],[ Type of Contract]]="ESCO",Table1[[#This Row],[Status Detail]]="ACTIVE"),"yes","no") -> yes | O86: Sandwich | P86: Escada | R86: ACTIVE | S86: José Cruz Bartolomeu / Fátima Gonçalves dos Santos | T86: Presidente / Tesoureiro | U86: centrosocialalferrarede@gmail.com | V86: 961327945 | W86: =IF(Table1[[#This Row],[Maintenance]]="yes",IF(OR(Table1[[#This Row],[Start Contract]]="",Table1[[#This Row],[Duration Month2]]=""),"",EDATE(Table1[[#This Row],[Start Contract]],Table1[[#This Row],[Duration Month2]])),"-") -> 50496 | X86: =IF(OR((W86=""),(W86="-")),"",YEAR(Table1[[#This Row],[End Contract]])) -> 2038 | Y86: =IF(Table1[[#This Row],[Maintenance]]="yes",IF(Table1[[#This Row],[End Contract]]="","no",IF(TODAY()<=Table1[[#This Row],[End Contract]],"yes","no")),"no") -> yes | AA86: 7393.68 | AB86: Fixa
A87: 81 | B87: Centro de dia de Alferrarede - Lar | C87: Centro Social De Alferrarede | D87: 500851085 | E87: Rua de Goa, Alferrarede 2200-023 Abrantes | F87: Alferrarede - Abrantes | G87: 44 | H87: 21.56 | I87: ESCO | J87: Solcorelios II | K87: 15 | L87: =Table1[[#This Row],[Duration]]*12 -> 180 | M87: 45017 | N87: =IF(AND(Table1[[#This Row],[ Type of Contract]]="ESCO",Table1[[#This Row],[Status Detail]]="ACTIVE"),"yes","no") -> yes | O87: Sandwich | P87: Escada | R87: ACTIVE | S87: José Cruz Bartolomeu / Fátima Gonçalves dos Santos | T87: Presidente / Tesoureiro | U87: centrosocialalferrarede@gmail.com | V87: 961327944 | W87: =IF(Table1[[#This Row],[Maintenance]]="yes",IF(OR(Table1[[#This Row],[Start Contract]]="",Table1[[#This Row],[Duration Month2]]=""),"",EDATE(Table1[[#This Row],[Start Contract]],Table1[[#This Row],[Duration Month2]])),"-") -> 50496 | X87: =IF(OR((W87=""),(W87="-")),"",YEAR(Table1[[#This Row],[End Contract]])) -> 2038 | Y87: =IF(Table1[[#This Row],[Maintenance]]="yes",IF(Table1[[#This Row],[End Contract]]="","no",IF(TODAY()<=Table1[[#This Row],[End Contract]],"yes","no")),"no") -> yes | AA87: 3914.76 | AB87: Fixa
A88: 82 | B88: Bombeiros Rio Maior | C88: Associação Humanitária De Bombeiros Voluntários De Rio Maior | D88: 501302433 | E88: Avenida Dr. João Afonso Calado da Maia 2040-333 Rio Maior | F88: Santarém | G88: 56 | H88: 27.44 | I88: ESCO | J88: Solcorelios II | K88: 15 | L88: =Table1[[#This Row],[Duration]]*12 -> 180 | M88: 44958 | N88: =IF(AND(Table1[[#This Row],[ Type of Contract]]="ESCO",Table1[[#This Row],[Status Detail]]="ACTIVE"),"yes","no") -> yes | O88: Sandwich | P88: Plataforma Elevatória dos Bombeiros | R88: ACTIVE | S88: António Manuel de Carvalho Quevedo / José Carlos Abadesso dos Santos | T88: Presidente / Tesoureiro | U88: geral@bvrm.pt | V88: 243999510 | W88: =IF(Table1[[#This Row],[Maintenance]]="yes",IF(OR(Table1[[#This Row],[Start Contract]]="",Table1[[#This Row],[Duration Month2]]=""),"",EDATE(Table1[[#This Row],[Start Contract]],Table1[[#This Row],[Duration Month2]])),"-") -> 50437 | X88: =IF(OR((W88=""),(W88="-")),"",YEAR(Table1[[#This Row],[End Contract]])) -> 2038 | Y88: =IF(Table1[[#This Row],[Maintenance]]="yes",IF(Table1[[#This Row],[End Contract]]="","no",IF(TODAY()<=Table1[[#This Row],[End Contract]],"yes","no")),"no") -> yes | AA88: 4030.56 | AB88: Fixa
A89: 83 | B89: Lar ASESM | C89: Asesm - Associação De Solidariedade E Educação De Salir De Matos | D89: 500878684 | E89: Rua Principal, Nº. 4 2500-637 Salir de Matos | F89: Salir de Matos - Leiria | G89: 35 | H89: 19.3 | I89: ESCO | J89: Solcorelios II | K89: 15 | L89: =Table1[[#This Row],[Duration]]*12 -> 180 | M89: 44932 | N89: =IF(AND(Table1[[#This Row],[ Type of Contract]]="ESCO",Table1[[#This Row],[Status Detail]]="ACTIVE"),"yes","no") -> yes | O89: Cobertura Plana | P89: Escada | R89: ACTIVE | S89: Pedro Miguel Paulo Rebelo / Maria José Canas de Oliveira | T89: Presidente / Tesoureiro | U89: asesm-geral@sapo.pt | V89: 918 268 963/ 262 839 550 | W89: =IF(Table1[[#This Row],[Maintenance]]="yes",IF(OR(Table1[[#This Row],[Start Contract]]="",Table1[[#This Row],[Duration Month2]]=""),"",EDATE(Table1[[#This Row],[Start Contract]],Table1[[#This Row],[Duration Month2]])),"-") -> 50411 | X89: =IF(OR((W89=""),(W89="-")),"",YEAR(Table1[[#This Row],[End Contract]])) -> 2038 | Y89: =IF(Table1[[#This Row],[Maintenance]]="yes",IF(Table1[[#This Row],[End Contract]]="","no",IF(TODAY()<=Table1[[#This Row],[End Contract]],"yes","no")),"no") -> yes | AA89: 3562.2 | AB89: Fixa
A90: 84 | B90: Vidigal Wines | C90: Vidigal Wines, S.A. | D90: 500299676 | E90: Rua da Ribeira 230, Cortes Leiria, 2410 - 502 | F90: Leiria | G90: 272 | H90: 125.1 | I90: EPC | J90: Cliente | K90: 0 | L90: =Table1[[#This Row],[Duration]]*12 -> 0 | M90: - | N90: =IF(AND(Table1[[#This Row],[ Type of Contract]]="ESCO",Table1[[#This Row],[Status Detail]]="ACTIVE"),"yes","no") -> no | O90: Telha e Sandwich | P90: Escada | Q90: To discuss with the client | R90: ACTIVE | S90: Manuel Martinho Franco Lavaredas Bio / Ana Maria Figueira Godinho Bio | T90: Presidente / Vice-Presidente | V90: 927605949 930682070 | W90: =IF(Table1[[#This Row],[Maintenance]]="yes",IF(OR(Table1[[#This Row],[Start Contract]]="",Table1[[#This Row],[Duration Month2]]=""),"",EDATE(Table1[[#This Row],[Start Contract]],Table1[[#This Row],[Duration Month2]])),"-") -> - | X90: =IF(OR((W90=""),(W90="-")),"",YEAR(Table1[[#This Row],[End Contract]])) | Y90: =IF(Table1[[#This Row],[Maintenance]]="yes",IF(Table1[[#This Row],[End Contract]]="","no",IF(TODAY()<=Table1[[#This Row],[End Contract]],"yes","no")),"no") -> no
A91: 85 | B91: EBI Boa Água | C91: Agrupamento De Escolas Da Boa Água | D91: 600083780 | E91: Rua Serra de Monchique Escola, 2975-174 Quinta do Conde | F91: Quinta do Conde | G91: 94 | H91: 51.7 | I91: ESCO | J91: Solcorelios II | K91: 10 | L91: =Table1[[#This Row],[Duration]]*12 -> 120 | M91: 45078 | N91: =IF(AND(Table1[[#This Row],[ Type of Contract]]="ESCO",Table1[[#This Row],[Status Detail]]="ACTIVE"),"yes","no") -> yes | O91: Sandwich | P91: Escada | R91: ACTIVE | S91: Nuno Manuel Polido Mantas | T91: Diretor | U91: direcao@aeboaagua.org | V91: 925404760 | W91: =IF(Table1[[#This Row],[Maintenance]]="yes",IF(OR(Table1[[#This Row],[Start Contract]]="",Table1[[#This Row],[Duration Month2]]=""),"",EDATE(Table1[[#This Row],[Start Contract]],Table1[[#This Row],[Duration Month2]])),"-") -> 48731 | X91: =IF(OR((W91=""),(W91="-")),"",YEAR(Table1[[#This Row],[End Contract]])) -> 2033 | Y91: =IF(Table1[[#This Row],[Maintenance]]="yes",IF(Table1[[#This Row],[End Contract]]="","no",IF(TODAY()<=Table1[[#This Row],[End Contract]],"yes","no")),"no") -> yes | AA91: - | AB91: Tarifa
A92: 86 | B92: SCM Galizes (EPC) | C92: Santa Casa Da Misericordia De Galizes | D92: 500876851 | E92: R. Misericórdia 60, 3400-443 Nogueira do Cravo | F92: Coimbra | G92: 120 | H92: 52.8 | I92: EPC | J92: Cliente | K92: 0 | L92: =Table1[[#This Row],[Duration]]*12 -> 0 | M92: - | N92: =IF(AND(Table1[[#This Row],[ Type of Contract]]="ESCO",Table1[[#This Row],[Status Detail]]="ACTIVE"),"yes","no") -> no | O92: Telha | P92: Escada | Q92: To discuss with Rui Nunes | R92: ACTIVE | S92: Carlos | T92: Gestão | U92: gestao@scmgalizes.com | V92: 238671257 | W92: =IF(Table1[[#This Row],[Maintenance]]="yes",IF(OR(Table1[[#This Row],[Start Contract]]="",Table1[[#This Row],[Duration Month2]]=""),"",EDATE(Table1[[#This Row],[Start Contract]],Table1[[#This Row],[Duration Month2]])),"-") -> - | X92: =IF(OR((W92=""),(W92="-")),"",YEAR(Table1[[#This Row],[End Contract]])) | Y92: =IF(Table1[[#This Row],[Maintenance]]="yes",IF(Table1[[#This Row],[End Contract]]="","no",IF(TODAY()<=Table1[[#This Row],[End Contract]],"yes","no")),"no") -> no
A93: 87 | B93: Coopérnico - SCM Benavente (EPC) | C93: Coopérnico - Cooperativa De Desenvolvimento Sustentável Crl | D93: 510852270 | E93: Av. Dona, Av. Dom Francisca Montanha Apartado 54 2130, Benavente | F93: Santarém | G93: 423 | H93: 177.09 | I93: EPC | J93: Cliente | K93: 0 | L93: =Table1[[#This Row],[Duration]]*12 -> 0 | M93: - | N93: =IF(AND(Table1[[#This Row],[ Type of Contract]]="ESCO",Table1[[#This Row],[Status Detail]]="ACTIVE"),"yes","no") -> no | O93: Telha | P93: Escada | Q93: To discuss with the client | R93: ACTIVE | S93: Nuno (Manutenção) / João Santos (Coopérnico) | U93: producao@coopernico.org | V93: 926995319 / 967189750 | W93: =IF(Table1[[#This Row],[Maintenance]]="yes",IF(OR(Table1[[#This Row],[Start Contract]]="",Table1[[#This Row],[Duration Month2]]=""),"",EDATE(Table1[[#This Row],[Start Contract]],Table1[[#This Row],[Duration Month2]])),"-") -> - | X93: =IF(OR((W93=""),(W93="-")),"",YEAR(Table1[[#This Row],[End Contract]])) | Y93: =IF(Table1[[#This Row],[Maintenance]]="yes",IF(Table1[[#This Row],[End Contract]]="","no",IF(TODAY()<=Table1[[#This Row],[End Contract]],"yes","no")),"no") -> no
A94: 88 | B94: APPACDM Lisboa - Lar das Pedralvas | C94: Appacdm De Lisboa - Associação Portuguesa De Pais E Amigos Do Cidadão Deficiente Mental | D94: 504646788 | E94: Rua Ary Dos Santos, 3, 1500-062 Lisboa | F94: Lisboa | G94: 44 | H94: 24.2 | I94: ESCO | J94: Solcorelios II | K94: 15 | L94: =Table1[[#This Row],[Duration]]*12 -> 180 | M94: 45078 | N94: =IF(AND(Table1[[#This Row],[ Type of Contract]]="ESCO",Table1[[#This Row],[Status Detail]]="ACTIVE"),"yes","no") -> yes | O94: Sandwich | P94: Escada | R94: ACTIVE | S94: Mário José Santos de Matos / Luís Fernando Pintão Cascais Xavier | T94: Presidente / Vice-Presidente | U94: dir.pedralvas@appacdm-lisboa.pt | V94: 217621180 / 919203686 | W94: =IF(Table1[[#This Row],[Maintenance]]="yes",IF(OR(Table1[[#This Row],[Start Contract]]="",Table1[[#This Row],[Duration Month2]]=""),"",EDATE(Table1[[#This Row],[Start Contract]],Table1[[#This Row],[Duration Month2]])),"-") -> 50557 | X94: =IF(OR((W94=""),(W94="-")),"",YEAR(Table1[[#This Row],[End Contract]])) -> 2038 | Y94: =IF(Table1[[#This Row],[Maintenance]]="yes",IF(Table1[[#This Row],[End Contract]]="","no",IF(TODAY()<=Table1[[#This Row],[End Contract]],"yes","no")),"no") -> yes | AA94: 3807 | AB94: Fixa
A95: 89 | B95: APPACDM Lisboa - Centro Júlia Moreira | C95: Appacdm De Lisboa - Associação Portuguesa De Pais E Amigos Do Cidadão Deficiente Mental | D95: 504646788 | E95: Rua Adolfo Coelho, 9, Lisboa, 1900-028 Lisboa | F95: Lisboa | G95: 36 | H95: 25.1 | I95: ESCO | J95: Solcorelios II | K95: 15 | L95: =Table1[[#This Row],[Duration]]*12 -> 180 | M95: 45108 | N95: =IF(AND(Table1[[#This Row],[ Type of Contract]]="ESCO",Table1[[#This Row],[Status Detail]]="ACTIVE"),"yes","no") -> yes | O95: Telha | P95: Escada | R95: ACTIVE | S95: Mário José Santos de Matos / Luís Fernando Pintão Cascais Xavier | T95: Presidente / Vice-Presidente | U95: atrimonio@appacdm-lisboa.pt | V95: 218163270 | W95: =IF(Table1[[#This Row],[Maintenance]]="yes",IF(OR(Table1[[#This Row],[Start Contract]]="",Table1[[#This Row],[Duration Month2]]=""),"",EDATE(Table1[[#This Row],[Start Contract]],Table1[[#This Row],[Duration Month2]])),"-") -> 50587 | X95: =IF(OR((W95=""),(W95="-")),"",YEAR(Table1[[#This Row],[End Contract]])) -> 2038 | Y95: =IF(Table1[[#This Row],[Maintenance]]="yes",IF(Table1[[#This Row],[End Contract]]="","no",IF(TODAY()<=Table1[[#This Row],[End Contract]],"yes","no")),"no") -> yes | AA95: 3819.24 | AB95: Fixa
A96: 90 | B96: APPACDM Lisboa - Flor da Quinta | C96: Appacdm De Lisboa - Associação Portuguesa De Pais E Amigos Do Cidadão Deficiente Mental | D96: 504646788 | E96: Quinta Inglesinhas Pera, S/N, Caparica, 2825-000 Almada | F96: Lisboa | G96: 44 | H96: 20.5 | I96: ESCO | J96: Solcorelios II | K96: 15 | L96: =Table1[[#This Row],[Duration]]*12 -> 180 | N96: =IF(AND(Table1[[#This Row],[ Type of Contract]]="ESCO",Table1[[#This Row],[Status Detail]]="ACTIVE"),"yes","no") -> no | O96: Solo | P96: Não é necessário | Q96: To discuss with Rui Nunes | R96: ON HOLD | S96: Mário José Santos de Matos / Luís Fernando Pintão Cascais Xavier | T96: Presidente / Vice-Presidente | U96: . | W96: =IF(Table1[[#This Row],[Maintenance]]="yes",IF(OR(Table1[[#This Row],[Start Contract]]="",Table1[[#This Row],[Duration Month2]]=""),"",EDATE(Table1[[#This Row],[Start Contract]],Table1[[#This Row],[Duration Month2]])),"-") -> - | X96: =IF(OR((W96=""),(W96="-")),"",YEAR(Table1[[#This Row],[End Contract]])) | Y96: =IF(Table1[[#This Row],[Maintenance]]="yes",IF(Table1[[#This Row],[End Contract]]="","no",IF(TODAY()<=Table1[[#This Row],[End Contract]],"yes","no")),"no") -> no
A97: 91 | B97: APPACDM Lisboa - Lar Alapraia 2 | C97: Appacdm De Lisboa - Associação Portuguesa De Pais E Amigos Do Cidadão Deficiente Mental | D97: 504646788 | E97: Travessa Doutor Felix Pereira, 190 RC LT2 | F97: Leiria | H97: 16.2 | I97: ESCO | J97: Solcorelios II | K97: 15 | L97: =Table1[[#This Row],[Duration]]*12 -> 180 | N97: =IF(AND(Table1[[#This Row],[ Type of Contract]]="ESCO",Table1[[#This Row],[Status Detail]]="ACTIVE"),"yes","no") -> no | R97: CANCELLED | S97: Mário José Santos de Matos / Luís Fernando Pintão Cascais Xavier | T97: Presidente / Vice-Presidente | U97: . | W97: =IF(Table1[[#This Row],[Maintenance]]="yes",IF(OR(Table1[[#This Row],[Start Contract]]="",Table1[[#This Row],[Duration Month2]]=""),"",EDATE(Table1[[#This Row],[Start Contract]],Table1[[#This Row],[Duration Month2]])),"-") -> - | X97: =IF(OR((W97=""),(W97="-")),"",YEAR(Table1[[#This Row],[End Contract]])) | Y97: =IF(Table1[[#This Row],[Maintenance]]="yes",IF(Table1[[#This Row],[End Contract]]="","no",IF(TODAY()<=Table1[[#This Row],[End Contract]],"yes","no")),"no") -> no
A98: 92 | B98: Cercilei - Leiria | C98: Cercilei - Cooperativa De Ensino E Reabilitação De Cidadãos Inadaptados De Leiria Crl | D98: 500594147 | E98: Estrada das Moitas Altas nº 279, Pinheiros 2415-799 Leiria | F98: Leiria | G98: 103 | H98: 53 | I98: EPC | J98: Cliente | K98: 0 | L98: =Table1[[#This Row],[Duration]]*12 -> 0 | M98: 45078 | N98: =IF(AND(Table1[[#This Row],[ Type of Contract]]="ESCO",Table1[[#This Row],[Status Detail]]="ACTIVE"),"yes","no") -> no | O98: Telha | P98: Escada | Q98: To discuss with Rui Nunes | R98: ACTIVE | S98: Ricardo Alexandre | U98: ricardo.alexandre@cerlicei.pt | V98: 961900171 | W98: =IF(Table1[[#This Row],[Maintenance]]="yes",IF(OR(Table1[[#This Row],[Start Contract]]="",Table1[[#This Row],[Duration Month2]]=""),"",EDATE(Table1[[#This Row],[Start Contract]],Table1[[#This Row],[Duration Month2]])),"-") -> - | X98: =IF(OR((W98=""),(W98="-")),"",YEAR(Table1[[#This Row],[End Contract]])) | Y98: =IF(Table1[[#This Row],[Maintenance]]="yes",IF(Table1[[#This Row],[End Contract]]="","no",IF(TODAY()<=Table1[[#This Row],[End Contract]],"yes","no")),"no") -> no
A99: 93 | B99: CERCILEI - Porto de Mós (EPC) | C99: Cercilei - Cooperativa De Ensino E Reabilitação De Cidadãos Inadaptados De Leiria Crl | D99: 500594147 | E99: Estr. das Moitas Altas 279, Leiria | F99: Leiria | G99: 61 | H99: 29.9 | I99: EPC | J99: Cliente | K99: 0 | L99: =Table1[[#This Row],[Duration]]*12 -> 0 | M99: 44986 | N99: =IF(AND(Table1[[#This Row],[ Type of Contract]]="ESCO",Table1[[#This Row],[Status Detail]]="ACTIVE"),"yes","no") -> no | O99: Telha | P99: Escada | Q99: To discuss with Rui Nunes | R99: ACTIVE | S99: Ricardo Alexandre | U99: ricardo.alexandre@cerlicei.pt | V99: 244482590/914495464 | W99: =IF(Table1[[#This Row],[Maintenance]]="yes",IF(OR(Table1[[#This Row],[Start Contract]]="",Table1[[#This Row],[Duration Month2]]=""),"",EDATE(Table1[[#This Row],[Start Contract]],Table1[[#This Row],[Duration Month2]])),"-") -> - | X99: =IF(OR((W99=""),(W99="-")),"",YEAR(Table1[[#This Row],[End Contract]])) | Y99: =IF(Table1[[#This Row],[Maintenance]]="yes",IF(Table1[[#This Row],[End Contract]]="","no",IF(TODAY()<=Table1[[#This Row],[End Contract]],"yes","no")),"no") -> no
A100: 94 | B100: Proteco (Cancelado) | G100: 202 | L100: =Table1[[#This Row],[Duration]]*12 -> 0 | N100: =IF(AND(Table1[[#This Row],[ Type of Contract]]="ESCO",Table1[[#This Row],[Status Detail]]="ACTIVE"),"yes","no") -> no | O100: Telha | P100: Escada | R100: CANCELLED | W100: =IF(Table1[[#This Row],[Maintenance]]="yes",IF(OR(Table1[[#This Row],[Start Contract]]="",Table1[[#This Row],[Duration Month2]]=""),"",EDATE(Table1[[#This Row],[Start Contract]],Table1[[#This Row],[Duration Month2]])),"-") -> - | X100: =IF(OR((W100=""),(W100="-")),"",YEAR(Table1[[#This Row],[End Contract]])) | Y100: =IF(Table1[[#This Row],[Maintenance]]="yes",IF(Table1[[#This Row],[End Contract]]="","no",IF(TODAY()<=Table1[[#This Row],[End Contract]],"yes","no")),"no") -> no
...

Sheet Venda do excedente
B1: Status | C1: Company Name | D1: Comercializador | E1: Tipo de Contrato | F1: Envio de Proposta | G1: Envio do Contrato | H1: Ass. do Contrato (Recebido do cliente) | I1: Envio p/ Comercializador | J1: Situação | K1: Duração (Mês) | L1: Data Inicio | M1: Data Final | N1: Observação
B2: =IF(J2="Não Tratar",4,IF(J2="Ativo",3,IF(J2="Aguardando",2,IF(J2="Certificado",1,IF(J2="Pendencias",0))))) -> 3 | C2: {=_xlfn._xlws.FILTER('Project Overview'!B:B,('Project Overview'!#REF!="ACTIVE")*('Project Overview'!#REF!="Com Injeção"))} -> #REF! | D2: Simples Energia | J2: Ativo | K2: 12 | L2: 44223 | M2: =EOMONTH(L2,K2) -> 44592
B3: =IF(J3="Não Tratar",4,IF(J3="Ativo",3,IF(J3="Aguardando",2,IF(J3="Certificado",1,IF(J3="Pendencias",0))))) -> 3 | D3: Simples Energia | J3: Ativo | K3: 12 | L3: 44360 | M3: =EOMONTH(L3,K3) -> 44742
B4: =IF(J4="Não Tratar",4,IF(J4="Ativo",3,IF(J4="Aguardando",2,IF(J4="Certificado",1,IF(J4="Pendencias",0))))) -> 3 | D4: Simples Energia | J4: Ativo | K4: 12 | L4: 44406 | M4: =EOMONTH(L4,K4) -> 44773
B5: =IF(J5="Não Tratar",4,IF(J5="Ativo",3,IF(J5="Aguardando",2,IF(J5="Certificado",1,IF(J5="Pendencias",0))))) -> 3 | D5: Simples Energia | J5: Ativo | K5: 12 | L5: 44341 | M5: =EOMONTH(L5,K5) -> 44712
B6: =IF(J6="Não Tratar",4,IF(J6="Ativo",3,IF(J6="Aguardando",2,IF(J6="Certificado",1,IF(J6="Pendencias",0))))) -> 4 | J6: Não Tratar
B7: =IF(J7="Não Tratar",4,IF(J7="Ativo",3,IF(J7="Aguardando",2,IF(J7="Certificado",1,IF(J7="Pendencias",0))))) -> 3 | D7: Simples Energia | J7: Ativo | K7: 12 | L7: 44295 | M7: =EOMONTH(L7,K7) -> 44681
B8: =IF(J8="Não Tratar",4,IF(J8="Ativo",3,IF(J8="Aguardando",2,IF(J8="Certificado",1,IF(J8="Pendencias",0))))) -> 3 | D8: Simples Energia | J8: Ativo | K8: 12 | L8: 44370 | M8: =EOMONTH(L8,K8) -> 44742
B9: =IF(J9="Não Tratar",4,IF(J9="Ativo",3,IF(J9="Aguardando",2,IF(J9="Certificado",1,IF(J9="Pendencias",0))))) -> 4 | D9: Simples Energia | G9: 44309 | J9: Não Tratar | K9: 12 | N9: Nunca enviou os documentos
B10: =IF(J10="Não Tratar",4,IF(J10="Ativo",3,IF(J10="Aguardando",2,IF(J10="Certificado",1,IF(J10="Pendencias",0))))) -> 3 | D10: Simples Energia Espanha | E10: Indexado | G10: 44519 | H10: 44586 | I10: 44586 | J10: Ativo | K10: 12 | L10: 44611 | M10: =EOMONTH(L10,K10) -> 44985 | N10: Foi solicitado novamento por email no dia 07.06.2021. Dia 22/06/2021. Liguei dia 01/07/2021. Contrato enviado 14/07/2021 e Procuração dia 09/07/2021.
B11: =IF(J11="Não Tratar",4,IF(J11="Ativo",3,IF(J11="Aguardando",2,IF(J11="Certificado",1,IF(J11="Pendencias",0))))) -> 3 | D11: Simples Energia | J11: Ativo | K11: 12 | L11: 44379 | M11: =EOMONTH(L11,K11) -> 44773
B12: =IF(J12="Não Tratar",4,IF(J12="Ativo",3,IF(J12="Aguardando",2,IF(J12="Certificado",1,IF(J12="Pendencias",0))))) -> 4 | D12: Contrato? | J12: Não Tratar | K12: 12 | N12: Vincent pediu para aguardar, não fazer nada até ele falar
B13: =IF(J13="Não Tratar",4,IF(J13="Ativo",3,IF(J13="Aguardando",2,IF(J13="Certificado",1,IF(J13="Pendencias",0))))) -> 3 | D13: Simples Energia | G13: 44293 | H13: 44321 | I13: 44326 | J13: Ativo | K13: 12 | L13: 44363 | M13: =EOMONTH(L13,K13) -> 44742
B14: =IF(J14="Não Tratar",4,IF(J14="Ativo",3,IF(J14="Aguardando",2,IF(J14="Certificado",1,IF(J14="Pendencias",0))))) -> 3 | D14: Simples Energia | E14: Indexado | G14: 44519 | J14: Ativo | K14: 12 | L14: 44572 | M14: =EOMONTH(L14,K14) -> 44957
B15: =IF(J15="Não Tratar",4,IF(J15="Ativo",3,IF(J15="Aguardando",2,IF(J15="Certificado",1,IF(J15="Pendencias",0))))) -> 3 | D15: LuzBoa | E15: Indexado | J15: Ativo | K15: 12 | L15: 44712 | M15: =EOMONTH(L15,K15) -> 45077
B16: =IF(J16="Não Tratar",4,IF(J16="Ativo",3,IF(J16="Aguardando",2,IF(J16="Certificado",1,IF(J16="Pendencias",0))))) -> 3 | D16: LuzBoa | E16: Indexado | G16: 44522 | H16: 44533 | I16: 44536 | J16: Ativo | K16: 12 | L16: 44561 | M16: =EOMONTH(L16,K16) -> 44926
B17: =IF(J17="Não Tratar",4,IF(J17="Ativo",3,IF(J17="Aguardando",2,IF(J17="Certificado",1,IF(J17="Pendencias",0))))) -> 3 | D17: LuzBoa | E17: Indexado | G17: 44605 | J17: Ativo | K17: 12 | L17: 44653 | M17: =EOMONTH(L17,K17) -> 45046
B18: =IF(J18="Não Tratar",4,IF(J18="Ativo",3,IF(J18="Aguardando",2,IF(J18="Certificado",1,IF(J18="Pendencias",0))))) -> 4 | J18: Não Tratar
B19: =IF(J19="Não Tratar",4,IF(J19="Ativo",3,IF(J19="Aguardando",2,IF(J19="Certificado",1,IF(J19="Pendencias",0))))) -> 3 | D19: Simples Energia Espanha | E19: Indexado | H19: 44537 | I19: 44547 | J19: Ativo | K19: 12 | L19: 44593 | M19: =EOMONTH(L19,K19) -> 44985
B20: =IF(J20="Não Tratar",4,IF(J20="Ativo",3,IF(J20="Aguardando",2,IF(J20="Certificado",1,IF(J20="Pendencias",0))))) -> 4 | J20: Não Tratar
B21: =IF(J21="Não Tratar",4,IF(J21="Ativo",3,IF(J21="Aguardando",2,IF(J21="Certificado",1,IF(J21="Pendencias",0))))) -> 4 | J21: Não Tratar
B22: =IF(J22="Não Tratar",4,IF(J22="Ativo",3,IF(J22="Aguardando",2,IF(J22="Certificado",1,IF(J22="Pendencias",0))))) -> 4 | J22: Não Tratar
B23: =IF(J23="Não Tratar",4,IF(J23="Ativo",3,IF(J23="Aguardando",2,IF(J23="Certificado",1,IF(J23="Pendencias",0))))) -> 3 | D23: - | J23: Ativo | K23: 12 | L23: 44712 | M23: =EOMONTH(L23,K23) -> 45077
B24: =IF(J24="Não Tratar",4,IF(J24="Ativo",3,IF(J24="Aguardando",2,IF(J24="Certificado",1,IF(J24="Pendencias",0))))) -> 3 | D24: LuzBoa | E24: Indexado | I24: 45106 | J24: Ativo | K24: 12 | L24: 44832 | M24: =EOMONTH(L24,K24) -> 45199
B25: =IF(J25="Não Tratar",4,IF(J25="Ativo",3,IF(J25="Aguardando",2,IF(J25="Certificado",1,IF(J25="Pendencias",0))))) -> 4 | J25: Não Tratar
B26: =IF(J26="Não Tratar",4,IF(J26="Ativo",3,IF(J26="Aguardando",2,IF(J26="Certificado",1,IF(J26="Pendencias",0))))) -> 3 | D26: LuzBoa | E26: Indexado | J26: Ativo | K26: 12 | L26: 44775 | M26: =EOMONTH(L26,K26) -> 45169
B27: =IF(J27="Não Tratar",4,IF(J27="Ativo",3,IF(J27="Aguardando",2,IF(J27="Certificado",1,IF(J27="Pendencias",0))))) -> 3 | D27: LuzBoa | E27: Indexado | G27: 44567 | H27: 44575 | I27: 44579 | J27: Ativo | K27: 12 | L27: 44607 | M27: =EOMONTH(L27,K27) -> 44985
B28: =IF(J28="Não Tratar",4,IF(J28="Ativo",3,IF(J28="Aguardando",2,IF(J28="Certificado",1,IF(J28="Pendencias",0))))) -> 3 | D28: EZU Energia | E28: Fixo | I28: 45105 | J28: Ativo | K28: 12 | L28: 45133 | M28: =EOMONTH(L28,K28) -> 45504 | N28: A Sicobrita 2 a única diferença é a data de inicio que é 19/07/2023
B29: =IF(J29="Não Tratar",4,IF(J29="Ativo",3,IF(J29="Aguardando",2,IF(J29="Certificado",1,IF(J29="Pendencias",0))))) -> 3 | D29: LuzBoa | E29: Indexado | J29: Ativo | K29: 12 | L29: 44722 | M29: =EOMONTH(L29,K29) -> 45107
B30: =IF(J30="Não Tratar",4,IF(J30="Ativo",3,IF(J30="Aguardando",2,IF(J30="Certificado",1,IF(J30="Pendencias",0))))) -> 3 | D30: LuzBoa | E30: Indexado | J30: Ativo | K30: 12 | L30: 44741 | M30: =EOMONTH(L30,K30) -> 45107
B31: =IF(J31="Não Tratar",4,IF(J31="Ativo",3,IF(J31="Aguardando",2,IF(J31="Certificado",1,IF(J31="Pendencias",0))))) -> 3 | D31: LuzBoa | E31: Indexado | J31: Ativo | K31: 12 | L31: 44790 | M31: =EOMONTH(L31,K31) -> 45169
B32: =IF(J32="Não Tratar",4,IF(J32="Ativo",3,IF(J32="Aguardando",2,IF(J32="Certificado",1,IF(J32="Pendencias",0))))) -> 4 | J32: Não Tratar
B33: =IF(J33="Não Tratar",4,IF(J33="Ativo",3,IF(J33="Aguardando",2,IF(J33="Certificado",1,IF(J33="Pendencias",0))))) -> 0 | J33: Pendencias
B34: =IF(J34="Não Tratar",4,IF(J34="Ativo",3,IF(J34="Aguardando",2,IF(J34="Certificado",1,IF(J34="Pendencias",0))))) -> 3 | D34: LuzBoa | E34: Indexado | G34: 44980 | H34: 44998 | I34: 45000 | J34: Ativo | K34: 12 | L34: 45049 | M34: =EOMONTH(L34,K34) -> 45443 | N34: Falta certificado para envio do contrato
B35: =IF(J35="Não Tratar",4,IF(J35="Ativo",3,IF(J35="Aguardando",2,IF(J35="Certificado",1,IF(J35="Pendencias",0))))) -> 3 | D35: LuzBoa | E35: Indexado | J35: Ativo | K35: 12 | L35: 44697 | M35: =EOMONTH(L35,K35) -> 45077 | N35: Trocou para Ezu em 30/10/2023
B36: =IF(J36="Não Tratar",4,IF(J36="Ativo",3,IF(J36="Aguardando",2,IF(J36="Certificado",1,IF(J36="Pendencias",0))))) -> 3 | D36: LuzBoa | E36: Indexado | J36: Ativo | K36: 12 | L36: 44696 | M36: =EOMONTH(L36,K36) -> 45077
B37: =IF(J37="Não Tratar",4,IF(J37="Ativo",3,IF(J37="Aguardando",2,IF(J37="Certificado",1,IF(J37="Pendencias",0))))) -> 3 | D37: LuzBoa | E37: Indexado | J37: Ativo | K37: 12 | L37: 44757 | M37: =EOMONTH(L37,K37) -> 45138
B38: =IF(J38="Não Tratar",4,IF(J38="Ativo",3,IF(J38="Aguardando",2,IF(J38="Certificado",1,IF(J38="Pendencias",0))))) -> 3 | D38: LuzBoa | E38: Indexado | J38: Ativo | K38: 12 | L38: 44782 | M38: =EOMONTH(L38,K38) -> 45169
B39: =IF(J39="Não Tratar",4,IF(J39="Ativo",3,IF(J39="Aguardando",2,IF(J39="Certificado",1,IF(J39="Pendencias",0))))) -> 3 | D39: LuzBoa | E39: Indexado | J39: Ativo | K39: 12 | L39: 44697 | M39: =EOMONTH(L39,K39) -> 45077
B40: =IF(J40="Não Tratar",4,IF(J40="Ativo",3,IF(J40="Aguardando",2,IF(J40="Certificado",1,IF(J40="Pendencias",0))))) -> 3 | D40: LuzBoa | E40: Indexado | G40: 44818 | H40: 44820 | I40: 44820 | J40: Ativo | K40: 12 | L40: 44860 | M40: =EOMONTH(L40,K40) -> 45230 | N40: Enviado dia 08/07/21 p/ Fabio e Certficado enviado 04/08/2021.
B41: =IF(J41="Não Tratar",4,IF(J41="Ativo",3,IF(J41="Aguardando",2,IF(J41="Certificado",1,IF(J41="Pendencias",0))))) -> 3 | D41: LuzBoa | E41: Indexado | G41: 44806 | H41: 44819 | I41: 44826 | J41: Ativo | K41: 12 | L41: 44868 | M41: =EOMONTH(L41,K41) -> 45260 | N41: Tem certificado - Oscar resolver em Janeiro
B42: =IF(J42="Não Tratar",4,IF(J42="Ativo",3,IF(J42="Aguardando",2,IF(J42="Certificado",1,IF(J42="Pendencias",0))))) -> 3 | D42: LuzBoa | E42: Indexado | G42: 44932 | H42: 44972 | I42: 44972 | J42: Ativo | K42: 12 | L42: 45049 | M42: =EOMONTH(L42,K42) -> 45443 | N42: Aguardando entrada na OMIE
B43: =IF(J43="Não Tratar",4,IF(J43="Ativo",3,IF(J43="Aguardando",2,IF(J43="Certificado",1,IF(J43="Pendencias",0))))) -> 3 | D43: LuzBoa | E43: Indexado | G43: 44967 | H43: 44981 | I43: 44984 | J43: Ativo | K43: 12 | L43: 45056 | M43: =EOMONTH(L43,K43) -> 45443 | N43: Aguardando entrada na OMIE
B44: =IF(J44="Não Tratar",4,IF(J44="Ativo",3,IF(J44="Aguardando",2,IF(J44="Certificado",1,IF(J44="Pendencias",0))))) -> 3 | D44: LuzBoa | E44: Indexado | G44: 44825 | H44: 44831 | I44: 44833 | J44: Ativo | K44: 12 | L44: 44860 | M44: =EOMONTH(L44,K44) -> 45230 | N44: Foi enviado diretamente pela Vatel
B45: =IF(J45="Não Tratar",4,IF(J45="Ativo",3,IF(J45="Aguardando",2,IF(J45="Certificado",1,IF(J45="Pendencias",0))))) -> 3 | D45: LuzBoa | E45: Indexado | G45: 44825 | H45: 44831 | I45: 44833 | J45: Ativo | K45: 12 | L45: 44868 | M45: =EOMONTH(L45,K45) -> 45260
B46: =IF(J46="Não Tratar",4,IF(J46="Ativo",3,IF(J46="Aguardando",2,IF(J46="Certificado",1,IF(J46="Pendencias",0))))) -> 3 | J46: Ativo
B47: =IF(J47="Não Tratar",4,IF(J47="Ativo",3,IF(J47="Aguardando",2,IF(J47="Certificado",1,IF(J47="Pendencias",0))))) -> 3 | D47: LuzBoa | E47: Indexado | G47: 44930 | H47: 44984 | I47: 44970 | J47: Ativo | K47: 12 | L47: 45049 | M47: =EOMONTH(L47,K47) -> 45443 | N47: Carolina está tratando da modificação do certificado
B48: =IF(J48="Não Tratar",4,IF(J48="Ativo",3,IF(J48="Aguardando",2,IF(J48="Certificado",1,IF(J48="Pendencias",0))))) -> 3 | D48: EZU Energia | E48: Fixo | G48: 45106 | I48: 45160 | J48: Ativo | K48: 12 | L48: 45182 | M48: =EOMONTH(L48,K48) -> 45565 | N48: Contrato enviado para EZU 22/08/2023
B49: =IF(J49="Não Tratar",4,IF(J49="Ativo",3,IF(J49="Aguardando",2,IF(J49="Certificado",1,IF(J49="Pendencias",0))))) -> 3 | D49: LuzBoa | E49: Indexado | G49: 44881 | H49: 44932 | I49: 44971 | J49: Ativo | K49: 12 | L49: 45029 | M49: =EOMONTH(L49,K49) -> 45412 | N49: Aguardando entrada na OMIE
B50: =IF(J50="Não Tratar",4,IF(J50="Ativo",3,IF(J50="Aguardando",2,IF(J50="Certificado",1,IF(J50="Pendencias",0))))) -> 3 | D50: LuzBoa | E50: Indexado | G50: 44881 | H50: 44932 | I50: 44606 | J50: Ativo | K50: 12 | L50: 44954 | M50: =EOMONTH(L50,K50) -> 45322
B51: =IF(J51="Não Tratar",4,IF(J51="Ativo",3,IF(J51="Aguardando",2,IF(J51="Certificado",1,IF(J51="Pendencias",0))))) -> 0 | D51: EZU Energia | F51: 45273 | J51: Pendencias | N51: Proposta enviada novamente 13/12/23 23/05/2023 - Nunca respondeu
B52: =IF(J52="Não Tratar",4,IF(J52="Ativo",3,IF(J52="Aguardando",2,IF(J52="Certificado",1,IF(J52="Pendencias",0))))) -> 3 | D52: EZU Energia | E52: Fixo | F52: 45147 | G52: 45211 | J52: Ativo | K52: 12 | L52: 45301 | M52: =EOMONTH(L52,K52) -> 45688 | N52: Estão Avaliando 14/12/23 Não devolveram assinado, perguntado Novamente 13/12/23 Proposta enviada dia 09/08/23 pelo Vincent
B53: =IF(J53="Não Tratar",4,IF(J53="Ativo",3,IF(J53="Aguardando",2,IF(J53="Certificado",1,IF(J53="Pendencias",0))))) -> 3 | D53: LuzBoa | E53: Indexado | G53: 45069 | H53: 45072 | I53: 45072 | J53: Ativo | K53: 12 | L53: 45154 | M53: =EOMONTH(L53,K53) -> 45535
B54: =IF(J54="Não Tratar",4,IF(J54="Ativo",3,IF(J54="Aguardando",2,IF(J54="Certificado",1,IF(J54="Pendencias",0))))) -> 0 | J54: Pendencias
B55: =IF(J55="Não Tratar",4,IF(J55="Ativo",3,IF(J55="Aguardando",2,IF(J55="Certificado",1,IF(J55="Pendencias",0))))) -> 0 | D55: EZU Energia | F55: 45273 | J55: Pendencias | N55: Proposta enviada novamente 13/12/23 27/06/2023
B56: =IF(J56="Não Tratar",4,IF(J56="Ativo",3,IF(J56="Aguardando",2,IF(J56="Certificado",1,IF(J56="Pendencias",0))))) -> 0 | D56: EZU Energia | E56: Indexado | F56: 45142 | J56: Pendencias | N56: Aguardar Kétsia falar com Vincent Proposta enviada 04/08/2023 Pelo Vincent
B57: =IF(J57="Não Tratar",4,IF(J57="Ativo",3,IF(J57="Aguardando",2,IF(J57="Certificado",1,IF(J57="Pendencias",0))))) -> 3 | D57: LuzBoa | E57: Indexado | G57: 45072 | H57: 45079 | I57: 45079 | J57: Ativo | K57: 12 | L57: 45154 | M57: =EOMONTH(L57,K57) -> 45535
B58: =IF(J58="Não Tratar",4,IF(J58="Ativo",3,IF(J58="Aguardando",2,IF(J58="Certificado",1,IF(J58="Pendencias",0))))) -> 3 | D58: EZU Energia | E58: Fixo | G58: 45166 | H58: 45168 | I58: 45169 | J58: Ativo | K58: 12 | L58: 45182 | M58: =EOMONTH(L58,K58) -> 45565 | N58: Ativo as duas instalações no mesmo dia
B59: =IF(J59="Não Tratar",4,IF(J59="Ativo",3,IF(J59="Aguardando",2,IF(J59="Certificado",1,IF(J59="Pendencias",0))))) -> 0 | D59: LuzBoa | E59: Indexado | J59: Pendencias | K59: 12
B60: =IF(J60="Não Tratar",4,IF(J60="Ativo",3,IF(J60="Aguardando",2,IF(J60="Certificado",1,IF(J60="Pendencias",0))))) -> 0 | D60: LuzBoa | E60: Indexado | J60: Pendencias | K60: 12
B61: =IF(J61="Não Tratar",4,IF(J61="Ativo",3,IF(J61="Aguardando",2,IF(J61="Certificado",1,IF(J61="Pendencias",0))))) -> 0 | J61: Pendencias
B62: =IF(J62="Não Tratar",4,IF(J62="Ativo",3,IF(J62="Aguardando",2,IF(J62="Certificado",1,IF(J62="Pendencias",0))))) -> 0 | D62: EZU Energia | E62: Fixo | F62: 45160 | G62: 45190 | I62: 45233 | J62: Pendencias | N62: Falta o comercializador receber os documentos originais
B63: =IF(J63="Não Tratar",4,IF(J63="Ativo",3,IF(J63="Aguardando",2,IF(J63="Certificado",1,IF(J63="Pendencias",0))))) -> 3 | D63: EZU Energia | E63: Fixo | G63: 45243 | H63: 45246 | I63: 45246 | J63: Ativo | K63: 12 | L63: 45267 | M63: =EOMONTH(L63,K63) -> 45657
B64: =IF(J64="Não Tratar",4,IF(J64="Ativo",3,IF(J64="Aguardando",2,IF(J64="Certificado",1,IF(J64="Pendencias",0))))) -> 0 | D64: EZU Energia | E64: Fixo | F64: 45106 | G64: 45314 | J64: Pendencias | N64: Contrato enviado de novo 23/01/24 Perguntado se pretendem realizar a venda do excedente 13/12/23 - Não perguntar mais nada Proposta enviada dia 29/06 - Falo c/ Vincent para esperar
B65: =IF(J65="Não Tratar",4,IF(J65="Ativo",3,IF(J65="Aguardando",2,IF(J65="Certificado",1,IF(J65="Pendencias",0))))) -> 0 | D65: EZU Energia | J65: Pendencias | N65: Enviado proposta - 20/12/23
B66: =IF(J66="Não Tratar",4,IF(J66="Ativo",3,IF(J66="Aguardando",2,IF(J66="Certificado",1,IF(J66="Pendencias",0))))) -> 0 | D66: EZU Energia | F66: 45301 | J66: Pendencias | N66: Enviado proposta - 10/01/24
B67: =IF(J67="Não Tratar",4,IF(J67="Ativo",3,IF(J67="Aguardando",2,IF(J67="Certificado",1,IF(J67="Pendencias",0))))) -> 0 | D67: EZU Energia | F67: 45273 | J67: Pendencias | N67: Mandou so o Nib, pedi os restantes documentos e qual opção 16/1/24 Enviado novamente proposta 13/12/23 25.08.23
B68: =IF(J68="Não Tratar",4,IF(J68="Ativo",3,IF(J68="Aguardando",2,IF(J68="Certificado",1,IF(J68="Pendencias",0))))) -> 2 | D68: EZU Energia | E68: Fixo | G68: 45106 | I68: 45168 | J68: Aguardando | N68: Falar com Vincent sobre procuração Contrato enviado para o cliente 29/06 - falta enviar documento autenticado (04/09/2023)
B69: =IF(J69="Não Tratar",4,IF(J69="Ativo",3,IF(J69="Aguardando",2,IF(J69="Certificado",1,IF(J69="Pendencias",0))))) -> 0 | D69: EZU Energia | E69: Fixo | G69: 45160 | J69: Pendencias | N69: Enviado proposta de novo 19/12/23 Email enviado a reforçar que não recebemos as cópias 13/12/23
B70: =IF(J70="Não Tratar",4,IF(J70="Ativo",3,IF(J70="Aguardando",2,IF(J70="Certificado",1,IF(J70="Pendencias",0))))) -> 0 | D70: EZU Energia | E70: Fixo | G70: 45107 | J70: Pendencias | N70: Enviado proposta de novo 19/12/23 Email enviado a reforçar que não recebemos as cópias 13/12/23 Contrato enviado para o cliente 30/06 - nunca respondeu e dia 22/08 perguntado novamente
B71: =IF(J71="Não Tratar",4,IF(J71="Ativo",3,IF(J71="Aguardando",2,IF(J71="Certificado",1,IF(J71="Pendencias",0))))) -> 3 | D71: EZU Energia | E71: Fixo | G71: 45075 | J71: Ativo | K71: 12 | L71: 45077 | M71: =EOMONTH(L71,K71) -> 45443
B72: =IF(J72="Não Tratar",4,IF(J72="Ativo",3,IF(J72="Aguardando",2,IF(J72="Certificado",1,IF(J72="Pendencias",0))))) -> 0 | D72: EZU Energia | F72: 45273 | J72: Pendencias | N72: Proposta enviada novamente 13/12/23 22/08/2023
B73: =IF(J73="Não Tratar",4,IF(J73="Ativo",3,IF(J73="Aguardando",2,IF(J73="Certificado",1,IF(J73="Pendencias",0))))) -> 3 | D73: EZU Energia | E73: Fixo | G73: 45106 | I73: 45140 | J73: Ativo | K73: 12 | L73: 45170 | M73: =EOMONTH(L73,K73) -> 45565
B74: =IF(J74="Não Tratar",4,IF(J74="Ativo",3,IF(J74="Aguardando",2,IF(J74="Certificado",1,IF(J74="Pendencias",0))))) -> 3 | D74: EZU Energia | E74: Fixo | G74: 45131 | I74: 45141 | J74: Ativo | K74: 12 | L74: 45168 | M74: =EOMONTH(L74,K74) -> 45535
B75: =IF(J75="Não Tratar",4,IF(J75="Ativo",3,IF(J75="Aguardando",2,IF(J75="Certificado",1,IF(J75="Pendencias",0))))) -> 3 | D75: EZU Energia | E75: Fixo | G75: 45215 | J75: Ativo | K75: 12 | L75: 45247 | M75: =EOMONTH(L75,K75) -> 45626
B76: =IF(J76="Não Tratar",4,IF(J76="Ativo",3,IF(J76="Aguardando",2,IF(J76="Certificado",1,IF(J76="Pendencias",0))))) -> 0 | J76: Pendencias
B77: =IF(J77="Não Tratar",4,IF(J77="Ativo",3,IF(J77="Aguardando",2,IF(J77="Certificado",1,IF(J77="Pendencias",0))))) -> 0 | D77: EZU Energia | F77: 45301 | J77: Pendencias | N77: Enviada proposta novamente 10/1/24 Proposta enviada 23/05/2023 - Nunca respondeu
B78: =IF(J78="Não Tratar",4,IF(J78="Ativo",3,IF(J78="Aguardando",2,IF(J78="Certificado",1,IF(J78="Pendencias",0))))) -> 3 | D78: EZU Energia | E78: Fixo | J78: Ativo | K78: 12 | L78: 45196 | M78: =EOMONTH(L78,K78) -> 45565
B79: =IF(J79="Não Tratar",4,IF(J79="Ativo",3,IF(J79="Aguardando",2,IF(J79="Certificado",1,IF(J79="Pendencias",0))))) -> 0 | J79: Pendencias
B80: =IF(J80="Não Tratar",4,IF(J80="Ativo",3,IF(J80="Aguardando",2,IF(J80="Certificado",1,IF(J80="Pendencias",0))))) -> 0 | J80: Pendencias
B81: =IF(J81="Não Tratar",4,IF(J81="Ativo",3,IF(J81="Aguardando",2,IF(J81="Certificado",1,IF(J81="Pendencias",0))))) -> 3 | D81: LuzBoa | E81: Indexado | J81: Ativo | K81: 12 | L81: 45139 | M81: =EOMONTH(L81,K81) -> 45535 | N81: Luzboa iria alterar o tamanho - solicitado dia 24/07/2023
B82: =IF(J82="Não Tratar",4,IF(J82="Ativo",3,IF(J82="Aguardando",2,IF(J82="Certificado",1,IF(J82="Pendencias",0))))) -> 0 | D82: EZU Energia | E82: Fixo | G82: 45295 | J82: Pendencias | N82: Enviado contrato 4/1/24 (Falta eles enviarem dp CC; IBAN; Cert. Perm) Vincent vai enviar mail com a proposta
B83: =IF(J83="Não Tratar",4,IF(J83="Ativo",3,IF(J83="Aguardando",2,IF(J83="Certificado",1,IF(J83="Pendencias",0))))) -> 3 | D83: EZU Energia | E83: Fixo | H83: 45201 | I83: 45202 | J83: Ativo | K83: 12 | L83: 45225 | M83: =EOMONTH(L83,K83) -> 45596
B84: =IF(J84="Não Tratar",4,IF(J84="Ativo",3,IF(J84="Aguardando",2,IF(J84="Certificado",1,IF(J84="Pendencias",0))))) -> 0 | J84: Pendencias
B85: =IF(J85="Não Tratar",4,IF(J85="Ativo",3,IF(J85="Aguardando",2,IF(J85="Certificado",1,IF(J85="Pendencias",0))))) -> 0 | D85: EZU Energia | F85: 45271 | J85: Pendencias | N85: Enviado proposta - 11/12/23
B86: =IF(J86="Não Tratar",4,IF(J86="Ativo",3,IF(J86="Aguardando",2,IF(J86="Certificado",1,IF(J86="Pendencias",0))))) -> 0 | D86: EZU Energia | F86: 45280 | J86: Pendencias | N86: Enviado proposta - 20/12/23

Sheet Validação Overview
A1: Validação do Project Overview
A2: Esta folha mostra linhas com dados em falta. Estado = REVER quando existe pelo menos uma falha.
A4: N° | B4: Project | C4: Company Name | D4: Status Detail | E4: Active Contract | F4: Falta projeto | G4: Falta empresa | H4: Falta NIF | I4: Falta localização | J4: Falta duração | K4: Falta start | L4: Falta email | M4: Falta Det Cobertura | N4: Falta Det Acesso | O4: Total falhas | P4: Estado | R4: Legenda
A5: =""&'Project Overview'!A2 -> 1 | B5: ='Project Overview'!B2 -> A Colmeia do Minho | C5: ='Project Overview'!C2 -> A Colmeia do Minho, S.A., | D5: ='Project Overview'!R2 -> ACTIVE | E5: ='Project Overview'!Y2 -> yes | F5: =IF(OR($A5="",$B5=""),1,0) -> 0 | G5: =IF($C5="",1,0) -> 0 | H5: =IF('Project Overview'!D2="",1,0) -> 0 | I5: =IF('Project Overview'!F2="",1,0) -> 0 | J5: =IF(AND($A5<>"",OR('Project Overview'!I2="ESCO",'Project Overview'!I2="EPC",'Project Overview'!I2="ESCO BUYOUT"),'Project Overview'!K2=""),1,0) -> 0 | K5: =IF(AND($A5<>"",'Project Overview'!M2=""),1,0) -> 0 | L5: =IF(AND($A5<>"",'Project Overview'!U2=""),1,0) -> 0 | M5: =IF(OR($A5="",'Project Overview'!O2="",'Project Overview'!O2="?"),1,0) -> 0 | N5: =IF(OR($A5="",'Project Overview'!P2="", 'Project Overview'!P2="?"),1,0) -> 0 | O5: =SUM(F5:N5) -> 0 | P5: =IF($A5="","",IF($O5=0,"OK","REVER")) -> OK | R5: OK | S5: Sem falhas
A6: =""&'Project Overview'!A3 -> 2 | B6: ='Project Overview'!B3 -> Florineve | C6: ='Project Overview'!C3 -> Florineve - Produção e Comércio de Flores de Corte | D6: ='Project Overview'!R3 -> ACTIVE | E6: ='Project Overview'!Y3 -> yes | F6: =IF(OR($A6="",$B6=""),1,0) -> 0 | G6: =IF($C6="",1,0) -> 0 | H6: =IF(AND($A6<>"",'Project Overview'!D3=""),1,0) -> 0 | I6: =IF(AND($A6<>"",'Project Overview'!F3=""),1,0) -> 0 | J6: =IF(AND($A6<>"",OR('Project Overview'!I3="ESCO",'Project Overview'!I3="EPC",'Project Overview'!I3="ESCO BUYOUT"),'Project Overview'!K3=""),1,0) -> 0 | K6: =IF(AND($A6<>"",'Project Overview'!M3=""),1,0) -> 0 | L6: =IF(AND($A6<>"",'Project Overview'!U3=""),1,0) -> 0 | M6: =IF(OR($A6="",'Project Overview'!O3="",'Project Overview'!O3="?"),1,0) -> 0 | N6: =IF(OR($A6="",'Project Overview'!P3="", 'Project Overview'!P3="?"),1,0) -> 0 | O6: =SUM(F6:N6) -> 0 | P6: =IF($A6="","",IF($O6=0,"OK","REVER")) -> OK | R6: REVER | S6: Faltam dados
A7: =""&'Project Overview'!A4 -> 3 | B7: ='Project Overview'!B4 -> Dialogos do Bosque | C7: ='Project Overview'!C4 -> Diálogos do Bosque, Unipessoal, LDA | D7: ='Project Overview'!R4 -> ACTIVE | E7: ='Project Overview'!Y4 -> yes | F7: =IF(OR($A7="",$B7=""),1,0) -> 0 | G7: =IF($C7="",1,0) -> 0 | H7: =IF(AND($A7<>"",'Project Overview'!D4=""),1,0) -> 0 | I7: =IF(AND($A7<>"",'Project Overview'!F4=""),1,0) -> 0 | J7: =IF(AND($A7<>"",OR('Project Overview'!I4="ESCO",'Project Overview'!I4="EPC",'Project Overview'!I4="ESCO BUYOUT"),'Project Overview'!K4=""),1,0) -> 0 | K7: =IF(AND($A7<>"",'Project Overview'!M4=""),1,0) -> 0 | L7: =IF(AND($A7<>"",'Project Overview'!U4=""),1,0) -> 0 | M7: =IF(OR($A7="",'Project Overview'!O4="",'Project Overview'!O4="?"),1,0) -> 0 | N7: =IF(OR($A7="",'Project Overview'!P4="", 'Project Overview'!P4="?"),1,0) -> 0 | O7: =SUM(F7:N7) -> 0 | P7: =IF($A7="","",IF($O7=0,"OK","REVER")) -> OK
A8: =""&'Project Overview'!A5 -> 4 | B8: ='Project Overview'!B5 -> Presuntos Lourenço 2 | C8: ='Project Overview'!C5 -> A. Pires Lourenço & Filhos S.A | D8: ='Project Overview'!R5 -> ACTIVE | E8: ='Project Overview'!Y5 -> yes | F8: =IF(AND($A8<>"",$B8=""),1,0) -> 0 | G8: =IF(AND($A8<>"",$C8=""),1,0) -> 0 | H8: =IF(AND($A8<>"",'Project Overview'!D5=""),1,0) -> 0 | I8: =IF(AND($A8<>"",'Project Overview'!F5=""),1,0) -> 0 | J8: =IF(AND($A8<>"",OR('Project Overview'!I5="ESCO",'Project Overview'!I5="EPC",'Project Overview'!I5="ESCO BUYOUT"),'Project Overview'!K5=""),1,0) -> 0 | K8: =IF(AND($A8<>"",'Project Overview'!M5=""),1,0) -> 0 | L8: =IF(AND($A8<>"",'Project Overview'!U5=""),1,0) -> 0 | M8: =IF(OR($A8="",'Project Overview'!O5="",'Project Overview'!O5="?"),1,0) -> 0 | N8: =IF(OR($A8="",'Project Overview'!P5="", 'Project Overview'!P5="?"),1,0) -> 0 | O8: =SUM(F8:N8) -> 0 | P8: =IF($A8="","",IF($O8=0,"OK","REVER")) -> OK | R8: =N8 -> 0
A9: =""&'Project Overview'!A6 -> 4 | B9: ='Project Overview'!B6 -> Pires Lourenço 1 | C9: ='Project Overview'!C6 -> A. Pires Lourenço & Filhos S.A | D9: ='Project Overview'!R6 -> ACTIVE | E9: ='Project Overview'!Y6 -> yes | F9: =IF(OR($A9="",$B9=""),1,0) -> 0 | G9: =IF($C9="",1,0) -> 0 | H9: =IF(AND($A9<>"",'Project Overview'!D6=""),1,0) -> 0 | I9: =IF(AND($A9<>"",'Project Overview'!F6=""),1,0) -> 0 | J9: =IF(AND($A9<>"",OR('Project Overview'!I6="ESCO",'Project Overview'!I6="EPC",'Project Overview'!I6="ESCO BUYOUT"),'Project Overview'!K6=""),1,0) -> 0 | K9: =IF(AND($A9<>"",'Project Overview'!M6=""),1,0) -> 0 | L9: =IF(AND($A9<>"",'Project Overview'!U6=""),1,0) -> 0 | M9: =IF(OR($A9="",'Project Overview'!O6="",'Project Overview'!O6="?"),1,0) -> 0 | N9: =IF(OR($A9="",'Project Overview'!P6="", 'Project Overview'!P6="?"),1,0) -> 0 | O9: =SUM(F9:N9) -> 0 | P9: =IF($A9="","",IF($O9=0,"OK","REVER")) -> OK
A10: =""&'Project Overview'!A7 -> 5 | B10: ='Project Overview'!B7 -> Usinage | C10: ='Project Overview'!C7 -> Usinage - Maquinação e Porta Moldes, Lda | D10: ='Project Overview'!R7 -> ACTIVE | E10: ='Project Overview'!Y7 -> no | F10: =IF(AND($A10<>"",$B10=""),1,0) -> 0 | G10: =IF(AND($A10<>"",$C10=""),1,0) -> 0 | H10: =IF(AND($A10<>"",'Project Overview'!D7=""),1,0) -> 0 | I10: =IF(AND($A10<>"",'Project Overview'!F7=""),1,0) -> 0 | J10: =IF(AND($A10<>"",OR('Project Overview'!I7="ESCO",'Project Overview'!I7="EPC",'Project Overview'!I7="ESCO BUYOUT"),'Project Overview'!K7=""),1,0) -> 0 | K10: =IF(AND($A10<>"",'Project Overview'!M7=""),1,0) -> 0 | L10: =IF(AND($A10<>"",'Project Overview'!U7=""),1,0) -> 0 | M10: =IF(OR($A10="",'Project Overview'!O7="",'Project Overview'!O7="?"),1,0) -> 0 | N10: =IF(OR($A10="",'Project Overview'!P7="", 'Project Overview'!P7="?"),1,0) -> 0 | O10: =SUM(F10:N10) -> 0 | P10: =IF($A10="","",IF($O10=0,"OK","REVER")) -> OK
A11: =""&'Project Overview'!A8 -> 6 | B11: ='Project Overview'!B8 -> Museu Caramulo | C11: ='Project Overview'!C8 -> Fundação Abel e João de Lacerda | D11: ='Project Overview'!R8 -> ACTIVE | E11: ='Project Overview'!Y8 -> yes | F11: =IF(OR($A11="",$B11=""),1,0) -> 0 | G11: =IF($C11="",1,0) -> 0 | H11: =IF(AND($A11<>"",'Project Overview'!D8=""),1,0) -> 0 | I11: =IF(AND($A11<>"",'Project Overview'!F8=""),1,0) -> 0 | J11: =IF(AND($A11<>"",OR('Project Overview'!I8="ESCO",'Project Overview'!I8="EPC",'Project Overview'!I8="ESCO BUYOUT"),'Project Overview'!K8=""),1,0) -> 0 | K11: =IF(AND($A11<>"",'Project Overview'!M8=""),1,0) -> 0 | L11: =IF(AND($A11<>"",'Project Overview'!U8=""),1,0) -> 0 | M11: =IF(OR($A11="",'Project Overview'!O8="",'Project Overview'!O8="?"),1,0) -> 0 | N11: =IF(OR($A11="",'Project Overview'!P8="", 'Project Overview'!P8="?"),1,0) -> 0 | O11: =SUM(F11:N11) -> 0 | P11: =IF($A11="","",IF($O11=0,"OK","REVER")) -> OK
A12: =""&'Project Overview'!A9 -> 7 | B12: ='Project Overview'!B9 -> Confrontar Sabores | C12: ='Project Overview'!C9 -> Confrontan Sabores, Lda | D12: ='Project Overview'!R9 -> CANCELLED | E12: ='Project Overview'!Y9 -> no | F12: =IF(AND($A12<>"",$B12=""),1,0) -> 0 | G12: =IF(AND($A12<>"",$C12=""),1,0) -> 0 | H12: =IF(AND($A12<>"",'Project Overview'!D9=""),1,0) -> 0 | I12: =IF(AND($A12<>"",'Project Overview'!F9=""),1,0) -> 1 | J12: =IF(AND($A12<>"",OR('Project Overview'!I9="ESCO",'Project Overview'!I9="EPC",'Project Overview'!I9="ESCO BUYOUT"),'Project Overview'!K9=""),1,0) -> 0 | K12: =IF(AND($A12<>"",'Project Overview'!M9=""),1,0) -> 1 | L12: =IF(AND($A12<>"",'Project Overview'!U9=""),1,0) -> 1 | M12: =IF(OR($A12="",'Project Overview'!O9="",'Project Overview'!O9="?"),1,0) -> 1 | N12: =IF(OR($A12="",'Project Overview'!P9="", 'Project Overview'!P9="?"),1,0) -> 1 | O12: =SUM(F12:N12) -> 5 | P12: =IF($A12="","",IF($O12=0,"OK","REVER")) -> REVER
A13: =""&'Project Overview'!A10 -> 8 | B13: ='Project Overview'!B10 -> Marmores da Granja | C13: ='Project Overview'!C10 -> Marmores da Granja Lda | D13: ='Project Overview'!R10 -> ACTIVE | E13: ='Project Overview'!Y10 -> yes | F13: =IF(OR($A13="",$B13=""),1,0) -> 0 | G13: =IF($C13="",1,0) -> 0 | H13: =IF(AND($A13<>"",'Project Overview'!D10=""),1,0) -> 0 | I13: =IF(AND($A13<>"",'Project Overview'!F10=""),1,0) -> 0 | J13: =IF(AND($A13<>"",OR('Project Overview'!I10="ESCO",'Project Overview'!I10="EPC",'Project Overview'!I10="ESCO BUYOUT"),'Project Overview'!K10=""),1,0) -> 0 | K13: =IF(AND($A13<>"",'Project Overview'!M10=""),1,0) -> 0 | L13: =IF(AND($A13<>"",'Project Overview'!U10=""),1,0) -> 0 | M13: =IF(OR($A13="",'Project Overview'!O10="",'Project Overview'!O10="?"),1,0) -> 0 | N13: =IF(OR($A13="",'Project Overview'!P10="", 'Project Overview'!P10="?"),1,0) -> 0 | O13: =SUM(F13:N13) -> 0 | P13: =IF($A13="","",IF($O13=0,"OK","REVER")) -> OK
A14: =""&'Project Overview'!A11 -> 9 | B14: ='Project Overview'!B11 -> Lands Hause - Pataias | C14: ='Project Overview'!C11 -> Ah Pinhal do Rei, Lda | D14: ='Project Overview'!R11 -> ACTIVE | E14: ='Project Overview'!Y11 -> no | F14: =IF(AND($A14<>"",$B14=""),1,0) -> 0 | G14: =IF(AND($A14<>"",$C14=""),1,0) -> 0 | H14: =IF(AND($A14<>"",'Project Overview'!D11=""),1,0) -> 0 | I14: =IF(AND($A14<>"",'Project Overview'!F11=""),1,0) -> 0 | J14: =IF(AND($A14<>"",OR('Project Overview'!I11="ESCO",'Project Overview'!I11="EPC",'Project Overview'!I11="ESCO BUYOUT"),'Project Overview'!K11=""),1,0) -> 0 | K14: =IF(AND($A14<>"",'Project Overview'!M11=""),1,0) -> 0 | L14: =IF(AND($A14<>"",'Project Overview'!U11=""),1,0) -> 0 | M14: =IF(OR($A14="",'Project Overview'!O11="",'Project Overview'!O11="?"),1,0) -> 0 | N14: =IF(OR($A14="",'Project Overview'!P11="", 'Project Overview'!P11="?"),1,0) -> 0 | O14: =SUM(F14:N14) -> 0 | P14: =IF($A14="","",IF($O14=0,"OK","REVER")) -> OK
A15: =""&'Project Overview'!A12 -> 10 | B15: ='Project Overview'!B12 -> Lusobatata | C15: ='Project Overview'!C12 -> Lusobatata- Produtos de lV Gama, LDA | D15: ='Project Overview'!R12 -> ACTIVE | E15: ='Project Overview'!Y12 -> yes | F15: =IF(OR($A15="",$B15=""),1,0) -> 0 | G15: =IF($C15="",1,0) -> 0 | H15: =IF(AND($A15<>"",'Project Overview'!D12=""),1,0) -> 0 | I15: =IF(AND($A15<>"",'Project Overview'!F12=""),1,0) -> 0 | J15: =IF(AND($A15<>"",OR('Project Overview'!I12="ESCO",'Project Overview'!I12="EPC",'Project Overview'!I12="ESCO BUYOUT"),'Project Overview'!K12=""),1,0) -> 0 | K15: =IF(AND($A15<>"",'Project Overview'!M12=""),1,0) -> 0 | L15: =IF(AND($A15<>"",'Project Overview'!U12=""),1,0) -> 0 | M15: =IF(OR($A15="",'Project Overview'!O12="",'Project Overview'!O12="?"),1,0) -> 0 | N15: =IF(OR($A15="",'Project Overview'!P12="", 'Project Overview'!P12="?"),1,0) -> 0 | O15: =SUM(F15:N15) -> 0 | P15: =IF($A15="","",IF($O15=0,"OK","REVER")) -> OK
A16: =""&'Project Overview'!A13 -> 11 | B16: ='Project Overview'!B13 -> Solidus | C16: ='Project Overview'!C13 -> Solidus Soluções Para Ferramentas e Moldes, Lda. | D16: ='Project Overview'!R13 -> ACTIVE | E16: ='Project Overview'!Y13 -> yes | F16: =IF(OR($A16="",$B16=""),1,0) -> 0 | G16: =IF($C16="",1,0) -> 0 | H16: =IF(AND($A16<>"",'Project Overview'!D13=""),1,0) -> 0 | I16: =IF(AND($A16<>"",'Project Overview'!F13=""),1,0) -> 0 | J16: =IF(AND($A16<>"",OR('Project Overview'!I13="ESCO",'Project Overview'!I13="EPC",'Project Overview'!I13="ESCO BUYOUT"),'Project Overview'!K13=""),1,0) -> 0 | K16: =IF(AND($A16<>"",'Project Overview'!M13=""),1,0) -> 0 | L16: =IF(AND($A16<>"",'Project Overview'!U13=""),1,0) -> 0 | M16: =IF(OR($A16="",'Project Overview'!O13="",'Project Overview'!O13="?"),1,0) -> 0 | N16: =IF(OR($A16="",'Project Overview'!P13="", 'Project Overview'!P13="?"),1,0) -> 0 | O16: =SUM(F16:N16) -> 0 | P16: =IF($A16="","",IF($O16=0,"OK","REVER")) -> OK
A17: =""&'Project Overview'!A14 -> 12 | B17: ='Project Overview'!B14 -> NC Logistica | C17: ='Project Overview'!C14 -> Natureza Em Congelados, Armazenagem e Comercialização de Produtos Alimentares Lda | D17: ='Project Overview'!R14 -> CANCELLED | E17: ='Project Overview'!Y14 -> no | F17: =IF(AND($A17<>"",$B17=""),1,0) -> 0 | G17: =IF(AND($A17<>"",$C17=""),1,0) -> 0 | H17: =IF(AND($A17<>"",'Project Overview'!D14=""),1,0) -> 0 | I17: =IF(AND($A17<>"",'Project Overview'!F14=""),1,0) -> 1 | J17: =IF(AND($A17<>"",OR('Project Overview'!I14="ESCO",'Project Overview'!I14="EPC",'Project Overview'!I14="ESCO BUYOUT"),'Project Overview'!K14=""),1,0) -> 0 | K17: =IF(AND($A17<>"",'Project Overview'!M14=""),1,0) -> 1 | L17: =IF(AND($A17<>"",'Project Overview'!U14=""),1,0) -> 0 | M17: =IF(OR($A17="",'Project Overview'!O14="",'Project Overview'!O14="?"),1,0) -> 1 | N17: =IF(OR($A17="",'Project Overview'!P14="", 'Project Overview'!P14="?"),1,0) -> 1 | O17: =SUM(F17:N17) -> 4 | P17: =IF($A17="","",IF($O17=0,"OK","REVER")) -> REVER
A18: =""&'Project Overview'!A15 -> 13 | B18: ='Project Overview'!B15 -> Marmo J | C18: ='Project Overview'!C15 -> Marmo J - Exportação, Importação, Mármores Unipessoal Lda | D18: ='Project Overview'!R15 -> ACTIVE | E18: ='Project Overview'!Y15 -> yes | F18: =IF(OR($A18="",$B18=""),1,0) -> 0 | G18: =IF($C18="",1,0) -> 0 | H18: =IF(AND($A18<>"",'Project Overview'!D15=""),1,0) -> 0 | I18: =IF(AND($A18<>"",'Project Overview'!F15=""),1,0) -> 0 | J18: =IF(AND($A18<>"",OR('Project Overview'!I15="ESCO",'Project Overview'!I15="EPC",'Project Overview'!I15="ESCO BUYOUT"),'Project Overview'!K15=""),1,0) -> 0 | K18: =IF(AND($A18<>"",'Project Overview'!M15=""),1,0) -> 0 | L18: =IF(AND($A18<>"",'Project Overview'!U15=""),1,0) -> 0 | M18: =IF(OR($A18="",'Project Overview'!O15="",'Project Overview'!O15="?"),1,0) -> 0 | N18: =IF(OR($A18="",'Project Overview'!P15="", 'Project Overview'!P15="?"),1,0) -> 0 | O18: =SUM(F18:N18) -> 0 | P18: =IF($A18="","",IF($O18=0,"OK","REVER")) -> OK
A19: =""&'Project Overview'!A16 -> 14 | B19: ='Project Overview'!B16 -> Roufimar | C19: ='Project Overview'!C16 -> Roufimar Industria de Marmores, S.A | D19: ='Project Overview'!R16 -> ACTIVE | E19: ='Project Overview'!Y16 -> yes | F19: =IF(OR($A19="",$B19=""),1,0) -> 0 | G19: =IF($C19="",1,0) -> 0 | H19: =IF(AND($A19<>"",'Project Overview'!D16=""),1,0) -> 0 | I19: =IF(AND($A19<>"",'Project Overview'!F16=""),1,0) -> 0 | J19: =IF(AND($A19<>"",OR('Project Overview'!I16="ESCO",'Project Overview'!I16="EPC",'Project Overview'!I16="ESCO BUYOUT"),'Project Overview'!K16=""),1,0) -> 0 | K19: =IF(AND($A19<>"",'Project Overview'!M16=""),1,0) -> 0 | L19: =IF(AND($A19<>"",'Project Overview'!U16=""),1,0) -> 0 | M19: =IF(OR($A19="",'Project Overview'!O16="",'Project Overview'!O16="?"),1,0) -> 0 | N19: =IF(OR($A19="",'Project Overview'!P16="", 'Project Overview'!P16="?"),1,0) -> 0 | O19: =SUM(F19:N19) -> 0 | P19: =IF($A19="","",IF($O19=0,"OK","REVER")) -> OK
A20: =""&'Project Overview'!A17 -> 15 | B20: ='Project Overview'!B17 -> Viarco | C20: ='Project Overview'!C17 -> Viarco-Industria de Lapis Lda | D20: ='Project Overview'!R17 -> ACTIVE | E20: ='Project Overview'!Y17 -> yes | F20: =IF(OR($A20="",$B20=""),1,0) -> 0 | G20: =IF($C20="",1,0) -> 0 | H20: =IF(AND($A20<>"",'Project Overview'!D17=""),1,0) -> 0 | I20: =IF(AND($A20<>"",'Project Overview'!F17=""),1,0) -> 0 | J20: =IF(AND($A20<>"",OR('Project Overview'!I17="ESCO",'Project Overview'!I17="EPC",'Project Overview'!I17="ESCO BUYOUT"),'Project Overview'!K17=""),1,0) -> 0 | K20: =IF(AND($A20<>"",'Project Overview'!M17=""),1,0) -> 0 | L20: =IF(AND($A20<>"",'Project Overview'!U17=""),1,0) -> 0 | M20: =IF(OR($A20="",'Project Overview'!O17="",'Project Overview'!O17="?"),1,0) -> 0 | N20: =IF(OR($A20="",'Project Overview'!P17="", 'Project Overview'!P17="?"),1,0) -> 0 | O20: =SUM(F20:N20) -> 0 | P20: =IF($A20="","",IF($O20=0,"OK","REVER")) -> OK
A21: =""&'Project Overview'!A18 -> 16 | B21: ='Project Overview'!B18 -> O Zé Pacheco | C21: ='Project Overview'!C18 -> Gadelho de Castro, S.A | D21: ='Project Overview'!R18 -> ACTIVE | E21: ='Project Overview'!Y18 -> yes | F21: =IF(OR($A21="",$B21=""),1,0) -> 0 | G21: =IF($C21="",1,0) -> 0 | H21: =IF(AND($A21<>"",'Project Overview'!D18=""),1,0) -> 0 | I21: =IF(AND($A21<>"",'Project Overview'!F18=""),1,0) -> 0 | J21: =IF(AND($A21<>"",OR('Project Overview'!I18="ESCO",'Project Overview'!I18="EPC",'Project Overview'!I18="ESCO BUYOUT"),'Project Overview'!K18=""),1,0) -> 0 | K21: =IF(AND($A21<>"",'Project Overview'!M18=""),1,0) -> 0 | L21: =IF(AND($A21<>"",'Project Overview'!U18=""),1,0) -> 0 | M21: =IF(OR($A21="",'Project Overview'!O18="",'Project Overview'!O18="?"),1,0) -> 0 | N21: =IF(OR($A21="",'Project Overview'!P18="", 'Project Overview'!P18="?"),1,0) -> 0 | O21: =SUM(F21:N21) -> 0 | P21: =IF($A21="","",IF($O21=0,"OK","REVER")) -> OK
A22: =""&'Project Overview'!A19 -> 17 | B22: ='Project Overview'!B19 -> Amadois | C22: ='Project Overview'!C19 -> Amadois-Calçado Lda | D22: ='Project Overview'!R19 -> ACTIVE | E22: ='Project Overview'!Y19 -> yes | F22: =IF(OR($A22="",$B22=""),1,0) -> 0 | G22: =IF($C22="",1,0) -> 0 | H22: =IF(AND($A22<>"",'Project Overview'!D19=""),1,0) -> 0 | I22: =IF(AND($A22<>"",'Project Overview'!F19=""),1,0) -> 0 | J22: =IF(AND($A22<>"",OR('Project Overview'!I19="ESCO",'Project Overview'!I19="EPC",'Project Overview'!I19="ESCO BUYOUT"),'Project Overview'!K19=""),1,0) -> 0 | K22: =IF(AND($A22<>"",'Project Overview'!M19=""),1,0) -> 0 | L22: =IF(AND($A22<>"",'Project Overview'!U19=""),1,0) -> 0 | M22: =IF(OR($A22="",'Project Overview'!O19="",'Project Overview'!O19="?"),1,0) -> 0 | N22: =IF(OR($A22="",'Project Overview'!P19="", 'Project Overview'!P19="?"),1,0) -> 0 | O22: =SUM(F22:N22) -> 0 | P22: =IF($A22="","",IF($O22=0,"OK","REVER")) -> OK
A23: =""&'Project Overview'!A20 -> 18 | B23: ='Project Overview'!B20 -> Transportes Rapido | C23: ='Project Overview'!C20 -> Sociedade de Transportes Poiarense Lda | D23: ='Project Overview'!R20 -> ACTIVE | E23: ='Project Overview'!Y20 -> yes | F23: =IF(OR($A23="",$B23=""),1,0) -> 0 | G23: =IF($C23="",1,0) -> 0 | H23: =IF(AND($A23<>"",'Project Overview'!D20=""),1,0) -> 0 | I23: =IF(AND($A23<>"",'Project Overview'!F20=""),1,0) -> 0 | J23: =IF(AND($A23<>"",OR('Project Overview'!I20="ESCO",'Project Overview'!I20="EPC",'Project Overview'!I20="ESCO BUYOUT"),'Project Overview'!K20=""),1,0) -> 0 | K23: =IF(AND($A23<>"",'Project Overview'!M20=""),1,0) -> 0 | L23: =IF(AND($A23<>"",'Project Overview'!U20=""),1,0) -> 0 | M23: =IF(OR($A23="",'Project Overview'!O20="",'Project Overview'!O20="?"),1,0) -> 0 | N23: =IF(OR($A23="",'Project Overview'!P20="", 'Project Overview'!P20="?"),1,0) -> 0 | O23: =SUM(F23:N23) -> 0 | P23: =IF($A23="","",IF($O23=0,"OK","REVER")) -> OK
A24: =""&'Project Overview'!A21 -> 19 | B24: ='Project Overview'!B21 -> Granetos | C24: ='Project Overview'!C21 -> Granetos-Mármores e Granitos, S.A | D24: ='Project Overview'!R21 -> ACTIVE | E24: ='Project Overview'!Y21 -> no | F24: =IF(AND($A24<>"",$B24=""),1,0) -> 0 | G24: =IF(AND($A24<>"",$C24=""),1,0) -> 0 | H24: =IF(AND($A24<>"",'Project Overview'!D21=""),1,0) -> 0 | I24: =IF(AND($A24<>"",'Project Overview'!F21=""),1,0) -> 0 | J24: =IF(AND($A24<>"",OR('Project Overview'!I21="ESCO",'Project Overview'!I21="EPC",'Project Overview'!I21="ESCO BUYOUT"),'Project Overview'!K21=""),1,0) -> 0 | K24: =IF(AND($A24<>"",'Project Overview'!M21=""),1,0) -> 0 | L24: =IF(AND($A24<>"",'Project Overview'!U21=""),1,0) -> 0 | M24: =IF(OR($A24="",'Project Overview'!O21="",'Project Overview'!O21="?"),1,0) -> 0 | N24: =IF(OR($A24="",'Project Overview'!P21="", 'Project Overview'!P21="?"),1,0) -> 0 | O24: =SUM(F24:N24) -> 0 | P24: =IF($A24="","",IF($O24=0,"OK","REVER")) -> OK
A25: =""&'Project Overview'!A22 -> 20 | B25: ='Project Overview'!B22 -> Queijaria Inácio Corvelo | C25: ='Project Overview'!C22 -> Inácio José Vinhas Corvelo | D25: ='Project Overview'!R22 -> ACTIVE | E25: ='Project Overview'!Y22 -> no | F25: =IF(AND($A25<>"",$B25=""),1,0) -> 0 | G25: =IF(AND($A25<>"",$C25=""),1,0) -> 0 | H25: =IF(AND($A25<>"",'Project Overview'!D22=""),1,0) -> 0 | I25: =IF(AND($A25<>"",'Project Overview'!F22=""),1,0) -> 0 | J25: =IF(AND($A25<>"",OR('Project Overview'!I22="ESCO",'Project Overview'!I22="EPC",'Project Overview'!I22="ESCO BUYOUT"),'Project Overview'!K22=""),1,0) -> 0 | K25: =IF(AND($A25<>"",'Project Overview'!M22=""),1,0) -> 0 | L25: =IF(AND($A25<>"",'Project Overview'!U22=""),1,0) -> 1 | M25: =IF(OR($A25="",'Project Overview'!O22="",'Project Overview'!O22="?"),1,0) -> 0 | N25: =IF(OR($A25="",'Project Overview'!P22="", 'Project Overview'!P22="?"),1,0) -> 0 | O25: =SUM(F25:N25) -> 1 | P25: =IF($A25="","",IF($O25=0,"OK","REVER")) -> REVER
A26: =""&'Project Overview'!A23 -> 21 | B26: ='Project Overview'!B23 -> Topeca | C26: ='Project Overview'!C23 -> Topeca-Produtos de Construção Civil Lda | D26: ='Project Overview'!R23 -> ACTIVE | E26: ='Project Overview'!Y23 -> yes | F26: =IF(OR($A26="",$B26=""),1,0) -> 0 | G26: =IF($C26="",1,0) -> 0 | H26: =IF(AND($A26<>"",'Project Overview'!D23=""),1,0) -> 0 | I26: =IF(AND($A26<>"",'Project Overview'!F23=""),1,0) -> 0 | J26: =IF(AND($A26<>"",OR('Project Overview'!I23="ESCO",'Project Overview'!I23="EPC",'Project Overview'!I23="ESCO BUYOUT"),'Project Overview'!K23=""),1,0) -> 0 | K26: =IF(AND($A26<>"",'Project Overview'!M23=""),1,0) -> 0 | L26: =IF(AND($A26<>"",'Project Overview'!U23=""),1,0) -> 0 | M26: =IF(OR($A26="",'Project Overview'!O23="",'Project Overview'!O23="?"),1,0) -> 0 | N26: =IF(OR($A26="",'Project Overview'!P23="", 'Project Overview'!P23="?"),1,0) -> 0 | O26: =SUM(F26:N26) -> 0 | P26: =IF($A26="","",IF($O26=0,"OK","REVER")) -> OK
A27: =""&'Project Overview'!A24 -> 22 | B27: ='Project Overview'!B24 -> Mindtrooper | C27: ='Project Overview'!C24 -> Mindtrooper, Unipessoal, Limitada | D27: ='Project Overview'!R24 -> ACTIVE | E27: ='Project Overview'!Y24 -> no | F27: =IF(AND($A27<>"",$B27=""),1,0) -> 0 | G27: =IF(AND($A27<>"",$C27=""),1,0) -> 0 | H27: =IF(AND($A27<>"",'Project Overview'!D24=""),1,0) -> 0 | I27: =IF(AND($A27<>"",'Project Overview'!F24=""),1,0) -> 0 | J27: =IF(AND($A27<>"",OR('Project Overview'!I24="ESCO",'Project Overview'!I24="EPC",'Project Overview'!I24="ESCO BUYOUT"),'Project Overview'!K24=""),1,0) -> 0 | K27: =IF(AND($A27<>"",'Project Overview'!M24=""),1,0) -> 0 | L27: =IF(AND($A27<>"",'Project Overview'!U24=""),1,0) -> 1 | M27: =IF(OR($A27="",'Project Overview'!O24="",'Project Overview'!O24="?"),1,0) -> 1 | N27: =IF(OR($A27="",'Project Overview'!P24="", 'Project Overview'!P24="?"),1,0) -> 1 | O27: =SUM(F27:N27) -> 3 | P27: =IF($A27="","",IF($O27=0,"OK","REVER")) -> REVER
A28: =""&'Project Overview'!A25 -> 23 | B28: ='Project Overview'!B25 -> Heden | C28: ='Project Overview'!C25 -> Liveworks, Lda | D28: ='Project Overview'!R25 -> ACTIVE | E28: ='Project Overview'!Y25 -> no | F28: =IF(AND($A28<>"",$B28=""),1,0) -> 0 | G28: =IF(AND($A28<>"",$C28=""),1,0) -> 0 | H28: =IF(AND($A28<>"",'Project Overview'!D25=""),1,0) -> 0 | I28: =IF(AND($A28<>"",'Project Overview'!F25=""),1,0) -> 0 | J28: =IF(AND($A28<>"",OR('Project Overview'!I25="ESCO",'Project Overview'!I25="EPC",'Project Overview'!I25="ESCO BUYOUT"),'Project Overview'!K25=""),1,0) -> 0 | K28: =IF(AND($A28<>"",'Project Overview'!M25=""),1,0) -> 0 | L28: =IF(AND($A28<>"",'Project Overview'!U25=""),1,0) -> 0 | M28: =IF(OR($A28="",'Project Overview'!O25="",'Project Overview'!O25="?"),1,0) -> 0 | N28: =IF(OR($A28="",'Project Overview'!P25="", 'Project Overview'!P25="?"),1,0) -> 0 | O28: =SUM(F28:N28) -> 0 | P28: =IF($A28="","",IF($O28=0,"OK","REVER")) -> OK
A29: =""&'Project Overview'!A26 -> 24 | B29: ='Project Overview'!B26 -> O Bolo do Caco | C29: ='Project Overview'!C26 -> Horizontes Renovados Lda | D29: ='Project Overview'!R26 -> CANCELLED | E29: ='Project Overview'!Y26 -> no | F29: =IF(AND($A29<>"",$B29=""),1,0) -> 0 | G29: =IF(AND($A29<>"",$C29=""),1,0) -> 0 | H29: =IF(AND($A29<>"",'Project Overview'!D26=""),1,0) -> 0 | I29: =IF(AND($A29<>"",'Project Overview'!F26=""),1,0) -> 0 | J29: =IF(AND($A29<>"",OR('Project Overview'!I26="ESCO",'Project Overview'!I26="EPC",'Project Overview'!I26="ESCO BUYOUT"),'Project Overview'!K26=""),1,0) -> 0 | K29: =IF(AND($A29<>"",'Project Overview'!M26=""),1,0) -> 0 | L29: =IF(AND($A29<>"",'Project Overview'!U26=""),1,0) -> 1 | M29: =IF(OR($A29="",'Project Overview'!O26="",'Project Overview'!O26="?"),1,0) -> 1 | N29: =IF(OR($A29="",'Project Overview'!P26="", 'Project Overview'!P26="?"),1,0) -> 1 | O29: =SUM(F29:N29) -> 3 | P29: =IF($A29="","",IF($O29=0,"OK","REVER")) -> REVER
A30: =""&'Project Overview'!A27 -> 25 | B30: ='Project Overview'!B27 -> Betafiel | C30: ='Project Overview'!C27 -> Betafiel-Artefactos de Betão de Penafiel S.A | D30: ='Project Overview'!R27 -> CANCELLED | E30: ='Project Overview'!Y27 -> no | F30: =IF(AND($A30<>"",$B30=""),1,0) -> 0 | G30: =IF(AND($A30<>"",$C30=""),1,0) -> 0 | H30: =IF(AND($A30<>"",'Project Overview'!D27=""),1,0) -> 0 | I30: =IF(AND($A30<>"",'Project Overview'!F27=""),1,0) -> 1 | J30: =IF(AND($A30<>"",OR('Project Overview'!I27="ESCO",'Project Overview'!I27="EPC",'Project Overview'!I27="ESCO BUYOUT"),'Project Overview'!K27=""),1,0) -> 0 | K30: =IF(AND($A30<>"",'Project Overview'!M27=""),1,0) -> 1 | L30: =IF(AND($A30<>"",'Project Overview'!U27=""),1,0) -> 0 | M30: =IF(OR($A30="",'Project Overview'!O27="",'Project Overview'!O27="?"),1,0) -> 1 | N30: =IF(OR($A30="",'Project Overview'!P27="", 'Project Overview'!P27="?"),1,0) -> 1 | O30: =SUM(F30:N30) -> 4 | P30: =IF($A30="","",IF($O30=0,"OK","REVER")) -> REVER
A31: =""&'Project Overview'!A28 -> 26 | B31: ='Project Overview'!B28 -> Multiaves | C31: ='Project Overview'!C28 -> Multiaves-Avicola Internacional Lda | D31: ='Project Overview'!R28 -> ACTIVE | E31: ='Project Overview'!Y28 -> yes | F31: =IF(OR($A31="",$B31=""),1,0) -> 0 | G31: =IF($C31="",1,0) -> 0 | H31: =IF(AND($A31<>"",'Project Overview'!D28=""),1,0) -> 0 | I31: =IF(AND($A31<>"",'Project Overview'!F28=""),1,0) -> 0 | J31: =IF(AND($A31<>"",OR('Project Overview'!I28="ESCO",'Project Overview'!I28="EPC",'Project Overview'!I28="ESCO BUYOUT"),'Project Overview'!K28=""),1,0) -> 0 | K31: =IF(AND($A31<>"",'Project Overview'!M28=""),1,0) -> 0 | L31: =IF(AND($A31<>"",'Project Overview'!U28=""),1,0) -> 0 | M31: =IF(OR($A31="",'Project Overview'!O28="",'Project Overview'!O28="?"),1,0) -> 0 | N31: =IF(OR($A31="",'Project Overview'!P28="", 'Project Overview'!P28="?"),1,0) -> 0 | O31: =SUM(F31:N31) -> 0 | P31: =IF($A31="","",IF($O31=0,"OK","REVER")) -> OK
A32: =""&'Project Overview'!A29 -> 27 | B32: ='Project Overview'!B29 -> ITM Moita | C32: ='Project Overview'!C29 -> Intervedros - Supermercados, Lda | D32: ='Project Overview'!R29 -> ACTIVE | E32: ='Project Overview'!Y29 -> yes | F32: =IF(OR($A32="",$B32=""),1,0) -> 0 | G32: =IF($C32="",1,0) -> 0 | H32: =IF(AND($A32<>"",'Project Overview'!D29=""),1,0) -> 0 | I32: =IF(AND($A32<>"",'Project Overview'!F29=""),1,0) -> 0 | J32: =IF(AND($A32<>"",OR('Project Overview'!I29="ESCO",'Project Overview'!I29="EPC",'Project Overview'!I29="ESCO BUYOUT"),'Project Overview'!K29=""),1,0) -> 0 | K32: =IF(AND($A32<>"",'Project Overview'!M29=""),1,0) -> 0 | L32: =IF(AND($A32<>"",'Project Overview'!U29=""),1,0) -> 0 | M32: =IF(OR($A32="",'Project Overview'!O29="",'Project Overview'!O29="?"),1,0) -> 0 | N32: =IF(OR($A32="",'Project Overview'!P29="", 'Project Overview'!P29="?"),1,0) -> 0 | O32: =SUM(F32:N32) -> 0 | P32: =IF($A32="","",IF($O32=0,"OK","REVER")) -> OK
A33: =""&'Project Overview'!A30 -> 28 | B33: ='Project Overview'!B30 -> Serralharia Vieira | C33: ='Project Overview'!C30 -> Serralharia Vieira Lda | D33: ='Project Overview'!R30 -> ACTIVE | E33: ='Project Overview'!Y30 -> yes | F33: =IF(OR($A33="",$B33=""),1,0) -> 0 | G33: =IF($C33="",1,0) -> 0 | H33: =IF(AND($A33<>"",'Project Overview'!D30=""),1,0) -> 0 | I33: =IF(AND($A33<>"",'Project Overview'!F30=""),1,0) -> 0 | J33: =IF(AND($A33<>"",OR('Project Overview'!I30="ESCO",'Project Overview'!I30="EPC",'Project Overview'!I30="ESCO BUYOUT"),'Project Overview'!K30=""),1,0) -> 0 | K33: =IF(AND($A33<>"",'Project Overview'!M30=""),1,0) -> 0 | L33: =IF(AND($A33<>"",'Project Overview'!U30=""),1,0) -> 0 | M33: =IF(OR($A33="",'Project Overview'!O30="",'Project Overview'!O30="?"),1,0) -> 0 | N33: =IF(OR($A33="",'Project Overview'!P30="", 'Project Overview'!P30="?"),1,0) -> 0 | O33: =SUM(F33:N33) -> 0 | P33: =IF($A33="","",IF($O33=0,"OK","REVER")) -> OK
A34: =""&'Project Overview'!A31 -> 29 | B34: ='Project Overview'!B31 -> Colégio Nossa Senhora da Apresentação | C34: ='Project Overview'!C31 -> Colégio Diocesano de Nossa Senhora da Apresentação | D34: ='Project Overview'!R31 -> ACTIVE | E34: ='Project Overview'!Y31 -> yes | F34: =IF(OR($A34="",$B34=""),1,0) -> 0 | G34: =IF($C34="",1,0) -> 0 | H34: =IF(AND($A34<>"",'Project Overview'!D31=""),1,0) -> 0 | I34: =IF(AND($A34<>"",'Project Overview'!F31=""),1,0) -> 0 | J34: =IF(AND($A34<>"",OR('Project Overview'!I31="ESCO",'Project Overview'!I31="EPC",'Project Overview'!I31="ESCO BUYOUT"),'Project Overview'!K31=""),1,0) -> 0 | K34: =IF(AND($A34<>"",'Project Overview'!M31=""),1,0) -> 0 | L34: =IF(AND($A34<>"",'Project Overview'!U31=""),1,0) -> 0 | M34: =IF(OR($A34="",'Project Overview'!O31="",'Project Overview'!O31="?"),1,0) -> 0 | N34: =IF(OR($A34="",'Project Overview'!P31="", 'Project Overview'!P31="?"),1,0) -> 0 | O34: =SUM(F34:N34) -> 0 | P34: =IF($A34="","",IF($O34=0,"OK","REVER")) -> OK
A35: =""&'Project Overview'!A32 -> 30 | B35: ='Project Overview'!B32 -> Absorvalor | C35: ='Project Overview'!C32 -> Absorvalor Lda | D35: ='Project Overview'!R32 -> ACTIVE | E35: ='Project Overview'!Y32 -> no | F35: =IF(AND($A35<>"",$B35=""),1,0) -> 0 | G35: =IF(AND($A35<>"",$C35=""),1,0) -> 0 | H35: =IF(AND($A35<>"",'Project Overview'!D32=""),1,0) -> 0 | I35: =IF(AND($A35<>"",'Project Overview'!F32=""),1,0) -> 0 | J35: =IF(AND($A35<>"",OR('Project Overview'!I32="ESCO",'Project Overview'!I32="EPC",'Project Overview'!I32="ESCO BUYOUT"),'Project Overview'!K32=""),1,0) -> 0 | K35: =IF(AND($A35<>"",'Project Overview'!M32=""),1,0) -> 0 | L35: =IF(AND($A35<>"",'Project Overview'!U32=""),1,0) -> 1 | M35: =IF(OR($A35="",'Project Overview'!O32="",'Project Overview'!O32="?"),1,0) -> 0 | N35: =IF(OR($A35="",'Project Overview'!P32="", 'Project Overview'!P32="?"),1,0) -> 0 | O35: =SUM(F35:N35) -> 1 | P35: =IF($A35="","",IF($O35=0,"OK","REVER")) -> REVER
A36: =""&'Project Overview'!A33 -> 31 | B36: ='Project Overview'!B33 -> MC Rios | C36: ='Project Overview'!C33 -> M.C. Rios, S.A | D36: ='Project Overview'!R33 -> CANCELLED | E36: ='Project Overview'!Y33 -> no | F36: =IF(AND($A36<>"",$B36=""),1,0) -> 0 | G36: =IF(AND($A36<>"",$C36=""),1,0) -> 0 | H36: =IF(AND($A36<>"",'Project Overview'!D33=""),1,0) -> 0 | I36: =IF(AND($A36<>"",'Project Overview'!F33=""),1,0) -> 1 | J36: =IF(AND($A36<>"",OR('Project Overview'!I33="ESCO",'Project Overview'!I33="EPC",'Project Overview'!I33="ESCO BUYOUT"),'Project Overview'!K33=""),1,0) -> 0 | K36: =IF(AND($A36<>"",'Project Overview'!M33=""),1,0) -> 1 | L36: =IF(AND($A36<>"",'Project Overview'!U33=""),1,0) -> 1 | M36: =IF(OR($A36="",'Project Overview'!O33="",'Project Overview'!O33="?"),1,0) -> 1 | N36: =IF(OR($A36="",'Project Overview'!P33="", 'Project Overview'!P33="?"),1,0) -> 1 | O36: =SUM(F36:N36) -> 5 | P36: =IF($A36="","",IF($O36=0,"OK","REVER")) -> REVER
A37: =""&'Project Overview'!A34 -> 32 | B37: ='Project Overview'!B34 -> VCP | C37: ='Project Overview'!C34 -> Vidraria Central do Porto, S.A | D37: ='Project Overview'!R34 -> ACTIVE | E37: ='Project Overview'!Y34 -> no | F37: =IF(AND($A37<>"",$B37=""),1,0) -> 0 | G37: =IF(AND($A37<>"",$C37=""),1,0) -> 0 | H37: =IF(AND($A37<>"",'Project Overview'!D34=""),1,0) -> 0 | I37: =IF(AND($A37<>"",'Project Overview'!F34=""),1,0) -> 0 | J37: =IF(AND($A37<>"",OR('Project Overview'!I34="ESCO",'Project Overview'!I34="EPC",'Project Overview'!I34="ESCO BUYOUT"),'Project Overview'!K34=""),1,0) -> 0 | K37: =IF(AND($A37<>"",'Project Overview'!M34=""),1,0) -> 0 | L37: =IF(AND($A37<>"",'Project Overview'!U34=""),1,0) -> 1 | M37: =IF(OR($A37="",'Project Overview'!O34="",'Project Overview'!O34="?"),1,0) -> 0 | N37: =IF(OR($A37="",'Project Overview'!P34="", 'Project Overview'!P34="?"),1,0) -> 0 | O37: =SUM(F37:N37) -> 1 | P37: =IF($A37="","",IF($O37=0,"OK","REVER")) -> REVER
A38: =""&'Project Overview'!A35 -> 33 | B38: ='Project Overview'!B35 -> Sicobrita | C38: ='Project Overview'!C35 -> Sicobrita - Extracção e Britagem de Pedra S.A | D38: ='Project Overview'!R35 -> ACTIVE | E38: ='Project Overview'!Y35 -> yes | F38: =IF(OR($A38="",$B38=""),1,0) -> 0 | G38: =IF($C38="",1,0) -> 0 | H38: =IF(AND($A38<>"",'Project Overview'!D35=""),1,0) -> 0 | I38: =IF(AND($A38<>"",'Project Overview'!F35=""),1,0) -> 0 | J38: =IF(AND($A38<>"",OR('Project Overview'!I35="ESCO",'Project Overview'!I35="EPC",'Project Overview'!I35="ESCO BUYOUT"),'Project Overview'!K35=""),1,0) -> 0 | K38: =IF(AND($A38<>"",'Project Overview'!M35=""),1,0) -> 0 | L38: =IF(AND($A38<>"",'Project Overview'!U35=""),1,0) -> 0 | M38: =IF(OR($A38="",'Project Overview'!O35="",'Project Overview'!O35="?"),1,0) -> 0 | N38: =IF(OR($A38="",'Project Overview'!P35="", 'Project Overview'!P35="?"),1,0) -> 0 | O38: =SUM(F38:N38) -> 0 | P38: =IF($A38="","",IF($O38=0,"OK","REVER")) -> OK
A39: =""&'Project Overview'!A36 -> 34 | B39: ='Project Overview'!B36 -> Mirandesa | C39: ='Project Overview'!C36 -> Cooperativa Agro-Pecuária Mirandesa Crl | D39: ='Project Overview'!R36 -> ACTIVE | E39: ='Project Overview'!Y36 -> yes | F39: =IF(OR($A39="",$B39=""),1,0) -> 0 | G39: =IF($C39="",1,0) -> 0 | H39: =IF(AND($A39<>"",'Project Overview'!D36=""),1,0) -> 0 | I39: =IF(AND($A39<>"",'Project Overview'!F36=""),1,0) -> 0 | J39: =IF(AND($A39<>"",OR('Project Overview'!I36="ESCO",'Project Overview'!I36="EPC",'Project Overview'!I36="ESCO BUYOUT"),'Project Overview'!K36=""),1,0) -> 0 | K39: =IF(AND($A39<>"",'Project Overview'!M36=""),1,0) -> 0 | L39: =IF(AND($A39<>"",'Project Overview'!U36=""),1,0) -> 0 | M39: =IF(OR($A39="",'Project Overview'!O36="",'Project Overview'!O36="?"),1,0) -> 0 | N39: =IF(OR($A39="",'Project Overview'!P36="", 'Project Overview'!P36="?"),1,0) -> 0 | O39: =SUM(F39:N39) -> 0 | P39: =IF($A39="","",IF($O39=0,"OK","REVER")) -> OK
A40: =""&'Project Overview'!A37 -> 35 | B40: ='Project Overview'!B37 -> Jovi-Sola | C40: ='Project Overview'!C37 -> Jovi-Sola – Pré fabricados para calçado, Lda | D40: ='Project Overview'!R37 -> CANCELLED | E40: ='Project Overview'!Y37 -> no | F40: =IF(AND($A40<>"",$B40=""),1,0) -> 0 | G40: =IF(AND($A40<>"",$C40=""),1,0) -> 0 | H40: =IF(AND($A40<>"",'Project Overview'!D37=""),1,0) -> 0 | I40: =IF(AND($A40<>"",'Project Overview'!F37=""),1,0) -> 1 | J40: =IF(AND($A40<>"",OR('Project Overview'!I37="ESCO",'Project Overview'!I37="EPC",'Project Overview'!I37="ESCO BUYOUT"),'Project Overview'!K37=""),1,0) -> 0 | K40: =IF(AND($A40<>"",'Project Overview'!M37=""),1,0) -> 1 | L40: =IF(AND($A40<>"",'Project Overview'!U37=""),1,0) -> 0 | M40: =IF(OR($A40="",'Project Overview'!O37="",'Project Overview'!O37="?"),1,0) -> 1 | N40: =IF(OR($A40="",'Project Overview'!P37="", 'Project Overview'!P37="?"),1,0) -> 1 | O40: =SUM(F40:N40) -> 4 | P40: =IF($A40="","",IF($O40=0,"OK","REVER")) -> REVER
A41: =""&'Project Overview'!A38 -> 36 | B41: ='Project Overview'!B38 -> Joaquim Pinheiro Santos | C41: ='Project Overview'!C38 -> JOAQUIM PINHEIRO SANTOS,SUCESSORES LDA | D41: ='Project Overview'!R38 -> ACTIVE | E41: ='Project Overview'!Y38 -> no | F41: =IF(AND($A41<>"",$B41=""),1,0) -> 0 | G41: =IF(AND($A41<>"",$C41=""),1,0) -> 0 | H41: =IF(AND($A41<>"",'Project Overview'!D38=""),1,0) -> 0 | I41: =IF(AND($A41<>"",'Project Overview'!F38=""),1,0) -> 0 | J41: =IF(AND($A41<>"",OR('Project Overview'!I38="ESCO",'Project Overview'!I38="EPC",'Project Overview'!I38="ESCO BUYOUT"),'Project Overview'!K38=""),1,0) -> 0 | K41: =IF(AND($A41<>"",'Project Overview'!M38=""),1,0) -> 0 | L41: =IF(AND($A41<>"",'Project Overview'!U38=""),1,0) -> 0 | M41: =IF(OR($A41="",'Project Overview'!O38="",'Project Overview'!O38="?"),1,0) -> 0 | N41: =IF(OR($A41="",'Project Overview'!P38="", 'Project Overview'!P38="?"),1,0) -> 0 | O41: =SUM(F41:N41) -> 0 | P41: =IF($A41="","",IF($O41=0,"OK","REVER")) -> OK
A42: =""&'Project Overview'!A39 -> 37 | B42: ='Project Overview'!B39 -> Ferraz & Ferreira | C42: ='Project Overview'!C39 -> Ferraz & Ferreira, Lda. | D42: ='Project Overview'!R39 -> ACTIVE | E42: ='Project Overview'!Y39 -> yes | F42: =IF(OR($A42="",$B42=""),1,0) -> 0 | G42: =IF($C42="",1,0) -> 0 | H42: =IF(AND($A42<>"",'Project Overview'!D39=""),1,0) -> 0 | I42: =IF(AND($A42<>"",'Project Overview'!F39=""),1,0) -> 0 | J42: =IF(AND($A42<>"",OR('Project Overview'!I39="ESCO",'Project Overview'!I39="EPC",'Project Overview'!I39="ESCO BUYOUT"),'Project Overview'!K39=""),1,0) -> 0 | K42: =IF(AND($A42<>"",'Project Overview'!M39=""),1,0) -> 0 | L42: =IF(AND($A42<>"",'Project Overview'!U39=""),1,0) -> 0 | M42: =IF(OR($A42="",'Project Overview'!O39="",'Project Overview'!O39="?"),1,0) -> 0 | N42: =IF(OR($A42="",'Project Overview'!P39="", 'Project Overview'!P39="?"),1,0) -> 0 | O42: =SUM(F42:N42) -> 0 | P42: =IF($A42="","",IF($O42=0,"OK","REVER")) -> OK
A43: =""&'Project Overview'!A40 -> 38 | B43: ='Project Overview'!B40 -> LIDL | C43: ='Project Overview'!C40 -> Lidl & Companhia | D43: ='Project Overview'!R40 -> ACTIVE | E43: ='Project Overview'!Y40 -> no | F43: =IF(AND($A43<>"",$B43=""),1,0) -> 0 | G43: =IF(AND($A43<>"",$C43=""),1,0) -> 0 | H43: =IF(AND($A43<>"",'Project Overview'!D40=""),1,0) -> 0 | I43: =IF(AND($A43<>"",'Project Overview'!F40=""),1,0) -> 1 | J43: =IF(AND($A43<>"",OR('Project Overview'!I40="ESCO",'Project Overview'!I40="EPC",'Project Overview'!I40="ESCO BUYOUT"),'Project Overview'!K40=""),1,0) -> 0 | K43: =IF(AND($A43<>"",'Project Overview'!M40=""),1,0) -> 0 | L43: =IF(AND($A43<>"",'Project Overview'!U40=""),1,0) -> 1 | M43: =IF(OR($A43="",'Project Overview'!O40="",'Project Overview'!O40="?"),1,0) -> 0 | N43: =IF(OR($A43="",'Project Overview'!P40="", 'Project Overview'!P40="?"),1,0) -> 0 | O43: =SUM(F43:N43) -> 2 | P43: =IF($A43="","",IF($O43=0,"OK","REVER")) -> REVER
A44: =""&'Project Overview'!A41 -> 39 | B44: ='Project Overview'!B41 -> ELS Sede | C44: ='Project Overview'!C41 -> Estevão Luis Salvador Lda | D44: ='Project Overview'!R41 -> ACTIVE | E44: ='Project Overview'!Y41 -> no | F44: =IF(AND($A44<>"",$B44=""),1,0) -> 0 | G44: =IF(AND($A44<>"",$C44=""),1,0) -> 0 | H44: =IF(AND($A44<>"",'Project Overview'!D41=""),1,0) -> 0 | I44: =IF(AND($A44<>"",'Project Overview'!F41=""),1,0) -> 0 | J44: =IF(AND($A44<>"",OR('Project Overview'!I41="ESCO",'Project Overview'!I41="EPC",'Project Overview'!I41="ESCO BUYOUT"),'Project Overview'!K41=""),1,0) -> 0 | K44: =IF(AND($A44<>"",'Project Overview'!M41=""),1,0) -> 0 | L44: =IF(AND($A44<>"",'Project Overview'!U41=""),1,0) -> 0 | M44: =IF(OR($A44="",'Project Overview'!O41="",'Project Overview'!O41="?"),1,0) -> 0 | N44: =IF(OR($A44="",'Project Overview'!P41="", 'Project Overview'!P41="?"),1,0) -> 0 | O44: =SUM(F44:N44) -> 0 | P44: =IF($A44="","",IF($O44=0,"OK","REVER")) -> OK
A45: =""&'Project Overview'!A42 -> 40 | B45: ='Project Overview'!B42 -> ELS Bolo do Caco | C45: ='Project Overview'!C42 -> Estevão Luis Salvador Lda | D45: ='Project Overview'!R42 -> ACTIVE | E45: ='Project Overview'!Y42 -> no | F45: =IF(AND($A45<>"",$B45=""),1,0) -> 0 | G45: =IF(AND($A45<>"",$C45=""),1,0) -> 0 | H45: =IF(AND($A45<>"",'Project Overview'!D42=""),1,0) -> 0 | I45: =IF(AND($A45<>"",'Project Overview'!F42=""),1,0) -> 0 | J45: =IF(AND($A45<>"",OR('Project Overview'!I42="ESCO",'Project Overview'!I42="EPC",'Project Overview'!I42="ESCO BUYOUT"),'Project Overview'!K42=""),1,0) -> 0 | K45: =IF(AND($A45<>"",'Project Overview'!M42=""),1,0) -> 0 | L45: =IF(AND($A45<>"",'Project Overview'!U42=""),1,0) -> 0 | M45: =IF(OR($A45="",'Project Overview'!O42="",'Project Overview'!O42="?"),1,0) -> 0 | N45: =IF(OR($A45="",'Project Overview'!P42="", 'Project Overview'!P42="?"),1,0) -> 0 | O45: =SUM(F45:N45) -> 0 | P45: =IF($A45="","",IF($O45=0,"OK","REVER")) -> OK
A46: =""&'Project Overview'!A43 -> 41 | B46: ='Project Overview'!B43 -> Mármores Galrão | C46: ='Project Overview'!C43 -> Marmores Galrão-Eduardo Galrão Jorge & Filhos S.A. | D46: ='Project Overview'!R43 -> ACTIVE | E46: ='Project Overview'!Y43 -> yes | F46: =IF(OR($A46="",$B46=""),1,0) -> 0 | G46: =IF($C46="",1,0) -> 0 | H46: =IF(AND($A46<>"",'Project Overview'!D43=""),1,0) -> 0 | I46: =IF(AND($A46<>"",'Project Overview'!F43=""),1,0) -> 0 | J46: =IF(AND($A46<>"",OR('Project Overview'!I43="ESCO",'Project Overview'!I43="EPC",'Project Overview'!I43="ESCO BUYOUT"),'Project Overview'!K43=""),1,0) -> 0 | K46: =IF(AND($A46<>"",'Project Overview'!M43=""),1,0) -> 0 | L46: =IF(AND($A46<>"",'Project Overview'!U43=""),1,0) -> 0 | M46: =IF(OR($A46="",'Project Overview'!O43="",'Project Overview'!O43="?"),1,0) -> 0 | N46: =IF(OR($A46="",'Project Overview'!P43="", 'Project Overview'!P43="?"),1,0) -> 0 | O46: =SUM(F46:N46) -> 0 | P46: =IF($A46="","",IF($O46=0,"OK","REVER")) -> OK
A47: =""&'Project Overview'!A44 -> 42 | B47: ='Project Overview'!B44 -> Granitos Galrão do Norte | C47: ='Project Overview'!C44 -> Granitos Galrão, Norte, Limitada | D47: ='Project Overview'!R44 -> ACTIVE | E47: ='Project Overview'!Y44 -> yes | F47: =IF(OR($A47="",$B47=""),1,0) -> 0 | G47: =IF($C47="",1,0) -> 0 | H47: =IF(AND($A47<>"",'Project Overview'!D44=""),1,0) -> 0 | I47: =IF(AND($A47<>"",'Project Overview'!F44=""),1,0) -> 0 | J47: =IF(AND($A47<>"",OR('Project Overview'!I44="ESCO",'Project Overview'!I44="EPC",'Project Overview'!I44="ESCO BUYOUT"),'Project Overview'!K44=""),1,0) -> 0 | K47: =IF(AND($A47<>"",'Project Overview'!M44=""),1,0) -> 0 | L47: =IF(AND($A47<>"",'Project Overview'!U44=""),1,0) -> 0 | M47: =IF(OR($A47="",'Project Overview'!O44="",'Project Overview'!O44="?"),1,0) -> 0 | N47: =IF(OR($A47="",'Project Overview'!P44="", 'Project Overview'!P44="?"),1,0) -> 0 | O47: =SUM(F47:N47) -> 0 | P47: =IF($A47="","",IF($O47=0,"OK","REVER")) -> OK
A48: =""&'Project Overview'!A45 -> 43 | B48: ='Project Overview'!B45 -> Ardavi | C48: ='Project Overview'!C45 -> Ardavi-Maquinação E Comercialização De Artefactos Metal... | D48: ='Project Overview'!R45 -> ACTIVE | E48: ='Project Overview'!Y45 -> yes | F48: =IF(OR($A48="",$B48=""),1,0) -> 0 | G48: =IF($C48="",1,0) -> 0 | H48: =IF(AND($A48<>"",'Project Overview'!D45=""),1,0) -> 0 | I48: =IF(AND($A48<>"",'Project Overview'!F45=""),1,0) -> 0 | J48: =IF(AND($A48<>"",OR('Project Overview'!I45="ESCO",'Project Overview'!I45="EPC",'Project Overview'!I45="ESCO BUYOUT"),'Project Overview'!K45=""),1,0) -> 0 | K48: =IF(AND($A48<>"",'Project Overview'!M45=""),1,0) -> 0 | L48: =IF(AND($A48<>"",'Project Overview'!U45=""),1,0) -> 0 | M48: =IF(OR($A48="",'Project Overview'!O45="",'Project Overview'!O45="?"),1,0) -> 0 | N48: =IF(OR($A48="",'Project Overview'!P45="", 'Project Overview'!P45="?"),1,0) -> 0 | O48: =SUM(F48:N48) -> 0 | P48: =IF($A48="","",IF($O48=0,"OK","REVER")) -> OK
A49: =""&'Project Overview'!A46 -> 44 | B49: ='Project Overview'!B46 -> Textil do Marco | C49: ='Project Overview'!C46 -> Textil Do Marco S.A. | D49: ='Project Overview'!R46 -> ACTIVE | E49: ='Project Overview'!Y46 -> no | F49: =IF(AND($A49<>"",$B49=""),1,0) -> 0 | G49: =IF(AND($A49<>"",$C49=""),1,0) -> 0 | H49: =IF(AND($A49<>"",'Project Overview'!D46=""),1,0) -> 0 | I49: =IF(AND($A49<>"",'Project Overview'!F46=""),1,0) -> 0 | J49: =IF(AND($A49<>"",OR('Project Overview'!I46="ESCO",'Project Overview'!I46="EPC",'Project Overview'!I46="ESCO BUYOUT"),'Project Overview'!K46=""),1,0) -> 0 | K49: =IF(AND($A49<>"",'Project Overview'!M46=""),1,0) -> 0 | L49: =IF(AND($A49<>"",'Project Overview'!U46=""),1,0) -> 1 | M49: =IF(OR($A49="",'Project Overview'!O46="",'Project Overview'!O46="?"),1,0) -> 0 | N49: =IF(OR($A49="",'Project Overview'!P46="", 'Project Overview'!P46="?"),1,0) -> 0 | O49: =SUM(F49:N49) -> 1 | P49: =IF($A49="","",IF($O49=0,"OK","REVER")) -> REVER
A50: =""&'Project Overview'!A47 -> 45 | B50: ='Project Overview'!B47 -> Diaco Fábrica 1 | C50: ='Project Overview'!C47 -> Diamantino Coelho & Filho S.A. | D50: ='Project Overview'!R47 -> ACTIVE | E50: ='Project Overview'!Y47 -> yes | F50: =IF(OR($A50="",$B50=""),1,0) -> 0 | G50: =IF($C50="",1,0) -> 0 | H50: =IF(AND($A50<>"",'Project Overview'!D47=""),1,0) -> 0 | I50: =IF(AND($A50<>"",'Project Overview'!F47=""),1,0) -> 0 | J50: =IF(AND($A50<>"",OR('Project Overview'!I47="ESCO",'Project Overview'!I47="EPC",'Project Overview'!I47="ESCO BUYOUT"),'Project Overview'!K47=""),1,0) -> 0 | K50: =IF(AND($A50<>"",'Project Overview'!M47=""),1,0) -> 0 | L50: =IF(AND($A50<>"",'Project Overview'!U47=""),1,0) -> 0 | M50: =IF(OR($A50="",'Project Overview'!O47="",'Project Overview'!O47="?"),1,0) -> 0 | N50: =IF(OR($A50="",'Project Overview'!P47="", 'Project Overview'!P47="?"),1,0) -> 0 | O50: =SUM(F50:N50) -> 0 | P50: =IF($A50="","",IF($O50=0,"OK","REVER")) -> OK
A51: =""&'Project Overview'!A48 -> 45 | B51: ='Project Overview'!B48 -> Diaco - Agriloja Tomar | C51: ='Project Overview'!C48 -> Diamantino Coelho & Filho S.A. | D51: ='Project Overview'!R48 -> ACTIVE | E51: ='Project Overview'!Y48 -> no | F51: =IF(AND($A51<>"",$B51=""),1,0) -> 0 | G51: =IF(AND($A51<>"",$C51=""),1,0) -> 0 | H51: =IF(AND($A51<>"",'Project Overview'!D48=""),1,0) -> 0 | I51: =IF(AND($A51<>"",'Project Overview'!F48=""),1,0) -> 0 | J51: =IF(AND($A51<>"",OR('Project Overview'!I48="ESCO",'Project Overview'!I48="EPC",'Project Overview'!I48="ESCO BUYOUT"),'Project Overview'!K48=""),1,0) -> 0 | K51: =IF(AND($A51<>"",'Project Overview'!M48=""),1,0) -> 0 | L51: =IF(AND($A51<>"",'Project Overview'!U48=""),1,0) -> 0 | M51: =IF(OR($A51="",'Project Overview'!O48="",'Project Overview'!O48="?"),1,0) -> 0 | N51: =IF(OR($A51="",'Project Overview'!P48="", 'Project Overview'!P48="?"),1,0) -> 0 | O51: =SUM(F51:N51) -> 0 | P51: =IF($A51="","",IF($O51=0,"OK","REVER")) -> OK
A52: =""&'Project Overview'!A49 -> 45 | B52: ='Project Overview'!B49 -> Diaco - Casa | C52: ='Project Overview'!C49 -> Diamantino Coelho & Filho S.A. | D52: ='Project Overview'!R49 -> ACTIVE | E52: ='Project Overview'!Y49 -> no | F52: =IF(AND($A52<>"",$B52=""),1,0) -> 0 | G52: =IF(AND($A52<>"",$C52=""),1,0) -> 0 | H52: =IF(AND($A52<>"",'Project Overview'!D49=""),1,0) -> 0 | I52: =IF(AND($A52<>"",'Project Overview'!F49=""),1,0) -> 0 | J52: =IF(AND($A52<>"",OR('Project Overview'!I49="ESCO",'Project Overview'!I49="EPC",'Project Overview'!I49="ESCO BUYOUT"),'Project Overview'!K49=""),1,0) -> 0 | K52: =IF(AND($A52<>"",'Project Overview'!M49=""),1,0) -> 0 | L52: =IF(AND($A52<>"",'Project Overview'!U49=""),1,0) -> 0 | M52: =IF(OR($A52="",'Project Overview'!O49="",'Project Overview'!O49="?"),1,0) -> 0 | N52: =IF(OR($A52="",'Project Overview'!P49="", 'Project Overview'!P49="?"),1,0) -> 0 | O52: =SUM(F52:N52) -> 0 | P52: =IF($A52="","",IF($O52=0,"OK","REVER")) -> OK
A53: =""&'Project Overview'!A50 -> 46 | B53: ='Project Overview'!B50 -> Pinhão & Irmão | C53: ='Project Overview'!C50 -> Pinhão & Irmão Lda | D53: ='Project Overview'!R50 -> ACTIVE | E53: ='Project Overview'!Y50 -> yes | F53: =IF(AND($A53<>"",$B53=""),1,0) -> 0 | G53: =IF(AND($A53<>"",$C53=""),1,0) -> 0 | H53: =IF(AND($A53<>"",'Project Overview'!D50=""),1,0) -> 0 | I53: =IF(AND($A53<>"",'Project Overview'!F50=""),1,0) -> 0 | J53: =IF(AND($A53<>"",OR('Project Overview'!I50="ESCO",'Project Overview'!I50="EPC",'Project Overview'!I50="ESCO BUYOUT"),'Project Overview'!K50=""),1,0) -> 0 | K53: =IF(AND($A53<>"",'Project Overview'!M50=""),1,0) -> 0 | L53: =IF(AND($A53<>"",'Project Overview'!U50=""),1,0) -> 0 | M53: =IF(OR($A53="",'Project Overview'!O50="",'Project Overview'!O50="?"),1,0) -> 0 | N53: =IF(OR($A53="",'Project Overview'!P50="", 'Project Overview'!P50="?"),1,0) -> 0 | O53: =SUM(F53:N53) -> 0 | P53: =IF($A53="","",IF($O53=0,"OK","REVER")) -> OK
A54: =""&'Project Overview'!A51 -> 47 | B54: ='Project Overview'!B51 -> Jetesetecar | C54: ='Project Overview'!C51 -> Jetesetecar - Equipamentos Auto Lda | D54: ='Project Overview'!R51 -> ACTIVE | E54: ='Project Overview'!Y51 -> yes | F54: =IF(OR($A54="",$B54=""),1,0) -> 0 | G54: =IF($C54="",1,0) -> 0 | H54: =IF(AND($A54<>"",'Project Overview'!D51=""),1,0) -> 0 | I54: =IF(AND($A54<>"",'Project Overview'!F51=""),1,0) -> 0 | J54: =IF(AND($A54<>"",OR('Project Overview'!I51="ESCO",'Project Overview'!I51="EPC",'Project Overview'!I51="ESCO BUYOUT"),'Project Overview'!K51=""),1,0) -> 0 | K54: =IF(AND($A54<>"",'Project Overview'!M51=""),1,0) -> 0 | L54: =IF(AND($A54<>"",'Project Overview'!U51=""),1,0) -> 0 | M54: =IF(OR($A54="",'Project Overview'!O51="",'Project Overview'!O51="?"),1,0) -> 0 | N54: =IF(OR($A54="",'Project Overview'!P51="", 'Project Overview'!P51="?"),1,0) -> 0 | O54: =SUM(F54:N54) -> 0 | P54: =IF($A54="","",IF($O54=0,"OK","REVER")) -> OK
A55: =""&'Project Overview'!A52 -> 48 | B55: ='Project Overview'!B52 -> ELS Laundos | C55: ='Project Overview'!C52 -> Estevão Luis Salvador Lda | D55: ='Project Overview'!R52 -> ACTIVE | E55: ='Project Overview'!Y52 -> no | F55: =IF(AND($A55<>"",$B55=""),1,0) -> 0 | G55: =IF(AND($A55<>"",$C55=""),1,0) -> 0 | H55: =IF(AND($A55<>"",'Project Overview'!D52=""),1,0) -> 0 | I55: =IF(AND($A55<>"",'Project Overview'!F52=""),1,0) -> 0 | J55: =IF(AND($A55<>"",OR('Project Overview'!I52="ESCO",'Project Overview'!I52="EPC",'Project Overview'!I52="ESCO BUYOUT"),'Project Overview'!K52=""),1,0) -> 0 | K55: =IF(AND($A55<>"",'Project Overview'!M52=""),1,0) -> 0 | L55: =IF(AND($A55<>"",'Project Overview'!U52=""),1,0) -> 0 | M55: =IF(OR($A55="",'Project Overview'!O52="",'Project Overview'!O52="?"),1,0) -> 0 | N55: =IF(OR($A55="",'Project Overview'!P52="", 'Project Overview'!P52="?"),1,0) -> 0 | O55: =SUM(F55:N55) -> 0 | P55: =IF($A55="","",IF($O55=0,"OK","REVER")) -> OK
A56: =""&'Project Overview'!A53 -> 49 | B56: ='Project Overview'!B53 -> Vatel | C56: ='Project Overview'!C53 -> Vatel-Companhia De Produtos Alimentares S.A. | D56: ='Project Overview'!R53 -> ACTIVE | E56: ='Project Overview'!Y53 -> no | F56: =IF(AND($A56<>"",$B56=""),1,0) -> 0 | G56: =IF(AND($A56<>"",$C56=""),1,0) -> 0 | H56: =IF(AND($A56<>"",'Project Overview'!D53=""),1,0) -> 0 | I56: =IF(AND($A56<>"",'Project Overview'!F53=""),1,0) -> 0 | J56: =IF(AND($A56<>"",OR('Project Overview'!I53="ESCO",'Project Overview'!I53="EPC",'Project Overview'!I53="ESCO BUYOUT"),'Project Overview'!K53=""),1,0) -> 0 | K56: =IF(AND($A56<>"",'Project Overview'!M53=""),1,0) -> 0 | L56: =IF(AND($A56<>"",'Project Overview'!U53=""),1,0) -> 0 | M56: =IF(OR($A56="",'Project Overview'!O53="",'Project Overview'!O53="?"),1,0) -> 0 | N56: =IF(OR($A56="",'Project Overview'!P53="", 'Project Overview'!P53="?"),1,0) -> 0 | O56: =SUM(F56:N56) -> 0 | P56: =IF($A56="","",IF($O56=0,"OK","REVER")) -> OK
A57: =""&'Project Overview'!A54 -> 50 | B57: ='Project Overview'!B54 -> Tecnisata | C57: ='Project Overview'!C54 -> Tecnisata - Indústria Metalomecânica S.A. | D57: ='Project Overview'!R54 -> ACTIVE | E57: ='Project Overview'!Y54 -> yes | F57: =IF(OR($A57="",$B57=""),1,0) -> 0 | G57: =IF($C57="",1,0) -> 0 | H57: =IF(AND($A57<>"",'Project Overview'!D54=""),1,0) -> 0 | I57: =IF(AND($A57<>"",'Project Overview'!F54=""),1,0) -> 0 | J57: =IF(AND($A57<>"",OR('Project Overview'!I54="ESCO",'Project Overview'!I54="EPC",'Project Overview'!I54="ESCO BUYOUT"),'Project Overview'!K54=""),1,0) -> 0 | K57: =IF(AND($A57<>"",'Project Overview'!M54=""),1,0) -> 0 | L57: =IF(AND($A57<>"",'Project Overview'!U54=""),1,0) -> 0 | M57: =IF(OR($A57="",'Project Overview'!O54="",'Project Overview'!O54="?"),1,0) -> 0 | N57: =IF(OR($A57="",'Project Overview'!P54="", 'Project Overview'!P54="?"),1,0) -> 0 | O57: =SUM(F57:N57) -> 0 | P57: =IF($A57="","",IF($O57=0,"OK","REVER")) -> OK
A58: =""&'Project Overview'!A55 -> 51 | B58: ='Project Overview'!B55 -> Moviportas 1 - Sede | C58: ='Project Overview'!C55 -> Moviportas-Fábrica De Móveis E Portas De Rio De Couros Lda | D58: ='Project Overview'!R55 -> ACTIVE | E58: ='Project Overview'!Y55 -> no | F58: =IF(AND($A58<>"",$B58=""),1,0) -> 0 | G58: =IF(AND($A58<>"",$C58=""),1,0) -> 0 | H58: =IF(AND($A58<>"",'Project Overview'!D55=""),1,0) -> 0 | I58: =IF(AND($A58<>"",'Project Overview'!F55=""),1,0) -> 0 | J58: =IF(AND($A58<>"",OR('Project Overview'!I55="ESCO",'Project Overview'!I55="EPC",'Project Overview'!I55="ESCO BUYOUT"),'Project Overview'!K55=""),1,0) -> 0 | K58: =IF(AND($A58<>"",'Project Overview'!M55=""),1,0) -> 0 | L58: =IF(AND($A58<>"",'Project Overview'!U55=""),1,0) -> 0 | M58: =IF(OR($A58="",'Project Overview'!O55="",'Project Overview'!O55="?"),1,0) -> 0 | N58: =IF(OR($A58="",'Project Overview'!P55="", 'Project Overview'!P55="?"),1,0) -> 0 | O58: =SUM(F58:N58) -> 0 | P58: =IF($A58="","",IF($O58=0,"OK","REVER")) -> OK
A59: =""&'Project Overview'!A56 -> 52 | B59: ='Project Overview'!B56 -> Moviportas 2 | C59: ='Project Overview'!C56 -> Moviportas-Fábrica De Móveis E Portas De Rio De Couros Lda | D59: ='Project Overview'!R56 -> ACTIVE | E59: ='Project Overview'!Y56 -> no | F59: =IF(AND($A59<>"",$B59=""),1,0) -> 0 | G59: =IF(AND($A59<>"",$C59=""),1,0) -> 0 | H59: =IF(AND($A59<>"",'Project Overview'!D56=""),1,0) -> 0 | I59: =IF(AND($A59<>"",'Project Overview'!F56=""),1,0) -> 0 | J59: =IF(AND($A59<>"",OR('Project Overview'!I56="ESCO",'Project Overview'!I56="EPC",'Project Overview'!I56="ESCO BUYOUT"),'Project Overview'!K56=""),1,0) -> 0 | K59: =IF(AND($A59<>"",'Project Overview'!M56=""),1,0) -> 0 | L59: =IF(AND($A59<>"",'Project Overview'!U56=""),1,0) -> 0 | M59: =IF(OR($A59="",'Project Overview'!O56="",'Project Overview'!O56="?"),1,0) -> 0 | N59: =IF(OR($A59="",'Project Overview'!P56="", 'Project Overview'!P56="?"),1,0) -> 0 | O59: =SUM(F59:N59) -> 0 | P59: =IF($A59="","",IF($O59=0,"OK","REVER")) -> OK
A60: =""&'Project Overview'!A57 -> 53 | B60: ='Project Overview'!B57 -> Moviportas 3 - casa | C60: ='Project Overview'!C57 -> Moviportas-Fábrica De Móveis E Portas De Rio De Couros Lda | D60: ='Project Overview'!R57 -> ACTIVE | E60: ='Project Overview'!Y57 -> no | F60: =IF(AND($A60<>"",$B60=""),1,0) -> 0 | G60: =IF(AND($A60<>"",$C60=""),1,0) -> 0 | H60: =IF(AND($A60<>"",'Project Overview'!D57=""),1,0) -> 0 | I60: =IF(AND($A60<>"",'Project Overview'!F57=""),1,0) -> 0 | J60: =IF(AND($A60<>"",OR('Project Overview'!I57="ESCO",'Project Overview'!I57="EPC",'Project Overview'!I57="ESCO BUYOUT"),'Project Overview'!K57=""),1,0) -> 0 | K60: =IF(AND($A60<>"",'Project Overview'!M57=""),1,0) -> 0 | L60: =IF(AND($A60<>"",'Project Overview'!U57=""),1,0) -> 0 | M60: =IF(OR($A60="",'Project Overview'!O57="",'Project Overview'!O57="?"),1,0) -> 0 | N60: =IF(OR($A60="",'Project Overview'!P57="", 'Project Overview'!P57="?"),1,0) -> 0 | O60: =SUM(F60:N60) -> 0 | P60: =IF($A60="","",IF($O60=0,"OK","REVER")) -> OK
A61: =""&'Project Overview'!A58 -> 54 | B61: ='Project Overview'!B58 -> Homeupdate | C61: ='Project Overview'!C58 -> Homeupdate, Lda | D61: ='Project Overview'!R58 -> ACTIVE | E61: ='Project Overview'!Y58 -> yes | F61: =IF(OR($A61="",$B61=""),1,0) -> 0 | G61: =IF($C61="",1,0) -> 0 | H61: =IF(AND($A61<>"",'Project Overview'!D58=""),1,0) -> 0 | I61: =IF(AND($A61<>"",'Project Overview'!F58=""),1,0) -> 0 | J61: =IF(AND($A61<>"",OR('Project Overview'!I58="ESCO",'Project Overview'!I58="EPC",'Project Overview'!I58="ESCO BUYOUT"),'Project Overview'!K58=""),1,0) -> 0 | K61: =IF(AND($A61<>"",'Project Overview'!M58=""),1,0) -> 0 | L61: =IF(AND($A61<>"",'Project Overview'!U58=""),1,0) -> 0 | M61: =IF(OR($A61="",'Project Overview'!O58="",'Project Overview'!O58="?"),1,0) -> 0 | N61: =IF(OR($A61="",'Project Overview'!P58="", 'Project Overview'!P58="?"),1,0) -> 0 | O61: =SUM(F61:N61) -> 0 | P61: =IF($A61="","",IF($O61=0,"OK","REVER")) -> OK
A62: =""&'Project Overview'!A59 -> 55 | B62: ='Project Overview'!B59 -> ELS Guia | C62: ='Project Overview'!C59 -> Estevão Luis Salvador Lda | D62: ='Project Overview'!R59 -> ACTIVE | E62: ='Project Overview'!Y59 -> no | F62: =IF(AND($A62<>"",$B62=""),1,0) -> 0 | G62: =IF(AND($A62<>"",$C62=""),1,0) -> 0 | H62: =IF(AND($A62<>"",'Project Overview'!D59=""),1,0) -> 0 | I62: =IF(AND($A62<>"",'Project Overview'!F59=""),1,0) -> 0 | J62: =IF(AND($A62<>"",OR('Project Overview'!I59="ESCO",'Project Overview'!I59="EPC",'Project Overview'!I59="ESCO BUYOUT"),'Project Overview'!K59=""),1,0) -> 0 | K62: =IF(AND($A62<>"",'Project Overview'!M59=""),1,0) -> 0 | L62: =IF(AND($A62<>"",'Project Overview'!U59=""),1,0) -> 0 | M62: =IF(OR($A62="",'Project Overview'!O59="",'Project Overview'!O59="?"),1,0) -> 0 | N62: =IF(OR($A62="",'Project Overview'!P59="", 'Project Overview'!P59="?"),1,0) -> 0 | O62: =SUM(F62:N62) -> 0 | P62: =IF($A62="","",IF($O62=0,"OK","REVER")) -> OK
A63: =""&'Project Overview'!A60 -> 56 | B63: ='Project Overview'!B60 -> Dayton Progress | C63: ='Project Overview'!C60 -> Dayton Progress - Perfuradores, Lda | D63: ='Project Overview'!R60 -> ACTIVE | E63: ='Project Overview'!Y60 -> yes | F63: =IF(OR($A63="",$B63=""),1,0) -> 0 | G63: =IF($C63="",1,0) -> 0 | H63: =IF(AND($A63<>"",'Project Overview'!D60=""),1,0) -> 0 | I63: =IF(AND($A63<>"",'Project Overview'!F60=""),1,0) -> 0 | J63: =IF(AND($A63<>"",OR('Project Overview'!I60="ESCO",'Project Overview'!I60="EPC",'Project Overview'!I60="ESCO BUYOUT"),'Project Overview'!K60=""),1,0) -> 0 | K63: =IF(AND($A63<>"",'Project Overview'!M60=""),1,0) -> 0 | L63: =IF(AND($A63<>"",'Project Overview'!U60=""),1,0) -> 0 | M63: =IF(OR($A63="",'Project Overview'!O60="",'Project Overview'!O60="?"),1,0) -> 0 | N63: =IF(OR($A63="",'Project Overview'!P60="", 'Project Overview'!P60="?"),1,0) -> 0 | O63: =SUM(F63:N63) -> 0 | P63: =IF($A63="","",IF($O63=0,"OK","REVER")) -> OK
A64: =""&'Project Overview'!A61 -> 57 | B64: ='Project Overview'!B61 -> RAP Industrial | C64: ='Project Overview'!C61 -> Rap - Industrial Lda | D64: ='Project Overview'!R61 -> ACTIVE | E64: ='Project Overview'!Y61 -> yes | F64: =IF(OR($A64="",$B64=""),1,0) -> 0 | G64: =IF($C64="",1,0) -> 0 | H64: =IF(AND($A64<>"",'Project Overview'!D61=""),1,0) -> 0 | I64: =IF(AND($A64<>"",'Project Overview'!F61=""),1,0) -> 0 | J64: =IF(AND($A64<>"",OR('Project Overview'!I61="ESCO",'Project Overview'!I61="EPC",'Project Overview'!I61="ESCO BUYOUT"),'Project Overview'!K61=""),1,0) -> 0 | K64: =IF(AND($A64<>"",'Project Overview'!M61=""),1,0) -> 0 | L64: =IF(AND($A64<>"",'Project Overview'!U61=""),1,0) -> 0 | M64: =IF(OR($A64="",'Project Overview'!O61="",'Project Overview'!O61="?"),1,0) -> 0 | N64: =IF(OR($A64="",'Project Overview'!P61="", 'Project Overview'!P61="?"),1,0) -> 0 | O64: =SUM(F64:N64) -> 0 | P64: =IF($A64="","",IF($O64=0,"OK","REVER")) -> OK
A65: =""&'Project Overview'!A62 -> 58 | B65: ='Project Overview'!B62 -> DRA Detergentes | C65: ='Project Overview'!C62 -> 0 | D65: ='Project Overview'!R62 -> CANCELLED | E65: ='Project Overview'!Y62 -> no | F65: =IF(AND($A65<>"",$B65=""),1,0) -> 0 | G65: =IF(AND($A65<>"",$C65=""),1,0) -> 0 | H65: =IF(AND($A65<>"",'Project Overview'!D62=""),1,0) -> 1 | I65: =IF(AND($A65<>"",'Project Overview'!F62=""),1,0) -> 1 | J65: =IF(AND($A65<>"",OR('Project Overview'!I62="ESCO",'Project Overview'!I62="EPC",'Project Overview'!I62="ESCO BUYOUT"),'Project Overview'!K62=""),1,0) -> 1 | K65: =IF(AND($A65<>"",'Project Overview'!M62=""),1,0) -> 1 | L65: =IF(AND($A65<>"",'Project Overview'!U62=""),1,0) -> 1 | M65: =IF(OR($A65="",'Project Overview'!O62="",'Project Overview'!O62="?"),1,0) -> 1 | N65: =IF(OR($A65="",'Project Overview'!P62="", 'Project Overview'!P62="?"),1,0) -> 1 | O65: =SUM(F65:N65) -> 7 | P65: =IF($A65="","",IF($O65=0,"OK","REVER")) -> REVER
A66: =""&'Project Overview'!A63 -> 59 | B66: ='Project Overview'!B63 -> Corkplas Armazém 21 | C66: ='Project Overview'!C63 -> Corkplas - Indústria De Transformação E Comércio De Plásticos E Derivados De Cortiça Lda | D66: ='Project Overview'!R63 -> ACTIVE | E66: ='Project Overview'!Y63 -> no | F66: =IF(AND($A66<>"",$B66=""),1,0) -> 0 | G66: =IF(AND($A66<>"",$C66=""),1,0) -> 0 | H66: =IF(AND($A66<>"",'Project Overview'!D63=""),1,0) -> 0 | I66: =IF(AND($A66<>"",'Project Overview'!F63=""),1,0) -> 0 | J66: =IF(AND($A66<>"",OR('Project Overview'!I63="ESCO",'Project Overview'!I63="EPC",'Project Overview'!I63="ESCO BUYOUT"),'Project Overview'!K63=""),1,0) -> 0 | K66: =IF(AND($A66<>"",'Project Overview'!M63=""),1,0) -> 0 | L66: =IF(AND($A66<>"",'Project Overview'!U63=""),1,0) -> 1 | M66: =IF(OR($A66="",'Project Overview'!O63="",'Project Overview'!O63="?"),1,0) -> 0 | N66: =IF(OR($A66="",'Project Overview'!P63="", 'Project Overview'!P63="?"),1,0) -> 0 | O66: =SUM(F66:N66) -> 1 | P66: =IF($A66="","",IF($O66=0,"OK","REVER")) -> REVER
A67: =""&'Project Overview'!A64 -> 60 | B67: ='Project Overview'!B64 -> Corkplas Armazém 13 | C67: ='Project Overview'!C64 -> Corkplas - Indústria De Transformação E Comércio De Plásticos E Derivados De Cortiça Lda | D67: ='Project Overview'!R64 -> ACTIVE | E67: ='Project Overview'!Y64 -> no | F67: =IF(AND($A67<>"",$B67=""),1,0) -> 0 | G67: =IF(AND($A67<>"",$C67=""),1,0) -> 0 | H67: =IF(AND($A67<>"",'Project Overview'!D64=""),1,0) -> 0 | I67: =IF(AND($A67<>"",'Project Overview'!F64=""),1,0) -> 0 | J67: =IF(AND($A67<>"",OR('Project Overview'!I64="ESCO",'Project Overview'!I64="EPC",'Project Overview'!I64="ESCO BUYOUT"),'Project Overview'!K64=""),1,0) -> 0 | K67: =IF(AND($A67<>"",'Project Overview'!M64=""),1,0) -> 0 | L67: =IF(AND($A67<>"",'Project Overview'!U64=""),1,0) -> 1 | M67: =IF(OR($A67="",'Project Overview'!O64="",'Project Overview'!O64="?"),1,0) -> 0 | N67: =IF(OR($A67="",'Project Overview'!P64="", 'Project Overview'!P64="?"),1,0) -> 0 | O67: =SUM(F67:N67) -> 1 | P67: =IF($A67="","",IF($O67=0,"OK","REVER")) -> REVER
A68: =""&'Project Overview'!A65 -> 61 | B68: ='Project Overview'!B65 -> Jeteprodesing | C68: ='Project Overview'!C65 -> Jeteprodesign, Lda | D68: ='Project Overview'!R65 -> ON HOLD | E68: ='Project Overview'!Y65 -> no | F68: =IF(AND($A68<>"",$B68=""),1,0) -> 0 | G68: =IF(AND($A68<>"",$C68=""),1,0) -> 0 | H68: =IF(AND($A68<>"",'Project Overview'!D65=""),1,0) -> 0 | I68: =IF(AND($A68<>"",'Project Overview'!F65=""),1,0) -> 1 | J68: =IF(AND($A68<>"",OR('Project Overview'!I65="ESCO",'Project Overview'!I65="EPC",'Project Overview'!I65="ESCO BUYOUT"),'Project Overview'!K65=""),1,0) -> 0 | K68: =IF(AND($A68<>"",'Project Overview'!M65=""),1,0) -> 1 | L68: =IF(AND($A68<>"",'Project Overview'!U65=""),1,0) -> 0 | M68: =IF(OR($A68="",'Project Overview'!O65="",'Project Overview'!O65="?"),1,0) -> 1 | N68: =IF(OR($A68="",'Project Overview'!P65="", 'Project Overview'!P65="?"),1,0) -> 1 | O68: =SUM(F68:N68) -> 4 | P68: =IF($A68="","",IF($O68=0,"OK","REVER")) -> REVER
A69: =""&'Project Overview'!A66 -> 62 | B69: ='Project Overview'!B66 -> BV Arruda dos Vinhos | C69: ='Project Overview'!C66 -> Associação Dos Bombeiros Voluntarios De Arruda Dos Vinhos | D69: ='Project Overview'!R66 -> ACTIVE | E69: ='Project Overview'!Y66 -> yes | F69: =IF(OR($A69="",$B69=""),1,0) -> 0 | G69: =IF($C69="",1,0) -> 0 | H69: =IF(AND($A69<>"",'Project Overview'!D66=""),1,0) -> 0 | I69: =IF(AND($A69<>"",'Project Overview'!F66=""),1,0) -> 0 | J69: =IF(AND($A69<>"",OR('Project Overview'!I66="ESCO",'Project Overview'!I66="EPC",'Project Overview'!I66="ESCO BUYOUT"),'Project Overview'!K66=""),1,0) -> 0 | K69: =IF(AND($A69<>"",'Project Overview'!M66=""),1,0) -> 0 | L69: =IF(AND($A69<>"",'Project Overview'!U66=""),1,0) -> 0 | M69: =IF(OR($A69="",'Project Overview'!O66="",'Project Overview'!O66="?"),1,0) -> 0 | N69: =IF(OR($A69="",'Project Overview'!P66="", 'Project Overview'!P66="?"),1,0) -> 0 | O69: =SUM(F69:N69) -> 0 | P69: =IF($A69="","",IF($O69=0,"OK","REVER")) -> OK
A70: =""&'Project Overview'!A67 -> 63 | B70: ='Project Overview'!B67 -> Encontrus | C70: ='Project Overview'!C67 -> Encontrus-Sociedade Hoteleira Lda | D70: ='Project Overview'!R67 -> ACTIVE | E70: ='Project Overview'!Y67 -> yes | F70: =IF(OR($A70="",$B70=""),1,0) -> 0 | G70: =IF($C70="",1,0) -> 0 | H70: =IF(AND($A70<>"",'Project Overview'!D67=""),1,0) -> 0 | I70: =IF(AND($A70<>"",'Project Overview'!F67=""),1,0) -> 0 | J70: =IF(AND($A70<>"",OR('Project Overview'!I67="ESCO",'Project Overview'!I67="EPC",'Project Overview'!I67="ESCO BUYOUT"),'Project Overview'!K67=""),1,0) -> 0 | K70: =IF(AND($A70<>"",'Project Overview'!M67=""),1,0) -> 0 | L70: =IF(AND($A70<>"",'Project Overview'!U67=""),1,0) -> 0 | M70: =IF(OR($A70="",'Project Overview'!O67="",'Project Overview'!O67="?"),1,0) -> 0 | N70: =IF(OR($A70="",'Project Overview'!P67="", 'Project Overview'!P67="?"),1,0) -> 0 | O70: =SUM(F70:N70) -> 0 | P70: =IF($A70="","",IF($O70=0,"OK","REVER")) -> OK
A71: =""&'Project Overview'!A68 -> 64 | B71: ='Project Overview'!B68 -> Licofrutos | C71: ='Project Overview'!C68 -> Licofrutos, Unipessoal Lda | D71: ='Project Overview'!R68 -> ACTIVE | E71: ='Project Overview'!Y68 -> yes | F71: =IF(OR($A71="",$B71=""),1,0) -> 0 | G71: =IF($C71="",1,0) -> 0 | H71: =IF(AND($A71<>"",'Project Overview'!D68=""),1,0) -> 0 | I71: =IF(AND($A71<>"",'Project Overview'!F68=""),1,0) -> 0 | J71: =IF(AND($A71<>"",OR('Project Overview'!I68="ESCO",'Project Overview'!I68="EPC",'Project Overview'!I68="ESCO BUYOUT"),'Project Overview'!K68=""),1,0) -> 0 | K71: =IF(AND($A71<>"",'Project Overview'!M68=""),1,0) -> 0 | L71: =IF(AND($A71<>"",'Project Overview'!U68=""),1,0) -> 0 | M71: =IF(OR($A71="",'Project Overview'!O68="",'Project Overview'!O68="?"),1,0) -> 0 | N71: =IF(OR($A71="",'Project Overview'!P68="", 'Project Overview'!P68="?"),1,0) -> 0 | O71: =SUM(F71:N71) -> 0 | P71: =IF($A71="","",IF($O71=0,"OK","REVER")) -> OK
A72: =""&'Project Overview'!A69 -> 65 | B72: ='Project Overview'!B69 -> Pancrisp | C72: ='Project Overview'!C69 -> Pancrisp-Industria De Panificação Lda | D72: ='Project Overview'!R69 -> ACTIVE | E72: ='Project Overview'!Y69 -> yes | F72: =IF(OR($A72="",$B72=""),1,0) -> 0 | G72: =IF($C72="",1,0) -> 0 | H72: =IF(AND($A72<>"",'Project Overview'!D69=""),1,0) -> 0 | I72: =IF(AND($A72<>"",'Project Overview'!F69=""),1,0) -> 0 | J72: =IF(AND($A72<>"",OR('Project Overview'!I69="ESCO",'Project Overview'!I69="EPC",'Project Overview'!I69="ESCO BUYOUT"),'Project Overview'!K69=""),1,0) -> 0 | K72: =IF(AND($A72<>"",'Project Overview'!M69=""),1,0) -> 0 | L72: =IF(AND($A72<>"",'Project Overview'!U69=""),1,0) -> 0 | M72: =IF(OR($A72="",'Project Overview'!O69="",'Project Overview'!O69="?"),1,0) -> 0 | N72: =IF(OR($A72="",'Project Overview'!P69="", 'Project Overview'!P69="?"),1,0) -> 0 | O72: =SUM(F72:N72) -> 0 | P72: =IF($A72="","",IF($O72=0,"OK","REVER")) -> OK
A73: =""&'Project Overview'!A70 -> 66 | B73: ='Project Overview'!B70 -> Barbotina | C73: ='Project Overview'!C70 -> Barbotina-Fábrica de Artigos Cerâmicos S.A | D73: ='Project Overview'!R70 -> CANCELLED | E73: ='Project Overview'!Y70 -> no | F73: =IF(AND($A73<>"",$B73=""),1,0) -> 0 | G73: =IF(AND($A73<>"",$C73=""),1,0) -> 0 | H73: =IF(AND($A73<>"",'Project Overview'!D70=""),1,0) -> 0 | I73: =IF(AND($A73<>"",'Project Overview'!F70=""),1,0) -> 1 | J73: =IF(AND($A73<>"",OR('Project Overview'!I70="ESCO",'Project Overview'!I70="EPC",'Project Overview'!I70="ESCO BUYOUT"),'Project Overview'!K70=""),1,0) -> 0 | K73: =IF(AND($A73<>"",'Project Overview'!M70=""),1,0) -> 1 | L73: =IF(AND($A73<>"",'Project Overview'!U70=""),1,0) -> 0 | M73: =IF(OR($A73="",'Project Overview'!O70="",'Project Overview'!O70="?"),1,0) -> 1 | N73: =IF(OR($A73="",'Project Overview'!P70="", 'Project Overview'!P70="?"),1,0) -> 1 | O73: =SUM(F73:N73) -> 4 | P73: =IF($A73="","",IF($O73=0,"OK","REVER")) -> REVER
A74: =""&'Project Overview'!A71 -> 67 | B74: ='Project Overview'!B71 -> ITECMO | C74: ='Project Overview'!C71 -> Itecmo - Indústria De Fabricação De Moldes Lda | D74: ='Project Overview'!R71 -> ACTIVE | E74: ='Project Overview'!Y71 -> yes | F74: =IF(OR($A74="",$B74=""),1,0) -> 0 | G74: =IF($C74="",1,0) -> 0 | H74: =IF(AND($A74<>"",'Project Overview'!D71=""),1,0) -> 0 | I74: =IF(AND($A74<>"",'Project Overview'!F71=""),1,0) -> 0 | J74: =IF(AND($A74<>"",OR('Project Overview'!I71="ESCO",'Project Overview'!I71="EPC",'Project Overview'!I71="ESCO BUYOUT"),'Project Overview'!K71=""),1,0) -> 0 | K74: =IF(AND($A74<>"",'Project Overview'!M71=""),1,0) -> 0 | L74: =IF(AND($A74<>"",'Project Overview'!U71=""),1,0) -> 0 | M74: =IF(OR($A74="",'Project Overview'!O71="",'Project Overview'!O71="?"),1,0) -> 0 | N74: =IF(OR($A74="",'Project Overview'!P71="", 'Project Overview'!P71="?"),1,0) -> 0 | O74: =SUM(F74:N74) -> 0 | P74: =IF($A74="","",IF($O74=0,"OK","REVER")) -> OK
A75: =""&'Project Overview'!A72 -> 68 | B75: ='Project Overview'!B72 -> Real Sport Clube | C75: ='Project Overview'!C72 -> Real Sport Clube | D75: ='Project Overview'!R72 -> ACTIVE | E75: ='Project Overview'!Y72 -> yes | F75: =IF(OR($A75="",$B75=""),1,0) -> 0 | G75: =IF($C75="",1,0) -> 0 | H75: =IF(AND($A75<>"",'Project Overview'!D72=""),1,0) -> 0 | I75: =IF(AND($A75<>"",'Project Overview'!F72=""),1,0) -> 0 | J75: =IF(AND($A75<>"",OR('Project Overview'!I72="ESCO",'Project Overview'!I72="EPC",'Project Overview'!I72="ESCO BUYOUT"),'Project Overview'!K72=""),1,0) -> 0 | K75: =IF(AND($A75<>"",'Project Overview'!M72=""),1,0) -> 0 | L75: =IF(AND($A75<>"",'Project Overview'!U72=""),1,0) -> 0 | M75: =IF(OR($A75="",'Project Overview'!O72="",'Project Overview'!O72="?"),1,0) -> 0 | N75: =IF(OR($A75="",'Project Overview'!P72="", 'Project Overview'!P72="?"),1,0) -> 0 | O75: =SUM(F75:N75) -> 0 | P75: =IF($A75="","",IF($O75=0,"OK","REVER")) -> OK
